Workbook
Name Alarm: options!$A$2:$A$3
Name BILLINGFREQ: [1]Tables!$C$1:$C$7
Name Customers: '[1]Customer Table'!$B$1:$B$1116
Name JOBTYPES: [1]Tables!$O$1:$O$6
Name SALESPERSON: [1]Tables!$E$1:$E$21

Sheet Totals
B1: ESTIMATING SHEET VERSION 8.6 | G1: Salesman: | I1: 40 VA | L1: Add Date Below
B2: Job Name: | G2: Estimator:
B3: Part Number | D3: QTY. | E3: MATERIAL DESCRIPTON | H3: LIST $ | J3: # of Contrs | K3: # of Points | M3: TOTAL | R3: Electrical Price Check | V3: Tech | Z3: Graphics | AD3: Programming
Q5: TOTAL | R5: ='Base Estimate'!R482+'Estimate 2'!R482+'Estimate 3'!R482+'Estimate 4'!R482+'Estimate 5'!R482+'Estimate 6'!R482+'Estimate 7'!R482+'Estimate 8'!R482+'Estimate 9'!R482+'Estimate 10'!R482 -> 0 | S5: Install | V5: ='Base Estimate'!V482+'Estimate 2'!V482+'Estimate 3'!V482+'Estimate 4'!V482+'Estimate 5'!V482+'Estimate 6'!V482+'Estimate 7'!V482+'Estimate 8'!V482+'Estimate 9'!V482+'Estimate 10'!V482 -> 0 | W5: Tech Hours | Z5: ='Base Estimate'!Z482+'Estimate 2'!Z482+'Estimate 3'!Z482+'Estimate 4'!Z482+'Estimate 5'!Z482+'Estimate 6'!Z482+'Estimate 7'!Z482+'Estimate 8'!Z482+'Estimate 9'!Z482+'Estimate 10'!Z482 -> 0 | AA5: Graphic Hours | AD5: ='Base Estimate'!AD482+'Estimate 2'!AD482+'Estimate 3'!AD482+'Estimate 4'!AD482+'Estimate 5'!AD482+'Estimate 6'!AD482+'Estimate 7'!AD482+'Estimate 8'!AD482+'Estimate 9'!AD482+'Estimate 10'!AD482 -> 0 | AE5: Programming Hours
J6: =D5+D7 -> 0 | K6: =J6*50 -> 0
R7: ='Base Estimate'!R484+'Estimate 2'!R484+'Estimate 3'!R484+'Estimate 4'!R484+'Estimate 5'!R484+'Estimate 6'!R484+'Estimate 7'!R484+'Estimate 8'!R484+'Estimate 9'!R484+'Estimate 10'!R484 -> 0 | S7: ='Base Estimate'!S484 -> 0
I8: SUB TOTAL | J8: ='Base Estimate'!J485+'Estimate 2'!J485+'Estimate 3'!J485+'Estimate 4'!J485+'Estimate 5'!J485+'Estimate 6'!J485+'Estimate 7'!J485+'Estimate 8'!J485+'Estimate 9'!J485+'Estimate 10'!J485 -> 0 | M8: ='Base Estimate'!M485+'Estimate 2'!M485+'Estimate 3'!M485+'Estimate 4'!M485+'Estimate 5'!M485+'Estimate 6'!M485+'Estimate 7'!M485+'Estimate 8'!M485+'Estimate 9'!M485+'Estimate 10'!M485 -> 0 | R8: ='Base Estimate'!R485+'Estimate 2'!R485+'Estimate 3'!R485+'Estimate 4'!R485+'Estimate 5'!R485+'Estimate 6'!R485+'Estimate 7'!R485+'Estimate 8'!R485+'Estimate 9'!R485+'Estimate 10'!R485 -> 0 | S8: ='Base Estimate'!S485 -> 0
I9: TAX | J9: ='Base Estimate'!J486+'Estimate 2'!J486+'Estimate 3'!J486+'Estimate 4'!J486+'Estimate 5'!J486+'Estimate 6'!J486+'Estimate 7'!J486+'Estimate 8'!J486+'Estimate 9'!J486+'Estimate 10'!J486 -> 0 | L9: ='Base Estimate'!L486 -> 0.0825 | M9: ='Base Estimate'!M486+'Estimate 2'!M486+'Estimate 3'!M486+'Estimate 4'!M486+'Estimate 5'!M486+'Estimate 6'!M486+'Estimate 7'!M486+'Estimate 8'!M486+'Estimate 9'!M486+'Estimate 10'!M486 -> 0 | R9: ='Base Estimate'!R486+'Estimate 2'!R486+'Estimate 3'!R486+'Estimate 4'!R486+'Estimate 5'!R486+'Estimate 6'!R486+'Estimate 7'!R486+'Estimate 8'!R486+'Estimate 9'!R486+'Estimate 10'!R486 -> 0 | S9: ='Base Estimate'!S486 -> 0
I10: FREIGHT | J10: ='Base Estimate'!J487+'Estimate 2'!J487+'Estimate 3'!J487+'Estimate 4'!J487+'Estimate 5'!J487+'Estimate 6'!J487+'Estimate 7'!J487+'Estimate 8'!J487+'Estimate 9'!J487+'Estimate 10'!J487 -> 0 | L10: 0.07 | M10: ='Base Estimate'!M487+'Estimate 2'!M487+'Estimate 3'!M487+'Estimate 4'!M487+'Estimate 5'!M487+'Estimate 6'!M487+'Estimate 7'!M487+'Estimate 8'!M487+'Estimate 9'!M487+'Estimate 10'!M487 -> 0 | R10: ='Base Estimate'!R487+'Estimate 2'!R487+'Estimate 3'!R487+'Estimate 4'!R487+'Estimate 5'!R487+'Estimate 6'!R487+'Estimate 7'!R487+'Estimate 8'!R487+'Estimate 9'!R487+'Estimate 10'!R487 -> 0 | S10: ='Base Estimate'!S487 -> 0
I11: TOTAL W/TAX | J11: ='Base Estimate'!J488+'Estimate 2'!J488+'Estimate 3'!J488+'Estimate 4'!J488+'Estimate 5'!J488+'Estimate 6'!J488+'Estimate 7'!J488+'Estimate 8'!J488+'Estimate 9'!J488+'Estimate 10'!J488 -> 0 | M11: ='Base Estimate'!M488+'Estimate 2'!M488+'Estimate 3'!M488+'Estimate 4'!M488+'Estimate 5'!M488+'Estimate 6'!M488+'Estimate 7'!M488+'Estimate 8'!M488+'Estimate 9'!M488+'Estimate 10'!M488 -> 0 | R11: {=MIN(IF(R7:R10>0,R7:R10))} -> 0
R12: =((R5-R13)/G23)*0.833 -> 0 | S12: Comparative labor hours @ burden rate based on the Total cost above
R13: =ROUND((R5*0.15)/1.1125,0) -> 0 | S13: This is 15% of the Total install dollars above to be used in no sub is chosen
B14: HOURS - CAL | C14: HOURS - ACT | D14: TITLE | G14: COST/HR | H14: TOTAL
B15: =ROUND(V32,0) -> 0 | C15: ='Base Estimate'!A492+'Estimate 2'!A492+'Estimate 3'!A492+'Estimate 4'!A492+'Estimate 5'!A492+'Estimate 6'!A492+'Estimate 7'!A492+'Estimate 8'!A492+'Estimate 9'!A492+'Estimate 10'!A492 -> 0 | D15: TECH PROGRAMMING | G15: 74 | H15: =C15*G15 -> 0 | J15: =H15 -> 0 | Q15: Tech, Engineering and PM Hours | X15: Travel Expenses | AD15: Parking Cost - Tech + Install
B16: =V31 -> 0 | C16: ='Base Estimate'!A493+'Estimate 2'!A493+'Estimate 3'!A493+'Estimate 4'!A493+'Estimate 5'!A493+'Estimate 6'!A493+'Estimate 7'!A493+'Estimate 8'!A493+'Estimate 9'!A493+'Estimate 10'!A493 -> 0 | D16: SENIOR TECHNICAL PROGRAMMING | G16: 101 | H16: =C16*G16 -> 0 | J16: =H16 -> 0
B17: =ROUND(V19,0) -> 0 | C17: ='Base Estimate'!A494+'Estimate 2'!A494+'Estimate 3'!A494+'Estimate 4'!A494+'Estimate 5'!A494+'Estimate 6'!A494+'Estimate 7'!A494+'Estimate 8'!A494+'Estimate 9'!A494+'Estimate 10'!A494 -> 0 | D17: GRAPHICS | G17: 74 | H17: =C17*G17 -> 0 | J17: =H17 -> 0 | Q17: Tech Training Hours | V17: ='Base Estimate'!V495+'Estimate 2'!V495+'Estimate 3'!V495+'Estimate 4'!V495+'Estimate 5'!V495+'Estimate 6'!V495+'Estimate 7'!V495+'Estimate 8'!V495+'Estimate 9'!V495+'Estimate 10'!V495 -> 0 | X17: Tech/Install Hotel | AA17: 0 | AD17: Cost Per Day | AG17: 0
B18: =V35 -> 0 | C18: ='Base Estimate'!A495+'Estimate 2'!A495+'Estimate 3'!A495+'Estimate 4'!A495+'Estimate 5'!A495+'Estimate 6'!A495+'Estimate 7'!A495+'Estimate 8'!A495+'Estimate 9'!A495+'Estimate 10'!A495 -> 0 | D18: ENGINEERING | G18: 102 | H18: =C18*G18 -> 0 | J18: =H18 -> 0 | N18: =C19+C17+C16+C15 -> 0 | O18: Tech+Graphics
B19: =V29 -> 0 | C19: ='Base Estimate'!A496+'Estimate 2'!A496+'Estimate 3'!A496+'Estimate 4'!A496+'Estimate 5'!A496+'Estimate 6'!A496+'Estimate 7'!A496+'Estimate 8'!A496+'Estimate 9'!A496+'Estimate 10'!A496 -> 0 | D19: TECHNICAL | G19: 74 | H19: =C19*G19 -> 0 | J19: =H19 -> 0 | O19: Programming | Q19: Graphics Hours | V19: =Z5 -> 0 | X19: Tech/Install Per Diem | AA19: 0 | AD19: Days Parked | AG19: =ROUNDUP((((V5+V17+V21+V23+C23)/40)*5),0) -> 0
B20: =ROUND(V38,0) -> 0 | C20: ='Base Estimate'!A497+'Estimate 2'!A497+'Estimate 3'!A497+'Estimate 4'!A497+'Estimate 5'!A497+'Estimate 6'!A497+'Estimate 7'!A497+'Estimate 8'!A497+'Estimate 9'!A497+'Estimate 10'!A497 -> 0 | D20: SENIOR PROJECT MANAGER | G20: 134 | H20: =C20*G20 -> 0 | J20: =H20 -> 0
B21: =ROUND(V39,0) -> 0 | C21: ='Base Estimate'!A498+'Estimate 2'!A498+'Estimate 3'!A498+'Estimate 4'!A498+'Estimate 5'!A498+'Estimate 6'!A498+'Estimate 7'!A498+'Estimate 8'!A498+'Estimate 9'!A498+'Estimate 10'!A498 -> 0 | D21: ASSISTANT PROJECT MANAGER | G21: 75 | H21: =C21*G21 -> 0 | J21: =H21 -> 0 | Q21: Add Tech Comm,Travel, TAB Hrs | V21: ='Base Estimate'!V499+'Estimate 2'!V499+'Estimate 3'!V499+'Estimate 4'!V499+'Estimate 5'!V499+'Estimate 6'!V499+'Estimate 7'!V499+'Estimate 8'!V499+'Estimate 9'!V499+'Estimate 10'!V499 -> 0 | X21: Tech/Install Days | AA21: =ROUNDUP((((V5+V17+V21+V23+V25+C23)/40)*5),0) -> 0
C22: ='Base Estimate'!C499+'Estimate 2'!C499+'Estimate 3'!C499+'Estimate 4'!C499+'Estimate 5'!C499+'Estimate 6'!C499+'Estimate 7'!C499+'Estimate 8'!C499+'Estimate 9'!C499+'Estimate 10'!C499 -> 0 | D22: ELECTRICAL ASSISTANT - Panel Building | G22: 58 | H22: =C22*G22 -> 0 | J22: =H22 -> 0 | X22: Out of Town | AD22: Total Parking Cost | AG22: ='Base Estimate'!AG500+'Estimate 2'!AG499+'Estimate 3'!AG499+'Estimate 4'!AG499+'Estimate 5'!AG499+'Estimate 6'!AG499+'Estimate 7'!AG499+'Estimate 8'!AG499+'Estimate 9'!AG499+'Estimate 10'!AG499 -> 0
C23: ='Base Estimate'!C500+'Estimate 2'!C500+'Estimate 3'!C500+'Estimate 4'!C500+'Estimate 5'!C500+'Estimate 6'!C500+'Estimate 7'!C500+'Estimate 8'!C500+'Estimate 9'!C500+'Estimate 10'!C500 -> 0 | D23: ELECTRICAL INSTALLER | G23: 58 | H23: =C23*G23 -> 0 | J23: =H23 -> 0 | Q23: Add Phasing, High Rise, etc | V23: ='Base Estimate'!V501+'Estimate 2'!V501+'Estimate 3'!V501+'Estimate 4'!V501+'Estimate 5'!V501+'Estimate 6'!V501+'Estimate 7'!V501+'Estimate 8'!V501+'Estimate 9'!V501+'Estimate 10'!V501 -> 0
D24: TOTAL LABOR COST | H24: =SUM(H15:H23) -> 0 | I24: =IFERROR((M24-H24)/(M24),0.32) -> 0.32 | J24: =SUM(J15:J23) -> 0 | M24: ='Base Estimate'!M501+'Estimate 2'!M501+'Estimate 3'!M501+'Estimate 4'!M501+'Estimate 5'!M501+'Estimate 6'!M501+'Estimate 7'!M501+'Estimate 8'!M501+'Estimate 9'!M501+'Estimate 10'!M501 -> 0 | N24: =IFERROR(H24/H35,"0") -> 0 | O24: MTC w Local Labor | X24: Tech/Install Travel | AA24: ='Base Estimate'!AA502+'Estimate 2'!AA501+'Estimate 3'!AA501+'Estimate 4'!AA501+'Estimate 5'!AA501+'Estimate 6'!AA501+'Estimate 7'!AA501+'Estimate 8'!AA501+'Estimate 9'!AA501+'Estimate 10'!AA501 -> 0
Q25: Add Tech Travel Time | V25: ='Base Estimate'!V503+'Estimate 2'!V503+'Estimate 3'!V503+'Estimate 4'!V503+'Estimate 5'!V503+'Estimate 6'!V503+'Estimate 7'!V503+'Estimate 8'!V503+'Estimate 9'!V503+'Estimate 10'!V503 -> 0 | X25: Cost
D26: MATERIALS & TRIP | N26: =IFERROR(J24/J35,"0") -> 0 | O26: MTC w Sub Labor | Q26: Estimated travel time to site = | T26: 0 | U26: hrs
D27: MILEAGE - ROUND TRIP | G27: 100 | H27: ='Base Estimate'!H504+'Estimate 2'!H504+'Estimate 3'!H504+'Estimate 4'!H504+'Estimate 5'!H504+'Estimate 6'!H504+'Estimate 7'!H504+'Estimate 8'!H504+'Estimate 9'!H504+'Estimate 10'!H504 -> 0 | I27: =IFERROR((M27-H27)/(M27),0.32) -> 0.32 | J27: =IF(G27<=100,(C18+(C20/3))/8*(50),IF(G27>100,(C18+ (C20/3))/8*(G27)*0.5)) -> 0 | M27: ='Base Estimate'!M504+'Estimate 2'!M504+'Estimate 3'!M504+'Estimate 4'!M504+'Estimate 5'!M504+'Estimate 6'!M504+'Estimate 7'!M504+'Estimate 8'!M504+'Estimate 9'!M504+'Estimate 10'!M504 -> 0 | AD27: Mechanical Labor
D28: MATERIALS | H28: ='Base Estimate'!H505+'Estimate 2'!H505+'Estimate 3'!H505+'Estimate 4'!H505+'Estimate 5'!H505+'Estimate 6'!H505+'Estimate 7'!H505+'Estimate 8'!H505+'Estimate 9'!H505+'Estimate 10'!H505 -> 0 | I28: =IFERROR((M28-H28)/(M28),0.32) -> 0.32 | J28: =J11 -> 0 | M28: ='Base Estimate'!M505+'Estimate 2'!M505+'Estimate 3'!M505+'Estimate 4'!M505+'Estimate 5'!M505+'Estimate 6'!M505+'Estimate 7'!M505+'Estimate 8'!M505+'Estimate 9'!M505+'Estimate 10'!M505 -> 0
D29: SUB | H29: ='Base Estimate'!H506+'Estimate 2'!H506+'Estimate 3'!H506+'Estimate 4'!H506+'Estimate 5'!H506+'Estimate 6'!H506+'Estimate 7'!H506+'Estimate 8'!H506+'Estimate 9'!H506+'Estimate 10'!H506 -> 0 | I29: =IFERROR((M29-H29)/(M29),0.32) -> 0.32 | J29: =R5 -> 0 | M29: ='Base Estimate'!M506+'Estimate 2'!M506+'Estimate 3'!M506+'Estimate 4'!M506+'Estimate 5'!M506+'Estimate 6'!M506+'Estimate 7'!M506+'Estimate 8'!M506+'Estimate 9'!M506+'Estimate 10'!M506 -> 0 | Q29: Total Tech Hours (Less Graphics) | V29: =V5+V17+V21+V23+V25 -> 0 | X29: PM Hotel | AA29: 0 | AD29: Total Mechanical Labor | AG29: ='Base Estimate'!AG508+'Estimate 2'!AG506+'Estimate 3'!AG506+'Estimate 4'!AG506+'Estimate 5'!AG506+'Estimate 6'!AG506+'Estimate 7'!AG506+'Estimate 8'!AG506+'Estimate 9'!AG506+'Estimate 10'!AG506 -> 0
D30: INTEGRATION/CONTINENCY/OTHER | H30: ='Base Estimate'!H507+'Estimate 2'!H507+'Estimate 3'!H507+'Estimate 4'!H507+'Estimate 5'!H507+'Estimate 6'!H507+'Estimate 7'!H507+'Estimate 8'!H507+'Estimate 9'!H507+'Estimate 10'!H507 -> 0 | I30: =IFERROR((M30-H30)/(M30),0.32) -> 0.32 | J30: =H30 -> 0 | M30: ='Base Estimate'!M507+'Estimate 2'!M507+'Estimate 3'!M507+'Estimate 4'!M507+'Estimate 5'!M507+'Estimate 6'!M507+'Estimate 7'!M507+'Estimate 8'!M507+'Estimate 9'!M507+'Estimate 10'!M507 -> 0
D31: HOTEL/PER DIEM/AIRFARE/CAR/PARKING | H31: ='Base Estimate'!H508+'Estimate 2'!H508+'Estimate 3'!H508+'Estimate 4'!H508+'Estimate 5'!H508+'Estimate 6'!H508+'Estimate 7'!H508+'Estimate 8'!H508+'Estimate 9'!H508+'Estimate 10'!H508 -> 0 | I31: =IFERROR((M31-H31)/(M31),0.32) -> 0.32 | J31: =H31 -> 0 | M31: ='Base Estimate'!M508+'Estimate 2'!M508+'Estimate 3'!M508+'Estimate 4'!M508+'Estimate 5'!M508+'Estimate 6'!M508+'Estimate 7'!M508+'Estimate 8'!M508+'Estimate 9'!M508+'Estimate 10'!M508 -> 0 | Q31: =IFERROR((V31/(V31+V32)),0) -> 0 | R31: Hours for Senior Tech | V31: ='Base Estimate'!V509+'Estimate 2'!V509+'Estimate 3'!V509+'Estimate 4'!V509+'Estimate 5'!V509+'Estimate 6'!V509+'Estimate 7'!V509+'Estimate 8'!V509+'Estimate 9'!V509+'Estimate 10'!V509 -> 0
D32: CONTINGENCY | H32: ='Base Estimate'!H509+'Estimate 2'!H509+'Estimate 3'!H509+'Estimate 4'!H509+'Estimate 5'!H509+'Estimate 6'!H509+'Estimate 7'!H509+'Estimate 8'!H509+'Estimate 9'!H509+'Estimate 10'!H509 -> 0 | I32: =IFERROR((M32-H32)/(M32),0.32) -> 0.32 | J32: =H32 -> 0 | M32: ='Base Estimate'!M509+'Estimate 2'!M509+'Estimate 3'!M509+'Estimate 4'!M509+'Estimate 5'!M509+'Estimate 6'!M509+'Estimate 7'!M509+'Estimate 8'!M509+'Estimate 9'!M509+'Estimate 10'!M509 -> 0 | Q32: =IFERROR((V32/(V31+V32)),0) -> 0 | R32: Hours for Tech | V32: ='Base Estimate'!V510+'Estimate 2'!V510+'Estimate 3'!V510+'Estimate 4'!V510+'Estimate 5'!V510+'Estimate 6'!V510+'Estimate 7'!V510+'Estimate 8'!V510+'Estimate 9'!V510+'Estimate 10'!V510 -> 0 | X32: PM Per Diem | AA32: 0
D33: TOTAL MATERIALS & TRIP COST | H33: =SUM(H27:H32) -> 0 | J33: =SUM(J27:J32) -> 0
D35: JOB COST | H35: =H24+H33 -> 0 | J35: =J24+J33 -> 0 | Q35: Engineering x tech multiplier | T35: 0 | V35: ='Base Estimate'!V513+'Estimate 2'!V513+'Estimate 3'!V513+'Estimate 4'!V513+'Estimate 5'!V513+'Estimate 6'!V513+'Estimate 7'!V513+'Estimate 8'!V513+'Estimate 9'!V513+'Estimate 10'!V513 -> 0 | X35: PM Days out of Town | AA35: =ROUNDUP((((V41*V42)/40)*5),0) -> 0
D36: WARRANTY | G36: 0.02 | H36: ='Base Estimate'!H514+'Estimate 2'!H514+'Estimate 3'!H514+'Estimate 4'!H514+'Estimate 5'!H514+'Estimate 6'!H514+'Estimate 7'!H514+'Estimate 8'!H514+'Estimate 9'!H514+'Estimate 10'!H514 -> 0 | I36: =IFERROR((M36-H36)/(M36),0.32) -> 0.32 | M36: ='Base Estimate'!M514+'Estimate 2'!M514+'Estimate 3'!M514+'Estimate 4'!M514+'Estimate 5'!M514+'Estimate 6'!M514+'Estimate 7'!M514+'Estimate 8'!M514+'Estimate 9'!M514+'Estimate 10'!M514 -> 0
D37: MECHANICAL LABOR | H37: ='Base Estimate'!H515 -> 0 | M37: =AG29 -> 0
D38: SALES TAX (NC RMI ONLY) | F38: Mecklenburg, NC | G38: ='State Taxes'!E9 -> 0.0825 | M38: ='State Taxes'!E9 -> 0.0825 | Q38: =IFERROR((V38/(V38+V39)),0) -> 0 | R38: Hours for Senior PM | V38: ='Base Estimate'!V517+'Estimate 2'!V517+'Estimate 3'!V517+'Estimate 4'!V517+'Estimate 5'!V517+'Estimate 6'!V517+'Estimate 7'!V517+'Estimate 8'!V517+'Estimate 9'!V517+'Estimate 10'!V517 -> 0 | X38: PM Travel Cost | AA38: ='Base Estimate'!AA516+'Estimate 2'!AA514+'Estimate 3'!AA514+'Estimate 4'!AA514+'Estimate 5'!AA514+'Estimate 6'!AA514+'Estimate 7'!AA514+'Estimate 8'!AA514+'Estimate 9'!AA514+'Estimate 10'!AA514 -> 0
D39: Total Job Cost | H39: =H35+H36+H37+H38 -> 0 | Q39: =IFERROR((V39/(V38+V39)),0) -> 0 | R39: Hours for APM | V39: ='Base Estimate'!V518+'Estimate 2'!V518+'Estimate 3'!V518+'Estimate 4'!V518+'Estimate 5'!V518+'Estimate 6'!V518+'Estimate 7'!V518+'Estimate 8'!V518+'Estimate 9'!V518+'Estimate 10'!V518 -> 0
D40: JOB SALE PRICE | M40: ='Base Estimate'!M518+'Estimate 2'!M518+'Estimate 3'!M518+'Estimate 4'!M518+'Estimate 5'!M518+'Estimate 6'!M518+'Estimate 7'!M518+'Estimate 8'!M518+'Estimate 9'!M518+'Estimate 10'!M518 -> 0
Q41: Number of weeks of project | V41: 0 | X41: Car Allowance
I42: Margin | M42: =M40-H39 -> 0 | Q42: Hrs per week | V42: 0
Q43: Total PM Hrs - (Duration Driven) | V43: ='Base Estimate'!V522+'Estimate 2'!V522+'Estimate 3'!V522+'Estimate 4'!V522+'Estimate 5'!V522+'Estimate 6'!V522+'Estimate 7'!V522+'Estimate 8'!V522+'Estimate 9'!V522+'Estimate 10'!V522 -> 0 | X43: Cost Per Day | AA43: 0
D44: SALES PRICE CALCULATOR | G44: GM | H44: Sale Price
F45: =IFERROR((M40-H39)/(M40),0.32) -> 0.32 | G45: 0 | H45: =$H$39/(1-G45) -> 0 | Q45: Tech/Prog/Graphics Labor Percentages | X45: Days | AA45: 0
E46: Job GM | G46: 0.2 | H46: =$H$39/(1-G46) -> 0 | Q46: Percentage of labor that is tech time | V46: =IFERROR(ROUND((V5+V17+V21+V23+V25)/N18,2),"0") -> 0
G47: 0.25 | H47: =$H$39/(1-G47) -> 0 | Q47: Percentage of labor that is graphics time | V47: =IFERROR(ROUND(Z5/N18,2),"0") -> 0
G48: 0.3 | H48: =$H$39/(1-G48) -> 0 | Q48: Percentage of labor that is programming time | V48: =IFERROR(ROUND(AD5/N18,2),"0") -> 0 | X48: Total Car Allowance | AA48: ='Base Estimate'!AA526+'Estimate 2'!AA524+'Estimate 3'!AA525+'Estimate 4'!AA525+'Estimate 5'!AA525+'Estimate 6'!AA525+'Estimate 7'!AA525+'Estimate 8'!AA525+'Estimate 9'!AA525+'Estimate 10'!AA525 -> 0
G49: 0.35 | H49: =$H$39/(1-G49) -> 0
G50: 0.4 | H50: =$H$39/(1-G50) -> 0
X51: AirFare
X53: Cost Per Trip | AA53: 0
H54: =IFERROR(M40/(D5+D7),"$0") -> $0 | I54: Per Box
X55: Number of Trips | AA55: 0
H56: 0 | I56: Agreed Upon Price
B58: Multipliers for Quantity Discounts | X58: Total Air Allowance | AA58: ='Base Estimate'!AA536+'Estimate 2'!AA534+'Estimate 3'!AA535+'Estimate 4'!AA535+'Estimate 5'!AA535+'Estimate 6'!AA535+'Estimate 7'!AA535+'Estimate 8'!AA535+'Estimate 9'!AA535+'Estimate 10'!AA535 -> 0
F59: AX Jace 600 Sizing Tool
B60: WEBS Products: Includes Jaces, WEB's, LON/BACNet Modules | D60: 1.045 | F60: Controller Counts | G60: Number of Jace 600's
F61: =J6 -> 0 | G61: =IF(J61-INT(J61)>0.001,ROUNDUP(J61,0),INT(J61)) -> 0 | I61: LON | J61: =F61/80 -> 0
F62: =J6 -> 0 | G62: =IF(J62-INT(J62)>0.001,ROUNDUP(J62,0),INT(J62)) -> 0 | I62: BACNet | J62: =(F62*1.2)/80 -> 0
B63: Make Products: Includes Spyders, Strykers, Sensors, Wall Modules | D63: 1.045
F64: N4 Jace 8000 Sizing Tool
F65: Controller Counts | G65: Total Points | I65: Type
F66: =J6 -> 0 | G66: =K6 -> 0 | I66: =IF(F66>160,"WEB-8200",IF($G$66=0,"-",IF($G$66>5000,"WEB-8200",(IF($G$66>1250,"WEB-8100",IF($G$66>500,"WEB-8025",IF($G$66>250,"WEB-8010","WEB-8005"))))))) -> -
B67: Honeywell VFD's | D67: 1.045 | G67: =J67 -> 0 | I67: =IF(F66>320,"WEB-8200",IF($G$67=0,"-",IF($G$67>5000,"WEB-8200",(IF($G$67>1250,"WEB-8100",IF($G$67>500,"WEB-8025",IF($G$67>250,"WEB-8010","WEB-8005"))))))) -> - | J67: =IF(($G$66-10000)<0,0,$G$66-10000) -> 0
G68: =J68 -> 0 | I68: =IF(F66>480,"WEB-8200",IF($G$68=0,"-",IF($G$68>5000,"WEB-8200",(IF($G$68>1250,"WEB-8100",IF($G$68>500,"WEB-8025",IF($G$68>250,"WEB-8010","WEB-8005"))))))) -> - | J68: =IF(($G$66-20000)<0,0,$G$66-20000) -> 0
G69: =J69 -> 0 | I69: =IF(F66>640,"WEB-8200",IF($G$69=0,"-",IF($G$69>5000,"WEB-8200",(IF($G$69>1250,"WEB-8100",IF($G$69>500,"WEB-8025",IF($G$69>250,"WEB-8010","WEB-8005"))))))) -> - | J69: =IF(($G$66-30000)<0,0,$G$66-30000) -> 0
B71: JCI | D71: 1.05
B75: JCI with Special Pricing | D75: 1.05
B79: Siemens | D79: 1
B83: Other Materials | D83: 1
B91: Material | C91: Labor | E91: Sub | F91: Travel | H91: Margin | Q91: Programming | S91: Engineering | V91: Graphics | X91: Technical | Z91: PM | AB91: Panel | AD91: Install
B92: =M8 -> 0 | C92: =H24 -> 0 | E92: =H29 -> 0 | F92: =H27+H31 -> 0 | H92: =M42 -> 0 | M92: =SUM(B92:H92) -> 0 | Q92: =C15 -> 0 | S92: =C16 -> 0 | V92: =C17 -> 0 | X92: =C18 -> 0 | Z92: =C20 -> 0 | AB92: =C22 -> 0 | AD92: =C23 -> 0

Sheet Base Estimate
B1: =Totals!B1 -> ESTIMATING SHEET VERSION 8.6 | G1: Salesman: | H1: =Totals!H1 -> 0 | L1: 1 | N1: <- 1=Page Used, 0=Page not used
B2: Job Name: | C2: =Totals!C2 -> 0 | G2: Estimator: | H2: =Totals!H2 -> 0 | L2: =Totals!L2 -> 0
B3: Part Number | D3: QTY. | E3: MATERIAL DESCRIPTON | H3: LIST $ | J3: # of Contrs | K3: # of Points | M3: TOTAL | R3: Electrical Price Check | V3: Tech | Z3: Graphics | AD3: Programming
D5: 0 | E5: VAV Boxes w Heat | F5: Option | I5: #/unit | N5: 1 | O5: Pts/VAV | P5: =D5*N5 -> 0 | Q5: points | R5: =P5*S5 -> 0 | S5: 550 | T5: per VAV | V5: =P5*W5 -> 0 | W5: 1 | X5: per VAV | Z5: =P5*AA5 -> 0 | AA5: 0.25 | AB5: per VAV | AD5: =P5*AE5 -> 0 | AE5: 0.25 | AF5: per VAV
A6: =E6&F6 -> ControllerOptimizer BACnet MSTP VAV Cntr w Act & VP, Bluetooth, 7 UIO, 5 SSR | B6: =IF(E6="","",VLOOKUP(A6,'Parts List'!A:E,5,FALSE)) -> VAA-VA75MB24NMC | D6: =$D$5*I6 -> 0 | E6: Controller | F6: Optimizer BACnet MSTP VAV Cntr w Act & VP, Bluetooth, 7 UIO, 5 SSR | H6: =IF(E6="","",VLOOKUP(A6,'Parts List'!A:F,6,FALSE)) -> 281.3558 | I6: 1 | J6: =D6 -> 0 | K6: =D6*70 -> 0 | M6: =IF(H6="","",D6*H6) -> 0
A7: =E7&F7 -> Temp SensorTR100 Space with LCD | B7: =IF(E7="","",VLOOKUP(A7,'Parts List'!A:E,5,FALSE)) -> TR100-T-G | D7: =$D$5*I7 -> 0 | E7: Temp Sensor | F7: TR100 Space with LCD | H7: =IF(E7="","",VLOOKUP(A7,'Parts List'!A:F,6,FALSE)) -> 128.71265 | I7: 1 | M7: =IF(H7="","",D7*H7) -> 0
A8: =E8&F8 -> Temp SensorDuct Insertion Sensor | B8: =IF(E8="","",VLOOKUP(A8,'Parts List'!A:E,5,FALSE)) -> C7041B2005 | D8: =$D$5*I8 -> 0 | E8: Temp Sensor | F8: Duct Insertion Sensor | H8: =IF(E8="","",VLOOKUP(A8,'Parts List'!A:F,6,FALSE)) -> 23.18855 | I8: 1 | M8: =IF(H8="","",D8*H8) -> 0
A9: =E9&F9 -> Current SwDigital Status Switch | B9: =IF(E9="","",VLOOKUP(A9,'Parts List'!A:E,5,FALSE)) -> H600 | D9: =$D$5*I9 -> 0 | E9: Current Sw | F9: Digital Status Switch | H9: =IF(E9="","",VLOOKUP(A9,'Parts List'!A:F,6,FALSE)) -> 31.43 | I9: 0 | M9: =IF(H9="","",D9*H9) -> 0
A10: =E10&F10 -> RelayRIB Pilot Relay | B10: =IF(E10="","",VLOOKUP(A10,'Parts List'!A:E,5,FALSE)) -> RIBU1C | D10: =$D$5*I10 -> 0 | E10: Relay | F10: RIB Pilot Relay | H10: =IF(E10="","",VLOOKUP(A10,'Parts List'!A:F,6,FALSE)) -> 14.36 | I10: 0 | M10: =IF(H10="","",D10*H10) -> 0
A11: =E11&F11 -> VAV HW Valve 2W & 3-way NSR | B11: =IF(E11="","",VLOOKUP(A11,'Parts List'!A:E,5,FALSE)) -> N/A | D11: =$D$5*I11 -> 0 | E11: VAV HW Valve 2W & 3-way NSR | H11: 150 | I11: 0 | M11: =IF(H11="","",D11*H11) -> 0
A12: =E12&F12 -> Air Flow MonitorRetrofit Flow Ring for VAV Boxes | B12: =IF(E12="","",VLOOKUP(A12,'Parts List'!A:E,5,FALSE)) -> 36FMI | D12: =$D$5*I12 -> 0 | E12: Air Flow Monitor | F12: Retrofit Flow Ring for VAV Boxes | H12: =IF(E12="","",VLOOKUP(A12,'Parts List'!A:F,6,FALSE)) -> 95 | I12: 0 | M12: =IF(H12="","",D12*H12) -> 0
B13: =IF(E13="","",VLOOKUP(A13,'Parts List'!A:E,5,FALSE)) | H13: =IF(E13="","",VLOOKUP(A13,'Parts List'!A:F,6,FALSE)) | M13: =IF(H13="","",D13*H13)
A15: =E15&F15 -> Cooling Only VAV Boxes | D15: 0 | E15: Cooling Only VAV Boxes | I15: #/unit | N15: 1 | O15: Pts/VAV | P15: =D15*N15 -> 0 | Q15: points | R15: =P15*S15 -> 0 | S15: 550 | T15: per VAV | V15: =P15*W15 -> 0 | W15: 1 | X15: per VAV | Z15: =P15*AA15 -> 0 | AA15: 0.25 | AB15: per VAV | AD15: =P15*AE15 -> 0 | AE15: 0.25 | AF15: per VAV
A16: =E16&F16 -> ControllerOptimizer BACnet MSTP VAV Cntr w Act & VP, Bluetooth, 7 UIO, 5 SSR | B16: =IF(E16="","",VLOOKUP(A16,'Parts List'!A:E,5,FALSE)) -> VAA-VA75MB24NMC | D16: =$D$15*I16 -> 0 | E16: Controller | F16: Optimizer BACnet MSTP VAV Cntr w Act & VP, Bluetooth, 7 UIO, 5 SSR | H16: =IF(E16="","",VLOOKUP(A16,'Parts List'!A:F,6,FALSE)) -> 281.3558 | I16: 1 | J16: =D16 -> 0 | K16: =D16*70 -> 0 | M16: =IF(H16="","",D16*H16) -> 0
A17: =E17&F17 -> Temp SensorTR100 Space with LCD | B17: =IF(E17="","",VLOOKUP(A17,'Parts List'!A:E,5,FALSE)) -> TR100-T-G | D17: =$D$15*I17 -> 0 | E17: Temp Sensor | F17: TR100 Space with LCD | H17: =IF(E17="","",VLOOKUP(A17,'Parts List'!A:F,6,FALSE)) -> 128.71265 | I17: 1 | M17: =IF(H17="","",D17*H17) -> 0
A18: =E18&F18 -> Transformer40 VA | B18: =IF(E18="","",VLOOKUP(A18,'Parts List'!A:E,5,FALSE)) -> TR40VA001 | D18: =$D$15*I18 -> 0 | E18: Transformer | F18: 40 VA | H18: =IF(E18="","",VLOOKUP(A18,'Parts List'!A:F,6,FALSE)) -> 17.76 | I18: 0 | M18: =IF(H18="","",D18*H18) -> 0
A19: =E19&F19 -> Air Flow MonitorRetrofit Flow Ring for VAV Boxes | B19: =IF(E19="","",VLOOKUP(A19,'Parts List'!A:E,5,FALSE)) -> 36FMI | D19: =$D$15*I19 -> 0 | E19: Air Flow Monitor | F19: Retrofit Flow Ring for VAV Boxes | H19: =IF(E19="","",VLOOKUP(A19,'Parts List'!A:F,6,FALSE)) -> 95 | I19: 0 | M19: =IF(H19="","",D19*H19) -> 0
B20: =IF(E20="","",VLOOKUP(A20,'Parts List'!A:E,5,FALSE)) | H20: =IF(E20="","",VLOOKUP(A20,'Parts List'!A:F,6,FALSE)) | M20: =IF(H20="","",D20*H20)
D23: 0 | E23: Supply Air Boxes - CRC/Phoenix LV Wiring and Integration | I23: #/unit | N23: 1 | O23: Pts/VAV | P23: =D23*N23 -> 0 | Q23: points | R23: =P23*S23 -> 0 | S23: 750 | T23: per VAV | V23: =P23*W23 -> 0 | W23: 1 | X23: per VAV | Z23: =P23*AA23 -> 0 | AA23: 0.25 | AB23: per VAV | AD23: =P23*AE23 -> 0 | AE23: 0.25 | AF23: per VAV
A24: =E24&F24 | B24: =IF(E24="","",VLOOKUP(A24,'[2]Parts List'!A:E,5,FALSE)) | D24: =$D$23*I24 -> 0 | H24: =IF(E24="","",VLOOKUP(A24,'[2]Parts List'!A:F,6,FALSE)) | I24: 1 | J24: =D24 -> 0 | K24: =D24*50 -> 0 | M24: =IF(H24="","",D24*H24)
D27: 0 | E27: Exhaust Air Boxes - CRC/Phoenix LV Wiring and Integration | I27: #/unit | N27: 1 | O27: Pts/VAV | P27: =D27*N27 -> 0 | Q27: points | R27: =P27*S27 -> 0 | S27: 750 | T27: per VAV | V27: =P27*W27 -> 0 | W27: 1 | X27: per VAV | Z27: =P27*AA27 -> 0 | AA27: 0.25 | AB27: per VAV | AD27: =P27*AE27 -> 0 | AE27: 0.25 | AF27: per VAV
A28: =E28&F28 | B28: =IF(E28="","",VLOOKUP(A28,'[2]Parts List'!A:E,5,FALSE)) | D28: =$D$27*I28 -> 0 | H28: =IF(E28="","",VLOOKUP(A28,'[2]Parts List'!A:F,6,FALSE)) | I28: 1 | M28: =IF(H28="","",D28*H28)
D31: 0 | E31: Return Air Boxes - CRC/Phoenix LV Wiring and Integration | I31: #/unit | N31: 1 | O31: Pts/VAV | P31: =D31*N31 -> 0 | Q31: points | R31: =P31*S31 -> 0 | S31: 750 | T31: per VAV | V31: =P31*W31 -> 0 | W31: 1 | X31: per VAV | Z31: =P31*AA31 -> 0 | AA31: 0.25 | AB31: per VAV | AD31: =P31*AE31 -> 0 | AE31: 0.25 | AF31: per VAV
A32: =E32&F32 | B32: =IF(E32="","",VLOOKUP(A32,'[2]Parts List'!A:E,5,FALSE)) | D32: =$D$31*I32 -> 0 | H32: =IF(E32="","",VLOOKUP(A32,'[2]Parts List'!A:F,6,FALSE)) | I32: 1 | M32: =IF(H32="","",D32*H32)
D35: 0 | E35: OR Room Pressure Monitors - CRC/Phoenix LV Wiring and Integration | I35: #/unit | N35: 1 | O35: Pts/VAV | P35: =D35*N35 -> 0 | Q35: points | R35: =P35*S35 -> 0 | S35: 750 | T35: per VAV | V35: =P35*W35 -> 0 | W35: 1 | X35: per VAV | Z35: =P35*AA35 -> 0 | AA35: 0.25 | AB35: per VAV | AD35: =P35*AE35 -> 0 | AE35: 0.25 | AF35: per VAV
A36: =E36&F36 | B36: =IF(E36="","",VLOOKUP(A36,'[2]Parts List'!A:E,5,FALSE)) | D36: =$D$35*I36 -> 0 | H36: =IF(E36="","",VLOOKUP(A36,'[2]Parts List'!A:F,6,FALSE)) | I36: 1 | M36: =IF(H36="","",D36*H36)
A40: =E40&F40 -> Cooling Only VAV Box Transformers | D40: 0 | E40: Cooling Only VAV Box Transformers | I40: #/unit | N40: =SUM(I41:I43) -> 0 | O40: Pts/Unit | P40: =D40*N40 -> 0 | Q40: points | R40: =P40*S40 -> 0 | S40: 550 | T40: per Unit | V40: =P40*W40 -> 0 | W40: 0 | X40: per unit | Z40: =D40*AA40 -> 0 | AA40: 0 | AB40: per unit | AD40: =D40*AE40 -> 0 | AE40: 0 | AF40: per unit
A41: =E41&F41 -> Transformer(3) - 100 VA w Enclosure | B41: =IF(E41="","",VLOOKUP(A41,'Parts List'!A:E,5,FALSE)) -> PSH300A | D41: =$D$40*I41 -> 0 | E41: Transformer | F41: (3) - 100 VA w Enclosure | H41: =IF(E41="","",VLOOKUP(A41,'Parts List'!A:F,6,FALSE)) -> 314.8 | I41: 0 | M41: =IF(H41="","",D41*H41) -> 0
A42: =E42&F42 -> Transformer(5) - 100 VA w Enclosure | B42: =IF(E42="","",VLOOKUP(A42,'Parts List'!A:E,5,FALSE)) -> PSH500A | D42: =$D$40*I42 -> 0 | E42: Transformer | F42: (5) - 100 VA w Enclosure | H42: =IF(E42="","",VLOOKUP(A42,'Parts List'!A:F,6,FALSE)) -> 430.65 | I42: 0 | M42: =IF(H42="","",D42*H42) -> 0
A43: =E43&F43 | B43: =IF(E43="","",VLOOKUP(A43,'Parts List'!A:E,5,FALSE)) | D43: =$D$40*I43 -> 0 | H43: =IF(E43="","",VLOOKUP(A43,'Parts List'!A:F,6,FALSE)) | I43: 0 | M43: =IF(H43="","",D43*H43)
B44: =IF(E44="","",VLOOKUP(A44,'Parts List'!A:E,5,FALSE)) | H44: =IF(E44="","",VLOOKUP(A44,'Parts List'!A:F,6,FALSE)) | M44: =IF(H44="","",D44*H44)
A46: =E46&F46 -> VAV Air Handling Unit | D46: 0 | E46: VAV Air Handling Unit | I46: #/unit | N46: =SUM(I57:I73)+I52 -> 1 | O46: Pts/Unit | P46: =D46*N46 -> 0 | Q46: points | R46: =P46*S46 -> 0 | S46: 350 | T46: per point | V46: =P46*W46 -> 0 | W46: 1 | X46: per point | Z46: =D46*AA46 -> 0 | AA46: 4 | AB46: per unit | AD46: =D46*AE46 -> 0 | AE46: 6 | AF46: per unit
A47: =E47&F47 -> ControllerOptimizer Plant Cntr, 1 IP, 3 Ethernet Switched+4 RS485 Ports | B47: =IF(E47="","",VLOOKUP(A47,'Parts List'!A:E,5,FALSE)) -> N-ADV-134-H-C | D47: =$D$46*I47 -> 0 | E47: Controller | F47: Optimizer Plant Cntr, 1 IP, 3 Ethernet Switched+4 RS485 Ports | H47: =IF(E47="","",VLOOKUP(A47,'Parts List'!A:F,6,FALSE)) -> 875.1457 | I47: 0 | J47: =D47 -> 0 | K47: =D47*70 -> 0 | M47: =IF(H47="","",D47*H47) -> 0
A48: =E48&F48 -> Optimizer License with 18 Month SMA | B48: =IF(E48="","",VLOOKUP(A48,'Parts List'!A:E,5,FALSE)) -> Select Option | D48: =$D$46*I48 -> 0 | E48: Optimizer License with 18 Month SMA | H48: =IF(E48="","",VLOOKUP(A48,'Parts List'!A:F,6,FALSE)) -> 0 | I48: 0 | J48: =D48 -> 0 | K48: =D48*70 -> 0 | M48: =IF(H48="","",D48*H48) -> 0
A49: =E49&F49 -> I/O ModuleOptimzer Unitary Cntr 5-UI, 5-DI, 4-AO, 4-DO I/O Module | B49: =IF(E49="","",VLOOKUP(A49,'Parts List'!A:E,5,FALSE)) -> ISMA-B-MIX18 | D49: =$D$46*I49 -> 0 | E49: I/O Module | F49: Optimzer Unitary Cntr 5-UI, 5-DI, 4-AO, 4-DO I/O Module | H49: =IF(E49="","",VLOOKUP(A49,'Parts List'!A:F,6,FALSE)) -> 338.81 | I49: 0 | M49: =IF(H49="","",D49*H49) -> 0
A50: =E50&F50 -> Phoenix Controller Core License | B50: =IF(E50="","",VLOOKUP(A50,'Parts List'!A:E,5,FALSE)) -> Select Option | D50: =$D$46*I50 -> 0 | E50: Phoenix Controller Core License | H50: =IF(E50="","",VLOOKUP(A50,'Parts List'!A:F,6,FALSE)) -> 0 | I50: 0 | M50: =IF(H50="","",D50*H50) -> 0
A51: =E51&F51 -> Phoenix ILC SMA | B51: =IF(E51="","",VLOOKUP(A51,'Parts List'!A:E,5,FALSE)) -> Select Option | D51: =$D$46*I51 -> 0 | E51: Phoenix ILC SMA | H51: =IF(E51="","",VLOOKUP(A51,'Parts List'!A:F,6,FALSE)) -> 0 | I51: 0 | M51: =IF(H51="","",D51*H51) -> 0
A52: =E52&F52 -> Panel - Enclosure w SubpanelNema-1 Medium | B52: =IF(E52="","",VLOOKUP(A52,'Parts List'!A:E,5,FALSE)) -> RET1-262007BT-P | D52: =$D$46*I52 -> 0 | E52: Panel - Enclosure w Subpanel | F52: Nema-1 Medium | H52: =IF(E52="","",VLOOKUP(A52,'Parts List'!A:F,6,FALSE)) -> 436.83 | I52: 0 | M52: =IF(H52="","",D52*H52) -> 0
A53: =E53&F53 -> Relay24VAC DPDT with Base | B53: =IF(E53="","",VLOOKUP(A53,'Parts List'!A:E,5,FALSE)) -> RH2B-UAC24 + SH2B-05 | D53: =$D$46*I53 -> 0 | E53: Relay | F53: 24VAC DPDT with Base | H53: =IF(E53="","",VLOOKUP(A53,'Parts List'!A:F,6,FALSE)) -> 8.12 | I53: 0 | M53: =IF(H53="","",D53*H53) -> 0
A54: =E54&F54 -> Transformer75 VA with circuit breaker | B54: =IF(E54="","",VLOOKUP(A54,'Parts List'!A:E,5,FALSE)) -> TR75VA004 | D54: =$D$46*I54 -> 0 | E54: Transformer | F54: 75 VA with circuit breaker | H54: =IF(E54="","",VLOOKUP(A54,'Parts List'!A:F,6,FALSE)) -> 42.14 | I54: 0 | M54: =IF(H54="","",D54*H54) -> 0
A55: =E55&F55 -> Power Supply24VDC Panel Mounted - 1.3 A | B55: =IF(E55="","",VLOOKUP(A55,'Parts List'!A:E,5,FALSE)) -> PS5R-VB24 | D55: =$D$46*I55 -> 0 | E55: Power Supply | F55: 24VDC Panel Mounted - 1.3 A | H55: =IF(E55="","",VLOOKUP(A55,'Parts List'!A:F,6,FALSE)) -> 50.96 | I55: 0 | M55: =IF(H55="","",D55*H55) -> 0
A56: =E56&F56 -> Static Pressure TipsDuct Kit | B56: =IF(E56="","",VLOOKUP(A56,'Parts List'!A:E,5,FALSE)) -> A-302K + A-345k | D56: =$D$46*I56 -> 0 | E56: Static Pressure Tips | F56: Duct Kit | H56: =IF(E56="","",VLOOKUP(A56,'Parts List'!A:F,6,FALSE)) -> 17.9 | I56: 0 | M56: =IF(H56="","",D56*H56) -> 0
A57: =E57&F57 -> ThermostatLow Limit | B57: =IF(E57="","",VLOOKUP(A57,'Parts List'!A:E,5,FALSE)) -> A11A-1C | D57: =$D$46*I57 -> 0 | E57: Thermostat | F57: Low Limit | H57: =IF(E57="","",VLOOKUP(A57,'Parts List'!A:F,6,FALSE)) -> 270.31 | I57: 0 | M57: =IF(H57="","",D57*H57) -> 0
A58: =E58&F58 -> Filter StatusDigital Status | B58: =IF(E58="","",VLOOKUP(A58,'Parts List'!A:E,5,FALSE)) -> AFS-145 | D58: =$D$46*I58 -> 0 | E58: Filter Status | F58: Digital Status | H58: =IF(E58="","",VLOOKUP(A58,'Parts List'!A:F,6,FALSE)) -> 40.9 | I58: 0 | M58: =IF(H58="","",D58*H58) -> 0
A59: =E59&F59 -> Press TransmitterDuct Static Air | B59: =IF(E59="","",VLOOKUP(A59,'Parts List'!A:E,5,FALSE)) -> PX3DXX02 | D59: =$D$46*I59 -> 0 | E59: Press Transmitter | F59: Duct Static Air | H59: =IF(E59="","",VLOOKUP(A59,'Parts List'!A:F,6,FALSE)) -> 130.12 | I59: 0 | M59: =IF(H59="","",D59*H59) -> 0
A60: =E60&F60 -> Press Transmitter | B60: =IF(E60="","",VLOOKUP(A60,'Parts List'!A:E,5,FALSE)) -> Select Option | D60: =$D$46*I60 -> 0 | E60: Press Transmitter | H60: =IF(E60="","",VLOOKUP(A60,'Parts List'!A:F,6,FALSE)) -> 0 | I60: 0 | M60: =IF(H60="","",D60*H60) -> 0
A61: =E61&F61 -> Press TransmitterHigh Static Limit Switch | B61: =IF(E61="","",VLOOKUP(A61,'Parts List'!A:E,5,FALSE)) -> 1900-5-MR | D61: =$D$46*I61 -> 0 | E61: Press Transmitter | F61: High Static Limit Switch | H61: =IF(E61="","",VLOOKUP(A61,'Parts List'!A:F,6,FALSE)) -> 111.93 | I61: 0 | M61: =IF(H61="","",D61*H61) -> 0
A62: =E62&F62 -> Current SwDigital for VFD Status | B62: =IF(E62="","",VLOOKUP(A62,'Parts List'!A:E,5,FALSE)) -> H904 | D62: =$D$46*I62 -> 0 | E62: Current Sw | F62: Digital for VFD Status | H62: =IF(E62="","",VLOOKUP(A62,'Parts List'!A:F,6,FALSE)) -> 88.31 | I62: 0 | M62: =IF(H62="","",D62*H62) -> 0
A63: =E63&F63 -> Damper ActuatorLarge - Spring Return | B63: =IF(E63="","",VLOOKUP(A63,'Parts List'!A:E,5,FALSE)) -> MS7520A2007 | D63: =$D$46*I63 -> 0 | E63: Damper Actuator | F63: Large - Spring Return | H63: =IF(E63="","",VLOOKUP(A63,'Parts List'!A:F,6,FALSE)) -> 446.4658 | I63: 0 | M63: =IF(H63="","",D63*H63) -> 0
A64: =E64&F64 -> Temp SensorAveraging Sensor | B64: =IF(E64="","",VLOOKUP(A64,'Parts List'!A:E,5,FALSE)) -> C7041R2018 | D64: =$D$46*I64 -> 0 | E64: Temp Sensor | F64: Averaging Sensor | H64: =IF(E64="","",VLOOKUP(A64,'Parts List'!A:F,6,FALSE)) -> 166.9283 | I64: 0 | M64: =IF(H64="","",D64*H64) -> 0
A65: =E65&F65 -> Temp SensorDuct Temp/Humidity | B65: =IF(E65="","",VLOOKUP(A65,'Parts List'!A:E,5,FALSE)) -> H7735B2018 | D65: =$D$46*I65 -> 0 | E65: Temp Sensor | F65: Duct Temp/Humidity | H65: =IF(E65="","",VLOOKUP(A65,'Parts List'!A:F,6,FALSE)) -> 266.23465 | I65: 0 | M65: =IF(H65="","",D65*H65) -> 0
A66: =E66&F66 -> Humidity | B66: =IF(E66="","",VLOOKUP(A66,'Parts List'!A:E,5,FALSE)) -> Select Option | D66: =$D$46*I66 -> 0 | E66: Humidity | H66: =IF(E66="","",VLOOKUP(A66,'Parts List'!A:F,6,FALSE)) -> 0 | I66: 0 | M66: =IF(H66="","",D66*H66) -> 0
A67: =E67&F67 -> Humidity | B67: =IF(E67="","",VLOOKUP(A67,'Parts List'!A:E,5,FALSE)) -> Select Option | D67: =$D$46*I67 -> 0 | E67: Humidity | H67: =IF(E67="","",VLOOKUP(A67,'Parts List'!A:F,6,FALSE)) -> 0 | I67: 0 | M67: =IF(H67="","",D67*H67) -> 0
A68: =E68&F68 -> Carbon Dioxide SensorSpace CO2 wo LCD | B68: =IF(E68="","",VLOOKUP(A68,'Parts List'!A:E,5,FALSE)) -> C7263A1008 | D68: =$D$46*I68 -> 0 | E68: Carbon Dioxide Sensor | F68: Space CO2 wo LCD | H68: =IF(E68="","",VLOOKUP(A68,'Parts List'!A:F,6,FALSE)) -> 355.7389 | I68: 0 | M68: =IF(H68="","",D68*H68) -> 0
A69: =E69&F69 -> Carbon Dioxide SensorDuct CO2 wo LCD | B69: =IF(E69="","",VLOOKUP(A69,'Parts List'!A:E,5,FALSE)) -> C7632B1002 | D69: =$D$46*I69 -> 0 | E69: Carbon Dioxide Sensor | F69: Duct CO2 wo LCD | H69: =IF(E69="","",VLOOKUP(A69,'Parts List'!A:F,6,FALSE)) -> 331.2441 | I69: 0 | M69: =IF(H69="","",D69*H69) -> 0
A70: =E70&F70 -> Emergency Stop SwitchFlush Mtd | B70: =IF(E70="","",VLOOKUP(A70,'Parts List'!A:E,5,FALSE)) -> AOW401R + SSG1-67 | D70: =$D$46*I70 -> 0 | E70: Emergency Stop Switch | F70: Flush Mtd | H70: =IF(E70="","",VLOOKUP(A70,'Parts List'!A:F,6,FALSE)) -> 75.69 | I70: 0 | M70: =IF(H70="","",D70*H70) -> 0
A71: =E71&F71 -> Air Flow Monitor | B71: =IF(E71="","",VLOOKUP(A71,'Parts List'!A:E,5,FALSE)) -> Select Option | D71: =$D$46*I71 -> 0 | E71: Air Flow Monitor | H71: =IF(E71="","",VLOOKUP(A71,'Parts List'!A:F,6,FALSE)) -> 0 | I71: 0 | M71: =IF(H71="","",D71*H71) -> 0
A72: =E72&F72 -> See Valve Quote | B72: =IF(E72="","",VLOOKUP(A72,'Parts List'!A:E,5,FALSE)) -> N/A | D72: =$D$46*I72 -> 0 | E72: See Valve Quote | H72: =IF(E72="","",VLOOKUP(A72,'Parts List'!A:F,6,FALSE)) -> 0 | I72: 0 | M72: =IF(H72="","",D72*H72) -> 0
A73: =E73&F73 | B73: =IF(E73="","",VLOOKUP(A73,'Parts List'!A:E,5,FALSE)) | D73: =$D$46*I73 -> 0 | H73: =IF(E73="","",VLOOKUP(A73,'Parts List'!A:F,6,FALSE)) | I73: 1 | M73: =IF(H73="","",D73*H73) | N73: <- Duct Detector Interlock - Used for point count
A74: =E74&F74 | B74: =IF(E74="","",VLOOKUP(A74,'Parts List'!A:E,5,FALSE)) | D74: =$D$46*I74 -> 0 | H74: =IF(E74="","",VLOOKUP(A74,'Parts List'!A:F,6,FALSE)) | I74: 0 | M74: =IF(H74="","",D74*H74)
A75: =E75&F75 | B75: =IF(E75="","",VLOOKUP(A75,'Parts List'!A:E,5,FALSE)) | D75: =$D$46*I75 -> 0 | H75: =IF(E75="","",VLOOKUP(A75,'Parts List'!A:F,6,FALSE)) | I75: 0 | M75: =IF(H75="","",D75*H75)
A76: =E76&F76 | B76: =IF(E76="","",VLOOKUP(A76,'Parts List'!A:E,5,FALSE)) | H76: =IF(E76="","",VLOOKUP(A76,'Parts List'!A:F,6,FALSE)) | M76: =IF(H76="","",D76*H76)
A77: =E77&F77 -> Constant Volume Air Handling Units | D77: 0 | E77: Constant Volume Air Handling Units | I77: #/unit | N77: =SUM(I88:I102)+I83 -> 1 | O77: Pts/Unit | P77: =D77*N77 -> 0 | Q77: units | R77: =P77*S77 -> 0 | S77: 350 | T77: per point | V77: =P77*W77 -> 0 | W77: 1 | X77: per point | Z77: =D77*AA77 -> 0 | AA77: 4 | AB77: per unit | AD77: =D77*AE77 -> 0 | AE77: 6 | AF77: per unit
A78: =E78&F78 -> ControllerOptimizer Plant Cntr, 1 IP, 3 Ethernet Switched+4 RS485 Ports | B78: =IF(E78="","",VLOOKUP(A78,'Parts List'!A:E,5,FALSE)) -> N-ADV-134-H-C | D78: =$D$77*I78 -> 0 | E78: Controller | F78: Optimizer Plant Cntr, 1 IP, 3 Ethernet Switched+4 RS485 Ports | H78: =IF(E78="","",VLOOKUP(A78,'Parts List'!A:F,6,FALSE)) -> 875.1457 | I78: 0 | J78: =D78 -> 0 | K78: =D78*70 -> 0 | M78: =IF(H78="","",D78*H78) -> 0
A79: =E79&F79 -> Optimizer License with 18 Month SMA | B79: =IF(E79="","",VLOOKUP(A79,'Parts List'!A:E,5,FALSE)) -> Select Option | D79: =$D$77*I79 -> 0 | E79: Optimizer License with 18 Month SMA | H79: =IF(E79="","",VLOOKUP(A79,'Parts List'!A:F,6,FALSE)) -> 0 | I79: 0 | J79: =D79 -> 0 | K79: =D79*70 -> 0 | M79: =IF(H79="","",D79*H79) -> 0
A80: =E80&F80 -> I/O ModuleOptimzer Unitary Cntr 5-UI, 5-DI, 4-AO, 4-DO I/O Module | B80: =IF(E80="","",VLOOKUP(A80,'Parts List'!A:E,5,FALSE)) -> ISMA-B-MIX18 | D80: =$D$77*I80 -> 0 | E80: I/O Module | F80: Optimzer Unitary Cntr 5-UI, 5-DI, 4-AO, 4-DO I/O Module | H80: =IF(E80="","",VLOOKUP(A80,'Parts List'!A:F,6,FALSE)) -> 338.81 | I80: 0 | M80: =IF(H80="","",D80*H80) -> 0
A81: =E81&F81 -> Phoenix Controller Core License | B81: =IF(E81="","",VLOOKUP(A81,'Parts List'!A:E,5,FALSE)) -> Select Option | D81: =$D$77*I81 -> 0 | E81: Phoenix Controller Core License | H81: =IF(E81="","",VLOOKUP(A81,'Parts List'!A:F,6,FALSE)) -> 0 | I81: 0 | M81: =IF(H81="","",D81*H81) -> 0
A82: =E82&F82 -> Phoenix ILC SMA | B82: =IF(E82="","",VLOOKUP(A82,'Parts List'!A:E,5,FALSE)) -> Select Option | D82: =$D$77*I82 -> 0 | E82: Phoenix ILC SMA | H82: =IF(E82="","",VLOOKUP(A82,'Parts List'!A:F,6,FALSE)) -> 0 | I82: 0 | M82: =IF(H82="","",D82*H82) -> 0
A83: =E83&F83 -> Panel - Enclosure w SubpanelNema-1 Medium | B83: =IF(E83="","",VLOOKUP(A83,'Parts List'!A:E,5,FALSE)) -> RET1-262007BT-P | D83: =$D$77*I83 -> 0 | E83: Panel - Enclosure w Subpanel | F83: Nema-1 Medium | H83: =IF(E83="","",VLOOKUP(A83,'Parts List'!A:F,6,FALSE)) -> 436.83 | I83: 0 | M83: =IF(H83="","",D83*H83) -> 0
A84: =E84&F84 -> Relay24VAC DPDT with Base | B84: =IF(E84="","",VLOOKUP(A84,'Parts List'!A:E,5,FALSE)) -> RH2B-UAC24 + SH2B-05 | D84: =$D$77*I84 -> 0 | E84: Relay | F84: 24VAC DPDT with Base | H84: =IF(E84="","",VLOOKUP(A84,'Parts List'!A:F,6,FALSE)) -> 8.12 | I84: 0 | M84: =IF(H84="","",D84*H84) -> 0
A85: =E85&F85 -> Transformer75 VA with circuit breaker | B85: =IF(E85="","",VLOOKUP(A85,'Parts List'!A:E,5,FALSE)) -> TR75VA004 | D85: =$D$77*I85 -> 0 | E85: Transformer | F85: 75 VA with circuit breaker | H85: =IF(E85="","",VLOOKUP(A85,'Parts List'!A:F,6,FALSE)) -> 42.14 | I85: 0 | M85: =IF(H85="","",D85*H85) -> 0
A86: =E86&F86 -> Power Supply24VDC Panel Mounted - 1.3 A | B86: =IF(E86="","",VLOOKUP(A86,'Parts List'!A:E,5,FALSE)) -> PS5R-VB24 | D86: =$D$77*I86 -> 0 | E86: Power Supply | F86: 24VDC Panel Mounted - 1.3 A | H86: =IF(E86="","",VLOOKUP(A86,'Parts List'!A:F,6,FALSE)) -> 50.96 | I86: 0 | M86: =IF(H86="","",D86*H86) -> 0
A87: =E87&F87 -> Static Pressure TipsDuct Kit | B87: =IF(E87="","",VLOOKUP(A87,'Parts List'!A:E,5,FALSE)) -> A-302K + A-345k | D87: =$D$77*I87 -> 0 | E87: Static Pressure Tips | F87: Duct Kit | H87: =IF(E87="","",VLOOKUP(A87,'Parts List'!A:F,6,FALSE)) -> 17.9 | I87: 0 | M87: =IF(H87="","",D87*H87) -> 0
A88: =E88&F88 -> ThermostatLow Limit | B88: =IF(E88="","",VLOOKUP(A88,'Parts List'!A:E,5,FALSE)) -> A11A-1C | D88: =$D$77*I88 -> 0 | E88: Thermostat | F88: Low Limit | H88: =IF(E88="","",VLOOKUP(A88,'Parts List'!A:F,6,FALSE)) -> 270.31 | I88: 0 | M88: =IF(H88="","",D88*H88) -> 0
A89: =E89&F89 -> Filter StatusDigital Status | B89: =IF(E89="","",VLOOKUP(A89,'Parts List'!A:E,5,FALSE)) -> AFS-145 | D89: =$D$77*I89 -> 0 | E89: Filter Status | F89: Digital Status | H89: =IF(E89="","",VLOOKUP(A89,'Parts List'!A:F,6,FALSE)) -> 40.9 | I89: 0 | M89: =IF(H89="","",D89*H89) -> 0
A90: =E90&F90 -> Press TransmitterDuct Static Air | B90: =IF(E90="","",VLOOKUP(A90,'Parts List'!A:E,5,FALSE)) -> PX3DXX02 | D90: =$D$77*I90 -> 0 | E90: Press Transmitter | F90: Duct Static Air | H90: =IF(E90="","",VLOOKUP(A90,'Parts List'!A:F,6,FALSE)) -> 130.12 | I90: 0 | M90: =IF(H90="","",D90*H90) -> 0
A91: =E91&F91 -> Current SwDigital for VFD Status | B91: =IF(E91="","",VLOOKUP(A91,'Parts List'!A:E,5,FALSE)) -> H904 | D91: =$D$77*I91 -> 0 | E91: Current Sw | F91: Digital for VFD Status | H91: =IF(E91="","",VLOOKUP(A91,'Parts List'!A:F,6,FALSE)) -> 88.31 | I91: 0 | M91: =IF(H91="","",D91*H91) -> 0
A92: =E92&F92 -> Damper ActuatorLarge - Spring Return | B92: =IF(E92="","",VLOOKUP(A92,'Parts List'!A:E,5,FALSE)) -> MS7520A2007 | D92: =$D$77*I92 -> 0 | E92: Damper Actuator | F92: Large - Spring Return | H92: =IF(E92="","",VLOOKUP(A92,'Parts List'!A:F,6,FALSE)) -> 446.4658 | I92: 0 | M92: =IF(H92="","",D92*H92) -> 0
A93: =E93&F93 -> Temp SensorAveraging Sensor | B93: =IF(E93="","",VLOOKUP(A93,'Parts List'!A:E,5,FALSE)) -> C7041R2018 | D93: =$D$77*I93 -> 0 | E93: Temp Sensor | F93: Averaging Sensor | H93: =IF(E93="","",VLOOKUP(A93,'Parts List'!A:F,6,FALSE)) -> 166.9283 | I93: 0 | M93: =IF(H93="","",D93*H93) -> 0
A94: =E94&F94 -> Temp SensorDuct Temp/Humidity | B94: =IF(E94="","",VLOOKUP(A94,'Parts List'!A:E,5,FALSE)) -> H7735B2018 | D94: =$D$77*I94 -> 0 | E94: Temp Sensor | F94: Duct Temp/Humidity | H94: =IF(E94="","",VLOOKUP(A94,'Parts List'!A:F,6,FALSE)) -> 266.23465 | I94: 0 | M94: =IF(H94="","",D94*H94) -> 0
A95: =E95&F95 -> Humidity | B95: =IF(E95="","",VLOOKUP(A95,'Parts List'!A:E,5,FALSE)) -> Select Option | D95: =$D$77*I95 -> 0 | E95: Humidity | H95: =IF(E95="","",VLOOKUP(A95,'Parts List'!A:F,6,FALSE)) -> 0 | I95: 0 | M95: =IF(H95="","",D95*H95) -> 0
A96: =E96&F96 -> Humidity | B96: =IF(E96="","",VLOOKUP(A96,'Parts List'!A:E,5,FALSE)) -> Select Option | D96: =$D$77*I96 -> 0 | E96: Humidity | H96: =IF(E96="","",VLOOKUP(A96,'Parts List'!A:F,6,FALSE)) -> 0 | I96: 0 | M96: =IF(H96="","",D96*H96) -> 0
A97: =E97&F97 -> Carbon Dioxide SensorSpace CO2 wo LCD | B97: =IF(E97="","",VLOOKUP(A97,'Parts List'!A:E,5,FALSE)) -> C7263A1008 | D97: =$D$77*I97 -> 0 | E97: Carbon Dioxide Sensor | F97: Space CO2 wo LCD | H97: =IF(E97="","",VLOOKUP(A97,'Parts List'!A:F,6,FALSE)) -> 355.7389 | I97: 0 | M97: =IF(H97="","",D97*H97) -> 0
A98: =E98&F98 -> Carbon Dioxide SensorDuct CO2 wo LCD | B98: =IF(E98="","",VLOOKUP(A98,'Parts List'!A:E,5,FALSE)) -> C7632B1002 | D98: =$D$77*I98 -> 0 | E98: Carbon Dioxide Sensor | F98: Duct CO2 wo LCD | H98: =IF(E98="","",VLOOKUP(A98,'Parts List'!A:F,6,FALSE)) -> 331.2441 | I98: 0 | M98: =IF(H98="","",D98*H98) -> 0
A99: =E99&F99 -> Emergency Stop SwitchFlush Mtd | B99: =IF(E99="","",VLOOKUP(A99,'Parts List'!A:E,5,FALSE)) -> AOW401R + SSG1-67 | D99: =$D$77*I99 -> 0 | E99: Emergency Stop Switch | F99: Flush Mtd | H99: =IF(E99="","",VLOOKUP(A99,'Parts List'!A:F,6,FALSE)) -> 75.69 | I99: 0 | M99: =IF(H99="","",D99*H99) -> 0
A100: =E100&F100 -> Air Flow Monitor | B100: =IF(E100="","",VLOOKUP(A100,'Parts List'!A:E,5,FALSE)) -> Select Option | D100: =$D$77*I100 -> 0 | E100: Air Flow Monitor | H100: =IF(E100="","",VLOOKUP(A100,'Parts List'!A:F,6,FALSE)) -> 0 | I100: 0 | M100: =IF(H100="","",D100*H100) -> 0
A101: =E101&F101 -> See Valve Quote | B101: =IF(E101="","",VLOOKUP(A101,'Parts List'!A:E,5,FALSE)) -> N/A | D101: =$D$77*I101 -> 0 | E101: See Valve Quote | H101: =IF(E101="","",VLOOKUP(A101,'Parts List'!A:F,6,FALSE)) -> 0 | I101: 0 | M101: =IF(H101="","",D101*H101) -> 0
A102: =E102&F102 | B102: =IF(E102="","",VLOOKUP(A102,'Parts List'!A:E,5,FALSE)) | D102: =$D$77*I102 -> 0 | H102: =IF(E102="","",VLOOKUP(A102,'Parts List'!A:F,6,FALSE)) | I102: 1 | M102: =IF(H102="","",D102*H102) | N102: <- Duct Detector Interlock - Used for point count
A103: =E103&F103 | B103: =IF(E103="","",VLOOKUP(A103,'Parts List'!A:E,5,FALSE)) | D103: =$D$77*I103 -> 0 | H103: =IF(E103="","",VLOOKUP(A103,'Parts List'!A:F,6,FALSE)) | I103: 0 | M103: =IF(H103="","",D103*H103)
A104: =E104&F104 | B104: =IF(E104="","",VLOOKUP(A104,'Parts List'!A:E,5,FALSE)) | D104: =$D$77*I104 -> 0 | H104: =IF(E104="","",VLOOKUP(A104,'Parts List'!A:F,6,FALSE)) | I104: 0 | M104: =IF(H104="","",D104*H104)
A105: =E105&F105 | B105: =IF(E105="","",VLOOKUP(A105,'Parts List'!A:E,5,FALSE)) | H105: =IF(E105="","",VLOOKUP(A105,'Parts List'!A:F,6,FALSE)) | M105: =IF(H105="","",D105*H105)
A106: =E106&F106 -> Water Source Heat Pumps | D106: 0 | E106: Water Source Heat Pumps | I106: #/unit | N106: =SUM(I112:I120)+I108 -> 0 | O106: Pts/Unit | P106: =D106*N106 -> 0 | Q106: units | R106: =D106*S106 -> 0 | S106: 1500 | T106: per unit | V106: =D106*W106 -> 0 | W106: 3 | X106: per unit | Z106: =D106*AA106 -> 0 | AA106: 1 | AB106: per unit | AD106: =D106*AE106 -> 0 | AE106: 1 | AF106: per unit
A107: =E107&F107 -> Controller | B107: =IF(E107="","",VLOOKUP(A107,'Parts List'!A:E,5,FALSE)) -> Select Option | D107: =$D$106*I107 -> 0 | E107: Controller | H107: =IF(E107="","",VLOOKUP(A107,'Parts List'!A:F,6,FALSE)) -> 0 | I107: 0 | J107: =D107 -> 0 | K107: =D107*70 -> 0 | M107: =IF(H107="","",D107*H107) -> 0
A108: =E108&F108 -> Panel - Enclosure w Subpanel | B108: =IF(E108="","",VLOOKUP(A108,'Parts List'!A:E,5,FALSE)) -> Select Option | D108: =$D$106*I108 -> 0 | E108: Panel - Enclosure w Subpanel | H108: =IF(E108="","",VLOOKUP(A108,'Parts List'!A:F,6,FALSE)) -> 0 | I108: 0 | M108: =IF(H108="","",D108*H108) -> 0
A109: =E109&F109 -> Relay | B109: =IF(E109="","",VLOOKUP(A109,'Parts List'!A:E,5,FALSE)) -> Select Option | D109: =$D$106*I109 -> 0 | E109: Relay | H109: =IF(E109="","",VLOOKUP(A109,'Parts List'!A:F,6,FALSE)) -> 0 | I109: 0 | M109: =IF(H109="","",D109*H109) -> 0
A110: =E110&F110 -> Transformer | B110: =IF(E110="","",VLOOKUP(A110,'Parts List'!A:E,5,FALSE)) -> Select Option | D110: =$D$106*I110 -> 0 | E110: Transformer | H110: =IF(E110="","",VLOOKUP(A110,'Parts List'!A:F,6,FALSE)) -> 0 | I110: 0 | M110: =IF(H110="","",D110*H110) -> 0
A111: =E111&F111 -> Static Pressure Tips | B111: =IF(E111="","",VLOOKUP(A111,'Parts List'!A:E,5,FALSE)) -> N/A | D111: =$D$106*I111 -> 0 | E111: Static Pressure Tips | H111: =IF(E111="","",VLOOKUP(A111,'Parts List'!A:F,6,FALSE)) -> 0 | I111: 0 | M111: =IF(H111="","",D111*H111) -> 0
A112: =E112&F112 -> Current Sw | B112: =IF(E112="","",VLOOKUP(A112,'Parts List'!A:E,5,FALSE)) -> Select Option | D112: =$D$106*I112 -> 0 | E112: Current Sw | H112: =IF(E112="","",VLOOKUP(A112,'Parts List'!A:F,6,FALSE)) -> 0 | I112: 0 | M112: =IF(H112="","",D112*H112) -> 0
A113: =E113&F113 -> Filter Status | B113: =IF(E113="","",VLOOKUP(A113,'Parts List'!A:E,5,FALSE)) -> Select Option | D113: =$D$106*I113 -> 0 | E113: Filter Status | H113: =IF(E113="","",VLOOKUP(A113,'Parts List'!A:F,6,FALSE)) -> 0 | I113: 0 | M113: =IF(H113="","",D113*H113) -> 0
A114: =E114&F114 -> Communicating Room Thermostat | B114: =IF(E114="","",VLOOKUP(A114,'Parts List'!A:E,5,FALSE)) -> Select Option | D114: =$D$106*I114 -> 0 | E114: Communicating Room Thermostat | H114: =IF(E114="","",VLOOKUP(A114,'Parts List'!A:F,6,FALSE)) -> 0 | I114: 0 | J114: =D114 -> 0 | K114: =D114*50 -> 0 | M114: =IF(H114="","",D114*H114) -> 0
...

Sheet Estimate 2
B1: =Totals!B1 -> ESTIMATING SHEET VERSION 8.6 | G1: Salesman: | H1: =Totals!H1 -> 0 | L1: 1 | N1: <- 1=Page Used, 0=Page not used
B2: Job Name: | C2: =Totals!C2 -> 0 | G2: Estimator: | H2: =Totals!H2 -> 0 | L2: =Totals!L2 -> 0
B3: Part Number | D3: QTY. | E3: MATERIAL DESCRIPTON | H3: LIST $ | J3: # of Contrs | K3: # of Points | M3: TOTAL | R3: Electrical Price Check | V3: Tech | Z3: Graphics | AD3: Programming
D5: 0 | E5: VAV Boxes w Heat | F5: Option | I5: #/unit | N5: 1 | O5: Pts/VAV | P5: =D5*N5 -> 0 | Q5: points | R5: =P5*S5 -> 0 | S5: 550 | T5: per VAV | V5: =P5*W5 -> 0 | W5: 1 | X5: per VAV | Z5: =P5*AA5 -> 0 | AA5: 0.25 | AB5: per VAV | AD5: =P5*AE5 -> 0 | AE5: 0.25 | AF5: per VAV
A6: =E6&F6 -> ControllerOptimizer BACnet MSTP VAV Cntr w Act & VP, Bluetooth, 7 UIO, 5 SSR | B6: =IF(E6="","",VLOOKUP(A6,'Parts List'!A:E,5,FALSE)) -> VAA-VA75MB24NMC | D6: =$D$5*I6 -> 0 | E6: Controller | F6: Optimizer BACnet MSTP VAV Cntr w Act & VP, Bluetooth, 7 UIO, 5 SSR | H6: =IF(E6="","",VLOOKUP(A6,'Parts List'!A:F,6,FALSE)) -> 281.3558 | I6: 1 | J6: =D6 -> 0 | K6: =D6*70 -> 0 | M6: =IF(H6="","",D6*H6) -> 0
A7: =E7&F7 -> Temp SensorTR100 Space with LCD | B7: =IF(E7="","",VLOOKUP(A7,'Parts List'!A:E,5,FALSE)) -> TR100-T-G | D7: =$D$5*I7 -> 0 | E7: Temp Sensor | F7: TR100 Space with LCD | H7: =IF(E7="","",VLOOKUP(A7,'Parts List'!A:F,6,FALSE)) -> 128.71265 | I7: 1 | M7: =IF(H7="","",D7*H7) -> 0
A8: =E8&F8 -> Temp SensorDuct Insertion Sensor | B8: =IF(E8="","",VLOOKUP(A8,'Parts List'!A:E,5,FALSE)) -> C7041B2005 | D8: =$D$5*I8 -> 0 | E8: Temp Sensor | F8: Duct Insertion Sensor | H8: =IF(E8="","",VLOOKUP(A8,'Parts List'!A:F,6,FALSE)) -> 23.18855 | I8: 1 | M8: =IF(H8="","",D8*H8) -> 0
A9: =E9&F9 -> Current SwDigital Status Switch | B9: =IF(E9="","",VLOOKUP(A9,'Parts List'!A:E,5,FALSE)) -> H600 | D9: =$D$5*I9 -> 0 | E9: Current Sw | F9: Digital Status Switch | H9: =IF(E9="","",VLOOKUP(A9,'Parts List'!A:F,6,FALSE)) -> 31.43 | I9: 0 | M9: =IF(H9="","",D9*H9) -> 0
A10: =E10&F10 -> RelayRIB Pilot Relay | B10: =IF(E10="","",VLOOKUP(A10,'Parts List'!A:E,5,FALSE)) -> RIBU1C | D10: =$D$5*I10 -> 0 | E10: Relay | F10: RIB Pilot Relay | H10: =IF(E10="","",VLOOKUP(A10,'Parts List'!A:F,6,FALSE)) -> 14.36 | I10: 0 | M10: =IF(H10="","",D10*H10) -> 0
A11: =E11&F11 -> VAV HW Valve 2W & 3-way NSR | B11: =IF(E11="","",VLOOKUP(A11,'Parts List'!A:E,5,FALSE)) -> N/A | D11: =$D$5*I11 -> 0 | E11: VAV HW Valve 2W & 3-way NSR | H11: 150 | I11: 0 | M11: =IF(H11="","",D11*H11) -> 0
A12: =E12&F12 -> Air Flow MonitorRetrofit Flow Ring for VAV Boxes | B12: =IF(E12="","",VLOOKUP(A12,'Parts List'!A:E,5,FALSE)) -> 36FMI | D12: =$D$5*I12 -> 0 | E12: Air Flow Monitor | F12: Retrofit Flow Ring for VAV Boxes | H12: =IF(E12="","",VLOOKUP(A12,'Parts List'!A:F,6,FALSE)) -> 95 | I12: 0 | M12: =IF(H12="","",D12*H12) -> 0
B13: =IF(E13="","",VLOOKUP(A13,'Parts List'!A:E,5,FALSE)) | H13: =IF(E13="","",VLOOKUP(A13,'Parts List'!A:F,6,FALSE)) | M13: =IF(H13="","",D13*H13)
A15: =E15&F15 -> Cooling Only VAV Boxes | D15: 0 | E15: Cooling Only VAV Boxes | I15: #/unit | N15: 1 | O15: Pts/VAV | P15: =D15*N15 -> 0 | Q15: points | R15: =P15*S15 -> 0 | S15: 550 | T15: per VAV | V15: =P15*W15 -> 0 | W15: 1 | X15: per VAV | Z15: =P15*AA15 -> 0 | AA15: 0.25 | AB15: per VAV | AD15: =P15*AE15 -> 0 | AE15: 0.25 | AF15: per VAV
A16: =E16&F16 -> ControllerOptimizer BACnet MSTP VAV Cntr w Act & VP, Bluetooth, 7 UIO, 5 SSR | B16: =IF(E16="","",VLOOKUP(A16,'Parts List'!A:E,5,FALSE)) -> VAA-VA75MB24NMC | D16: =$D$15*I16 -> 0 | E16: Controller | F16: Optimizer BACnet MSTP VAV Cntr w Act & VP, Bluetooth, 7 UIO, 5 SSR | H16: =IF(E16="","",VLOOKUP(A16,'Parts List'!A:F,6,FALSE)) -> 281.3558 | I16: 1 | J16: =D16 -> 0 | K16: =D16*70 -> 0 | M16: =IF(H16="","",D16*H16) -> 0
A17: =E17&F17 -> Temp SensorTR100 Space with LCD | B17: =IF(E17="","",VLOOKUP(A17,'Parts List'!A:E,5,FALSE)) -> TR100-T-G | D17: =$D$15*I17 -> 0 | E17: Temp Sensor | F17: TR100 Space with LCD | H17: =IF(E17="","",VLOOKUP(A17,'Parts List'!A:F,6,FALSE)) -> 128.71265 | I17: 1 | M17: =IF(H17="","",D17*H17) -> 0
A18: =E18&F18 -> Transformer40 VA | B18: =IF(E18="","",VLOOKUP(A18,'Parts List'!A:E,5,FALSE)) -> TR40VA001 | D18: =$D$15*I18 -> 0 | E18: Transformer | F18: 40 VA | H18: =IF(E18="","",VLOOKUP(A18,'Parts List'!A:F,6,FALSE)) -> 17.76 | I18: 0 | M18: =IF(H18="","",D18*H18) -> 0
A19: =E19&F19 -> Air Flow MonitorRetrofit Flow Ring for VAV Boxes | B19: =IF(E19="","",VLOOKUP(A19,'Parts List'!A:E,5,FALSE)) -> 36FMI | D19: =$D$15*I19 -> 0 | E19: Air Flow Monitor | F19: Retrofit Flow Ring for VAV Boxes | H19: =IF(E19="","",VLOOKUP(A19,'Parts List'!A:F,6,FALSE)) -> 95 | I19: 0 | M19: =IF(H19="","",D19*H19) -> 0
B20: =IF(E20="","",VLOOKUP(A20,'Parts List'!A:E,5,FALSE)) | H20: =IF(E20="","",VLOOKUP(A20,'Parts List'!A:F,6,FALSE)) | M20: =IF(H20="","",D20*H20)
D23: 0 | E23: Supply Air Boxes - CRC/Phoenix LV Wiring and Integration | I23: #/unit | N23: 1 | O23: Pts/VAV | P23: =D23*N23 -> 0 | Q23: points | R23: =P23*S23 -> 0 | S23: 750 | T23: per VAV | V23: =P23*W23 -> 0 | W23: 1 | X23: per VAV | Z23: =P23*AA23 -> 0 | AA23: 0.25 | AB23: per VAV | AD23: =P23*AE23 -> 0 | AE23: 0.25 | AF23: per VAV
A24: =E24&F24 | B24: =IF(E24="","",VLOOKUP(A24,'[2]Parts List'!A:E,5,FALSE)) | D24: =$D$23*I24 -> 0 | H24: =IF(E24="","",VLOOKUP(A24,'[2]Parts List'!A:F,6,FALSE)) | I24: 1 | J24: =D24 -> 0 | K24: =D24*50 -> 0 | M24: =IF(H24="","",D24*H24)
D27: 0 | E27: Exhaust Air Boxes - CRC/Phoenix LV Wiring and Integration | I27: #/unit | N27: 1 | O27: Pts/VAV | P27: =D27*N27 -> 0 | Q27: points | R27: =P27*S27 -> 0 | S27: 750 | T27: per VAV | V27: =P27*W27 -> 0 | W27: 1 | X27: per VAV | Z27: =P27*AA27 -> 0 | AA27: 0.25 | AB27: per VAV | AD27: =P27*AE27 -> 0 | AE27: 0.25 | AF27: per VAV
A28: =E28&F28 | B28: =IF(E28="","",VLOOKUP(A28,'[2]Parts List'!A:E,5,FALSE)) | D28: =$D$27*I28 -> 0 | H28: =IF(E28="","",VLOOKUP(A28,'[2]Parts List'!A:F,6,FALSE)) | I28: 1 | M28: =IF(H28="","",D28*H28)
D31: 0 | E31: Return Air Boxes - CRC/Phoenix LV Wiring and Integration | I31: #/unit | N31: 1 | O31: Pts/VAV | P31: =D31*N31 -> 0 | Q31: points | R31: =P31*S31 -> 0 | S31: 750 | T31: per VAV | V31: =P31*W31 -> 0 | W31: 1 | X31: per VAV | Z31: =P31*AA31 -> 0 | AA31: 0.25 | AB31: per VAV | AD31: =P31*AE31 -> 0 | AE31: 0.25 | AF31: per VAV
A32: =E32&F32 | B32: =IF(E32="","",VLOOKUP(A32,'[2]Parts List'!A:E,5,FALSE)) | D32: =$D$31*I32 -> 0 | H32: =IF(E32="","",VLOOKUP(A32,'[2]Parts List'!A:F,6,FALSE)) | I32: 1 | M32: =IF(H32="","",D32*H32)
D35: 0 | E35: OR Room Pressure Monitors - CRC/Phoenix LV Wiring and Integration | I35: #/unit | N35: 1 | O35: Pts/VAV | P35: =D35*N35 -> 0 | Q35: points | R35: =P35*S35 -> 0 | S35: 750 | T35: per VAV | V35: =P35*W35 -> 0 | W35: 1 | X35: per VAV | Z35: =P35*AA35 -> 0 | AA35: 0.25 | AB35: per VAV | AD35: =P35*AE35 -> 0 | AE35: 0.25 | AF35: per VAV
A36: =E36&F36 | B36: =IF(E36="","",VLOOKUP(A36,'[2]Parts List'!A:E,5,FALSE)) | D36: =$D$35*I36 -> 0 | H36: =IF(E36="","",VLOOKUP(A36,'[2]Parts List'!A:F,6,FALSE)) | I36: 1 | M36: =IF(H36="","",D36*H36)
A40: =E40&F40 -> Cooling Only VAV Box Transformers | D40: 0 | E40: Cooling Only VAV Box Transformers | I40: #/unit | N40: =SUM(I41:I43) -> 0 | O40: Pts/Unit | P40: =D40*N40 -> 0 | Q40: points | R40: =P40*S40 -> 0 | S40: 550 | T40: per Unit | V40: =P40*W40 -> 0 | W40: 0 | X40: per unit | Z40: =D40*AA40 -> 0 | AA40: 0 | AB40: per unit | AD40: =D40*AE40 -> 0 | AE40: 0 | AF40: per unit
A41: =E41&F41 -> Transformer(3) - 100 VA w Enclosure | B41: =IF(E41="","",VLOOKUP(A41,'Parts List'!A:E,5,FALSE)) -> PSH300A | D41: =$D$40*I41 -> 0 | E41: Transformer | F41: (3) - 100 VA w Enclosure | H41: =IF(E41="","",VLOOKUP(A41,'Parts List'!A:F,6,FALSE)) -> 314.8 | I41: 0 | M41: =IF(H41="","",D41*H41) -> 0
A42: =E42&F42 -> Transformer(5) - 100 VA w Enclosure | B42: =IF(E42="","",VLOOKUP(A42,'Parts List'!A:E,5,FALSE)) -> PSH500A | D42: =$D$40*I42 -> 0 | E42: Transformer | F42: (5) - 100 VA w Enclosure | H42: =IF(E42="","",VLOOKUP(A42,'Parts List'!A:F,6,FALSE)) -> 430.65 | I42: 0 | M42: =IF(H42="","",D42*H42) -> 0
A43: =E43&F43 | B43: =IF(E43="","",VLOOKUP(A43,'Parts List'!A:E,5,FALSE)) | D43: =$D$40*I43 -> 0 | H43: =IF(E43="","",VLOOKUP(A43,'Parts List'!A:F,6,FALSE)) | I43: 0 | M43: =IF(H43="","",D43*H43)
B44: =IF(E44="","",VLOOKUP(A44,'Parts List'!A:E,5,FALSE)) | H44: =IF(E44="","",VLOOKUP(A44,'Parts List'!A:F,6,FALSE)) | M44: =IF(H44="","",D44*H44)
A46: =E46&F46 -> VAV Air Handling Unit | D46: 0 | E46: VAV Air Handling Unit | I46: #/unit | N46: =SUM(I57:I73)+I52 -> 1 | O46: Pts/Unit | P46: =D46*N46 -> 0 | Q46: points | R46: =P46*S46 -> 0 | S46: 350 | T46: per point | V46: =P46*W46 -> 0 | W46: 1 | X46: per point | Z46: =D46*AA46 -> 0 | AA46: 4 | AB46: per unit | AD46: =D46*AE46 -> 0 | AE46: 6 | AF46: per unit
A47: =E47&F47 -> ControllerOptimizer Plant Cntr, 1 IP, 3 Ethernet Switched+4 RS485 Ports | B47: =IF(E47="","",VLOOKUP(A47,'Parts List'!A:E,5,FALSE)) -> N-ADV-134-H-C | D47: =$D$46*I47 -> 0 | E47: Controller | F47: Optimizer Plant Cntr, 1 IP, 3 Ethernet Switched+4 RS485 Ports | H47: =IF(E47="","",VLOOKUP(A47,'Parts List'!A:F,6,FALSE)) -> 875.1457 | I47: 0 | J47: =D47 -> 0 | K47: =D47*70 -> 0 | M47: =IF(H47="","",D47*H47) -> 0
A48: =E48&F48 -> Optimizer License with 18 Month SMA | B48: =IF(E48="","",VLOOKUP(A48,'Parts List'!A:E,5,FALSE)) -> Select Option | D48: =$D$46*I48 -> 0 | E48: Optimizer License with 18 Month SMA | H48: =IF(E48="","",VLOOKUP(A48,'Parts List'!A:F,6,FALSE)) -> 0 | I48: 0 | J48: =D48 -> 0 | K48: =D48*70 -> 0 | M48: =IF(H48="","",D48*H48) -> 0
A49: =E49&F49 -> I/O ModuleOptimzer Unitary Cntr 5-UI, 5-DI, 4-AO, 4-DO I/O Module | B49: =IF(E49="","",VLOOKUP(A49,'Parts List'!A:E,5,FALSE)) -> ISMA-B-MIX18 | D49: =$D$46*I49 -> 0 | E49: I/O Module | F49: Optimzer Unitary Cntr 5-UI, 5-DI, 4-AO, 4-DO I/O Module | H49: =IF(E49="","",VLOOKUP(A49,'Parts List'!A:F,6,FALSE)) -> 338.81 | I49: 0 | M49: =IF(H49="","",D49*H49) -> 0
A50: =E50&F50 -> Phoenix Controller Core License | B50: =IF(E50="","",VLOOKUP(A50,'Parts List'!A:E,5,FALSE)) -> Select Option | D50: =$D$46*I50 -> 0 | E50: Phoenix Controller Core License | H50: =IF(E50="","",VLOOKUP(A50,'Parts List'!A:F,6,FALSE)) -> 0 | I50: 0 | M50: =IF(H50="","",D50*H50) -> 0
A51: =E51&F51 -> Phoenix ILC SMA | B51: =IF(E51="","",VLOOKUP(A51,'Parts List'!A:E,5,FALSE)) -> Select Option | D51: =$D$46*I51 -> 0 | E51: Phoenix ILC SMA | H51: =IF(E51="","",VLOOKUP(A51,'Parts List'!A:F,6,FALSE)) -> 0 | I51: 0 | M51: =IF(H51="","",D51*H51) -> 0
A52: =E52&F52 -> Panel - Enclosure w SubpanelNema-1 Medium | B52: =IF(E52="","",VLOOKUP(A52,'Parts List'!A:E,5,FALSE)) -> RET1-262007BT-P | D52: =$D$46*I52 -> 0 | E52: Panel - Enclosure w Subpanel | F52: Nema-1 Medium | H52: =IF(E52="","",VLOOKUP(A52,'Parts List'!A:F,6,FALSE)) -> 436.83 | I52: 0 | M52: =IF(H52="","",D52*H52) -> 0
A53: =E53&F53 -> Relay24VAC DPDT with Base | B53: =IF(E53="","",VLOOKUP(A53,'Parts List'!A:E,5,FALSE)) -> RH2B-UAC24 + SH2B-05 | D53: =$D$46*I53 -> 0 | E53: Relay | F53: 24VAC DPDT with Base | H53: =IF(E53="","",VLOOKUP(A53,'Parts List'!A:F,6,FALSE)) -> 8.12 | I53: 0 | M53: =IF(H53="","",D53*H53) -> 0
A54: =E54&F54 -> Transformer75 VA with circuit breaker | B54: =IF(E54="","",VLOOKUP(A54,'Parts List'!A:E,5,FALSE)) -> TR75VA004 | D54: =$D$46*I54 -> 0 | E54: Transformer | F54: 75 VA with circuit breaker | H54: =IF(E54="","",VLOOKUP(A54,'Parts List'!A:F,6,FALSE)) -> 42.14 | I54: 0 | M54: =IF(H54="","",D54*H54) -> 0
A55: =E55&F55 -> Power Supply24VDC Panel Mounted - 1.3 A | B55: =IF(E55="","",VLOOKUP(A55,'Parts List'!A:E,5,FALSE)) -> PS5R-VB24 | D55: =$D$46*I55 -> 0 | E55: Power Supply | F55: 24VDC Panel Mounted - 1.3 A | H55: =IF(E55="","",VLOOKUP(A55,'Parts List'!A:F,6,FALSE)) -> 50.96 | I55: 0 | M55: =IF(H55="","",D55*H55) -> 0
A56: =E56&F56 -> Static Pressure TipsDuct Kit | B56: =IF(E56="","",VLOOKUP(A56,'Parts List'!A:E,5,FALSE)) -> A-302K + A-345k | D56: =$D$46*I56 -> 0 | E56: Static Pressure Tips | F56: Duct Kit | H56: =IF(E56="","",VLOOKUP(A56,'Parts List'!A:F,6,FALSE)) -> 17.9 | I56: 0 | M56: =IF(H56="","",D56*H56) -> 0
A57: =E57&F57 -> ThermostatLow Limit | B57: =IF(E57="","",VLOOKUP(A57,'Parts List'!A:E,5,FALSE)) -> A11A-1C | D57: =$D$46*I57 -> 0 | E57: Thermostat | F57: Low Limit | H57: =IF(E57="","",VLOOKUP(A57,'Parts List'!A:F,6,FALSE)) -> 270.31 | I57: 0 | M57: =IF(H57="","",D57*H57) -> 0
A58: =E58&F58 -> Filter StatusDigital Status | B58: =IF(E58="","",VLOOKUP(A58,'Parts List'!A:E,5,FALSE)) -> AFS-145 | D58: =$D$46*I58 -> 0 | E58: Filter Status | F58: Digital Status | H58: =IF(E58="","",VLOOKUP(A58,'Parts List'!A:F,6,FALSE)) -> 40.9 | I58: 0 | M58: =IF(H58="","",D58*H58) -> 0
A59: =E59&F59 -> Press TransmitterDuct Static Air | B59: =IF(E59="","",VLOOKUP(A59,'Parts List'!A:E,5,FALSE)) -> PX3DXX02 | D59: =$D$46*I59 -> 0 | E59: Press Transmitter | F59: Duct Static Air | H59: =IF(E59="","",VLOOKUP(A59,'Parts List'!A:F,6,FALSE)) -> 130.12 | I59: 0 | M59: =IF(H59="","",D59*H59) -> 0
A60: =E60&F60 -> Press Transmitter | B60: =IF(E60="","",VLOOKUP(A60,'Parts List'!A:E,5,FALSE)) -> Select Option | D60: =$D$46*I60 -> 0 | E60: Press Transmitter | H60: =IF(E60="","",VLOOKUP(A60,'Parts List'!A:F,6,FALSE)) -> 0 | I60: 0 | M60: =IF(H60="","",D60*H60) -> 0
A61: =E61&F61 -> Press TransmitterHigh Static Limit Switch | B61: =IF(E61="","",VLOOKUP(A61,'Parts List'!A:E,5,FALSE)) -> 1900-5-MR | D61: =$D$46*I61 -> 0 | E61: Press Transmitter | F61: High Static Limit Switch | H61: =IF(E61="","",VLOOKUP(A61,'Parts List'!A:F,6,FALSE)) -> 111.93 | I61: 0 | M61: =IF(H61="","",D61*H61) -> 0
A62: =E62&F62 -> Current SwDigital for VFD Status | B62: =IF(E62="","",VLOOKUP(A62,'Parts List'!A:E,5,FALSE)) -> H904 | D62: =$D$46*I62 -> 0 | E62: Current Sw | F62: Digital for VFD Status | H62: =IF(E62="","",VLOOKUP(A62,'Parts List'!A:F,6,FALSE)) -> 88.31 | I62: 0 | M62: =IF(H62="","",D62*H62) -> 0
A63: =E63&F63 -> Damper ActuatorLarge - Spring Return | B63: =IF(E63="","",VLOOKUP(A63,'Parts List'!A:E,5,FALSE)) -> MS7520A2007 | D63: =$D$46*I63 -> 0 | E63: Damper Actuator | F63: Large - Spring Return | H63: =IF(E63="","",VLOOKUP(A63,'Parts List'!A:F,6,FALSE)) -> 446.4658 | I63: 0 | M63: =IF(H63="","",D63*H63) -> 0
A64: =E64&F64 -> Temp SensorAveraging Sensor | B64: =IF(E64="","",VLOOKUP(A64,'Parts List'!A:E,5,FALSE)) -> C7041R2018 | D64: =$D$46*I64 -> 0 | E64: Temp Sensor | F64: Averaging Sensor | H64: =IF(E64="","",VLOOKUP(A64,'Parts List'!A:F,6,FALSE)) -> 166.9283 | I64: 0 | M64: =IF(H64="","",D64*H64) -> 0
A65: =E65&F65 -> Temp SensorDuct Temp/Humidity | B65: =IF(E65="","",VLOOKUP(A65,'Parts List'!A:E,5,FALSE)) -> H7735B2018 | D65: =$D$46*I65 -> 0 | E65: Temp Sensor | F65: Duct Temp/Humidity | H65: =IF(E65="","",VLOOKUP(A65,'Parts List'!A:F,6,FALSE)) -> 266.23465 | I65: 0 | M65: =IF(H65="","",D65*H65) -> 0
A66: =E66&F66 -> Humidity | B66: =IF(E66="","",VLOOKUP(A66,'Parts List'!A:E,5,FALSE)) -> Select Option | D66: =$D$46*I66 -> 0 | E66: Humidity | H66: =IF(E66="","",VLOOKUP(A66,'Parts List'!A:F,6,FALSE)) -> 0 | I66: 0 | M66: =IF(H66="","",D66*H66) -> 0
A67: =E67&F67 -> Humidity | B67: =IF(E67="","",VLOOKUP(A67,'Parts List'!A:E,5,FALSE)) -> Select Option | D67: =$D$46*I67 -> 0 | E67: Humidity | H67: =IF(E67="","",VLOOKUP(A67,'Parts List'!A:F,6,FALSE)) -> 0 | I67: 0 | M67: =IF(H67="","",D67*H67) -> 0
A68: =E68&F68 -> Carbon Dioxide SensorSpace CO2 wo LCD | B68: =IF(E68="","",VLOOKUP(A68,'Parts List'!A:E,5,FALSE)) -> C7263A1008 | D68: =$D$46*I68 -> 0 | E68: Carbon Dioxide Sensor | F68: Space CO2 wo LCD | H68: =IF(E68="","",VLOOKUP(A68,'Parts List'!A:F,6,FALSE)) -> 355.7389 | I68: 0 | M68: =IF(H68="","",D68*H68) -> 0
A69: =E69&F69 -> Carbon Dioxide SensorDuct CO2 wo LCD | B69: =IF(E69="","",VLOOKUP(A69,'Parts List'!A:E,5,FALSE)) -> C7632B1002 | D69: =$D$46*I69 -> 0 | E69: Carbon Dioxide Sensor | F69: Duct CO2 wo LCD | H69: =IF(E69="","",VLOOKUP(A69,'Parts List'!A:F,6,FALSE)) -> 331.2441 | I69: 0 | M69: =IF(H69="","",D69*H69) -> 0
A70: =E70&F70 -> Emergency Stop SwitchFlush Mtd | B70: =IF(E70="","",VLOOKUP(A70,'Parts List'!A:E,5,FALSE)) -> AOW401R + SSG1-67 | D70: =$D$46*I70 -> 0 | E70: Emergency Stop Switch | F70: Flush Mtd | H70: =IF(E70="","",VLOOKUP(A70,'Parts List'!A:F,6,FALSE)) -> 75.69 | I70: 0 | M70: =IF(H70="","",D70*H70) -> 0
A71: =E71&F71 -> Air Flow Monitor | B71: =IF(E71="","",VLOOKUP(A71,'Parts List'!A:E,5,FALSE)) -> Select Option | D71: =$D$46*I71 -> 0 | E71: Air Flow Monitor | H71: =IF(E71="","",VLOOKUP(A71,'Parts List'!A:F,6,FALSE)) -> 0 | I71: 0 | M71: =IF(H71="","",D71*H71) -> 0
A72: =E72&F72 -> See Valve Quote | B72: =IF(E72="","",VLOOKUP(A72,'Parts List'!A:E,5,FALSE)) -> N/A | D72: =$D$46*I72 -> 0 | E72: See Valve Quote | H72: =IF(E72="","",VLOOKUP(A72,'Parts List'!A:F,6,FALSE)) -> 0 | I72: 0 | M72: =IF(H72="","",D72*H72) -> 0
A73: =E73&F73 | B73: =IF(E73="","",VLOOKUP(A73,'Parts List'!A:E,5,FALSE)) | D73: =$D$46*I73 -> 0 | H73: =IF(E73="","",VLOOKUP(A73,'Parts List'!A:F,6,FALSE)) | I73: 1 | M73: =IF(H73="","",D73*H73) | N73: <- Duct Detector Interlock - Used for point count
A74: =E74&F74 | B74: =IF(E74="","",VLOOKUP(A74,'Parts List'!A:E,5,FALSE)) | D74: =$D$46*I74 -> 0 | H74: =IF(E74="","",VLOOKUP(A74,'Parts List'!A:F,6,FALSE)) | I74: 0 | M74: =IF(H74="","",D74*H74)
A75: =E75&F75 | B75: =IF(E75="","",VLOOKUP(A75,'Parts List'!A:E,5,FALSE)) | D75: =$D$46*I75 -> 0 | H75: =IF(E75="","",VLOOKUP(A75,'Parts List'!A:F,6,FALSE)) | I75: 0 | M75: =IF(H75="","",D75*H75)
A76: =E76&F76 | B76: =IF(E76="","",VLOOKUP(A76,'Parts List'!A:E,5,FALSE)) | H76: =IF(E76="","",VLOOKUP(A76,'Parts List'!A:F,6,FALSE)) | M76: =IF(H76="","",D76*H76)
A77: =E77&F77 -> Constant Volume Air Handling Units | D77: 0 | E77: Constant Volume Air Handling Units | I77: #/unit | N77: =SUM(I88:I102)+I83 -> 1 | O77: Pts/Unit | P77: =D77*N77 -> 0 | Q77: units | R77: =P77*S77 -> 0 | S77: 350 | T77: per point | V77: =P77*W77 -> 0 | W77: 1 | X77: per point | Z77: =D77*AA77 -> 0 | AA77: 4 | AB77: per unit | AD77: =D77*AE77 -> 0 | AE77: 6 | AF77: per unit
A78: =E78&F78 -> ControllerOptimizer Plant Cntr, 1 IP, 3 Ethernet Switched+4 RS485 Ports | B78: =IF(E78="","",VLOOKUP(A78,'Parts List'!A:E,5,FALSE)) -> N-ADV-134-H-C | D78: =$D$77*I78 -> 0 | E78: Controller | F78: Optimizer Plant Cntr, 1 IP, 3 Ethernet Switched+4 RS485 Ports | H78: =IF(E78="","",VLOOKUP(A78,'Parts List'!A:F,6,FALSE)) -> 875.1457 | I78: 0 | J78: =D78 -> 0 | K78: =D78*70 -> 0 | M78: =IF(H78="","",D78*H78) -> 0
A79: =E79&F79 -> Optimizer License with 18 Month SMA | B79: =IF(E79="","",VLOOKUP(A79,'Parts List'!A:E,5,FALSE)) -> Select Option | D79: =$D$77*I79 -> 0 | E79: Optimizer License with 18 Month SMA | H79: =IF(E79="","",VLOOKUP(A79,'Parts List'!A:F,6,FALSE)) -> 0 | I79: 0 | J79: =D79 -> 0 | K79: =D79*70 -> 0 | M79: =IF(H79="","",D79*H79) -> 0
A80: =E80&F80 -> I/O ModuleOptimzer Unitary Cntr 5-UI, 5-DI, 4-AO, 4-DO I/O Module | B80: =IF(E80="","",VLOOKUP(A80,'Parts List'!A:E,5,FALSE)) -> ISMA-B-MIX18 | D80: =$D$77*I80 -> 0 | E80: I/O Module | F80: Optimzer Unitary Cntr 5-UI, 5-DI, 4-AO, 4-DO I/O Module | H80: =IF(E80="","",VLOOKUP(A80,'Parts List'!A:F,6,FALSE)) -> 338.81 | I80: 0 | M80: =IF(H80="","",D80*H80) -> 0
A81: =E81&F81 -> Phoenix Controller Core License | B81: =IF(E81="","",VLOOKUP(A81,'Parts List'!A:E,5,FALSE)) -> Select Option | D81: =$D$77*I81 -> 0 | E81: Phoenix Controller Core License | H81: =IF(E81="","",VLOOKUP(A81,'Parts List'!A:F,6,FALSE)) -> 0 | I81: 0 | M81: =IF(H81="","",D81*H81) -> 0
A82: =E82&F82 -> Phoenix ILC SMA | B82: =IF(E82="","",VLOOKUP(A82,'Parts List'!A:E,5,FALSE)) -> Select Option | D82: =$D$77*I82 -> 0 | E82: Phoenix ILC SMA | H82: =IF(E82="","",VLOOKUP(A82,'Parts List'!A:F,6,FALSE)) -> 0 | I82: 0 | M82: =IF(H82="","",D82*H82) -> 0
A83: =E83&F83 -> Panel - Enclosure w SubpanelNema-1 Medium | B83: =IF(E83="","",VLOOKUP(A83,'Parts List'!A:E,5,FALSE)) -> RET1-262007BT-P | D83: =$D$77*I83 -> 0 | E83: Panel - Enclosure w Subpanel | F83: Nema-1 Medium | H83: =IF(E83="","",VLOOKUP(A83,'Parts List'!A:F,6,FALSE)) -> 436.83 | I83: 0 | M83: =IF(H83="","",D83*H83) -> 0
A84: =E84&F84 -> Relay24VAC DPDT with Base | B84: =IF(E84="","",VLOOKUP(A84,'Parts List'!A:E,5,FALSE)) -> RH2B-UAC24 + SH2B-05 | D84: =$D$77*I84 -> 0 | E84: Relay | F84: 24VAC DPDT with Base | H84: =IF(E84="","",VLOOKUP(A84,'Parts List'!A:F,6,FALSE)) -> 8.12 | I84: 0 | M84: =IF(H84="","",D84*H84) -> 0
A85: =E85&F85 -> Transformer75 VA with circuit breaker | B85: =IF(E85="","",VLOOKUP(A85,'Parts List'!A:E,5,FALSE)) -> TR75VA004 | D85: =$D$77*I85 -> 0 | E85: Transformer | F85: 75 VA with circuit breaker | H85: =IF(E85="","",VLOOKUP(A85,'Parts List'!A:F,6,FALSE)) -> 42.14 | I85: 0 | M85: =IF(H85="","",D85*H85) -> 0
A86: =E86&F86 -> Power Supply24VDC Panel Mounted - 1.3 A | B86: =IF(E86="","",VLOOKUP(A86,'Parts List'!A:E,5,FALSE)) -> PS5R-VB24 | D86: =$D$77*I86 -> 0 | E86: Power Supply | F86: 24VDC Panel Mounted - 1.3 A | H86: =IF(E86="","",VLOOKUP(A86,'Parts List'!A:F,6,FALSE)) -> 50.96 | I86: 0 | M86: =IF(H86="","",D86*H86) -> 0
A87: =E87&F87 -> Static Pressure TipsDuct Kit | B87: =IF(E87="","",VLOOKUP(A87,'Parts List'!A:E,5,FALSE)) -> A-302K + A-345k | D87: =$D$77*I87 -> 0 | E87: Static Pressure Tips | F87: Duct Kit | H87: =IF(E87="","",VLOOKUP(A87,'Parts List'!A:F,6,FALSE)) -> 17.9 | I87: 0 | M87: =IF(H87="","",D87*H87) -> 0
A88: =E88&F88 -> ThermostatLow Limit | B88: =IF(E88="","",VLOOKUP(A88,'Parts List'!A:E,5,FALSE)) -> A11A-1C | D88: =$D$77*I88 -> 0 | E88: Thermostat | F88: Low Limit | H88: =IF(E88="","",VLOOKUP(A88,'Parts List'!A:F,6,FALSE)) -> 270.31 | I88: 0 | M88: =IF(H88="","",D88*H88) -> 0
A89: =E89&F89 -> Filter StatusDigital Status | B89: =IF(E89="","",VLOOKUP(A89,'Parts List'!A:E,5,FALSE)) -> AFS-145 | D89: =$D$77*I89 -> 0 | E89: Filter Status | F89: Digital Status | H89: =IF(E89="","",VLOOKUP(A89,'Parts List'!A:F,6,FALSE)) -> 40.9 | I89: 0 | M89: =IF(H89="","",D89*H89) -> 0
A90: =E90&F90 -> Press TransmitterDuct Static Air | B90: =IF(E90="","",VLOOKUP(A90,'Parts List'!A:E,5,FALSE)) -> PX3DXX02 | D90: =$D$77*I90 -> 0 | E90: Press Transmitter | F90: Duct Static Air | H90: =IF(E90="","",VLOOKUP(A90,'Parts List'!A:F,6,FALSE)) -> 130.12 | I90: 0 | M90: =IF(H90="","",D90*H90) -> 0
A91: =E91&F91 -> Current SwDigital for VFD Status | B91: =IF(E91="","",VLOOKUP(A91,'Parts List'!A:E,5,FALSE)) -> H904 | D91: =$D$77*I91 -> 0 | E91: Current Sw | F91: Digital for VFD Status | H91: =IF(E91="","",VLOOKUP(A91,'Parts List'!A:F,6,FALSE)) -> 88.31 | I91: 0 | M91: =IF(H91="","",D91*H91) -> 0
A92: =E92&F92 -> Damper ActuatorLarge - Spring Return | B92: =IF(E92="","",VLOOKUP(A92,'Parts List'!A:E,5,FALSE)) -> MS7520A2007 | D92: =$D$77*I92 -> 0 | E92: Damper Actuator | F92: Large - Spring Return | H92: =IF(E92="","",VLOOKUP(A92,'Parts List'!A:F,6,FALSE)) -> 446.4658 | I92: 0 | M92: =IF(H92="","",D92*H92) -> 0
A93: =E93&F93 -> Temp SensorAveraging Sensor | B93: =IF(E93="","",VLOOKUP(A93,'Parts List'!A:E,5,FALSE)) -> C7041R2018 | D93: =$D$77*I93 -> 0 | E93: Temp Sensor | F93: Averaging Sensor | H93: =IF(E93="","",VLOOKUP(A93,'Parts List'!A:F,6,FALSE)) -> 166.9283 | I93: 0 | M93: =IF(H93="","",D93*H93) -> 0
A94: =E94&F94 -> Temp SensorDuct Temp/Humidity | B94: =IF(E94="","",VLOOKUP(A94,'Parts List'!A:E,5,FALSE)) -> H7735B2018 | D94: =$D$77*I94 -> 0 | E94: Temp Sensor | F94: Duct Temp/Humidity | H94: =IF(E94="","",VLOOKUP(A94,'Parts List'!A:F,6,FALSE)) -> 266.23465 | I94: 0 | M94: =IF(H94="","",D94*H94) -> 0
A95: =E95&F95 -> Humidity | B95: =IF(E95="","",VLOOKUP(A95,'Parts List'!A:E,5,FALSE)) -> Select Option | D95: =$D$77*I95 -> 0 | E95: Humidity | H95: =IF(E95="","",VLOOKUP(A95,'Parts List'!A:F,6,FALSE)) -> 0 | I95: 0 | M95: =IF(H95="","",D95*H95) -> 0
A96: =E96&F96 -> Humidity | B96: =IF(E96="","",VLOOKUP(A96,'Parts List'!A:E,5,FALSE)) -> Select Option | D96: =$D$77*I96 -> 0 | E96: Humidity | H96: =IF(E96="","",VLOOKUP(A96,'Parts List'!A:F,6,FALSE)) -> 0 | I96: 0 | M96: =IF(H96="","",D96*H96) -> 0
A97: =E97&F97 -> Carbon Dioxide SensorSpace CO2 wo LCD | B97: =IF(E97="","",VLOOKUP(A97,'Parts List'!A:E,5,FALSE)) -> C7263A1008 | D97: =$D$77*I97 -> 0 | E97: Carbon Dioxide Sensor | F97: Space CO2 wo LCD | H97: =IF(E97="","",VLOOKUP(A97,'Parts List'!A:F,6,FALSE)) -> 355.7389 | I97: 0 | M97: =IF(H97="","",D97*H97) -> 0
A98: =E98&F98 -> Carbon Dioxide SensorDuct CO2 wo LCD | B98: =IF(E98="","",VLOOKUP(A98,'Parts List'!A:E,5,FALSE)) -> C7632B1002 | D98: =$D$77*I98 -> 0 | E98: Carbon Dioxide Sensor | F98: Duct CO2 wo LCD | H98: =IF(E98="","",VLOOKUP(A98,'Parts List'!A:F,6,FALSE)) -> 331.2441 | I98: 0 | M98: =IF(H98="","",D98*H98) -> 0
A99: =E99&F99 -> Emergency Stop SwitchFlush Mtd | B99: =IF(E99="","",VLOOKUP(A99,'Parts List'!A:E,5,FALSE)) -> AOW401R + SSG1-67 | D99: =$D$77*I99 -> 0 | E99: Emergency Stop Switch | F99: Flush Mtd | H99: =IF(E99="","",VLOOKUP(A99,'Parts List'!A:F,6,FALSE)) -> 75.69 | I99: 0 | M99: =IF(H99="","",D99*H99) -> 0
A100: =E100&F100 -> Air Flow Monitor | B100: =IF(E100="","",VLOOKUP(A100,'Parts List'!A:E,5,FALSE)) -> Select Option | D100: =$D$77*I100 -> 0 | E100: Air Flow Monitor | H100: =IF(E100="","",VLOOKUP(A100,'Parts List'!A:F,6,FALSE)) -> 0 | I100: 0 | M100: =IF(H100="","",D100*H100) -> 0
A101: =E101&F101 -> See Valve Quote | B101: =IF(E101="","",VLOOKUP(A101,'Parts List'!A:E,5,FALSE)) -> N/A | D101: =$D$77*I101 -> 0 | E101: See Valve Quote | H101: =IF(E101="","",VLOOKUP(A101,'Parts List'!A:F,6,FALSE)) -> 0 | I101: 0 | M101: =IF(H101="","",D101*H101) -> 0
A102: =E102&F102 | B102: =IF(E102="","",VLOOKUP(A102,'Parts List'!A:E,5,FALSE)) | D102: =$D$77*I102 -> 0 | H102: =IF(E102="","",VLOOKUP(A102,'Parts List'!A:F,6,FALSE)) | I102: 1 | M102: =IF(H102="","",D102*H102) | N102: <- Duct Detector Interlock - Used for point count
A103: =E103&F103 | B103: =IF(E103="","",VLOOKUP(A103,'Parts List'!A:E,5,FALSE)) | D103: =$D$77*I103 -> 0 | H103: =IF(E103="","",VLOOKUP(A103,'Parts List'!A:F,6,FALSE)) | I103: 0 | M103: =IF(H103="","",D103*H103)
A104: =E104&F104 | B104: =IF(E104="","",VLOOKUP(A104,'Parts List'!A:E,5,FALSE)) | D104: =$D$77*I104 -> 0 | H104: =IF(E104="","",VLOOKUP(A104,'Parts List'!A:F,6,FALSE)) | I104: 0 | M104: =IF(H104="","",D104*H104)
A105: =E105&F105 | B105: =IF(E105="","",VLOOKUP(A105,'Parts List'!A:E,5,FALSE)) | H105: =IF(E105="","",VLOOKUP(A105,'Parts List'!A:F,6,FALSE)) | M105: =IF(H105="","",D105*H105)
A106: =E106&F106 -> Water Source Heat Pumps | D106: 0 | E106: Water Source Heat Pumps | I106: #/unit | N106: =SUM(I112:I120)+I108 -> 0 | O106: Pts/Unit | P106: =D106*N106 -> 0 | Q106: units | R106: =D106*S106 -> 0 | S106: 1500 | T106: per unit | V106: =D106*W106 -> 0 | W106: 3 | X106: per unit | Z106: =D106*AA106 -> 0 | AA106: 1 | AB106: per unit | AD106: =D106*AE106 -> 0 | AE106: 1 | AF106: per unit
A107: =E107&F107 -> Controller | B107: =IF(E107="","",VLOOKUP(A107,'Parts List'!A:E,5,FALSE)) -> Select Option | D107: =$D$106*I107 -> 0 | E107: Controller | H107: =IF(E107="","",VLOOKUP(A107,'Parts List'!A:F,6,FALSE)) -> 0 | I107: 0 | J107: =D107 -> 0 | K107: =D107*70 -> 0 | M107: =IF(H107="","",D107*H107) -> 0
A108: =E108&F108 -> Panel - Enclosure w Subpanel | B108: =IF(E108="","",VLOOKUP(A108,'Parts List'!A:E,5,FALSE)) -> Select Option | D108: =$D$106*I108 -> 0 | E108: Panel - Enclosure w Subpanel | H108: =IF(E108="","",VLOOKUP(A108,'Parts List'!A:F,6,FALSE)) -> 0 | I108: 0 | M108: =IF(H108="","",D108*H108) -> 0
A109: =E109&F109 -> Relay | B109: =IF(E109="","",VLOOKUP(A109,'Parts List'!A:E,5,FALSE)) -> Select Option | D109: =$D$106*I109 -> 0 | E109: Relay | H109: =IF(E109="","",VLOOKUP(A109,'Parts List'!A:F,6,FALSE)) -> 0 | I109: 0 | M109: =IF(H109="","",D109*H109) -> 0
A110: =E110&F110 -> Transformer | B110: =IF(E110="","",VLOOKUP(A110,'Parts List'!A:E,5,FALSE)) -> Select Option | D110: =$D$106*I110 -> 0 | E110: Transformer | H110: =IF(E110="","",VLOOKUP(A110,'Parts List'!A:F,6,FALSE)) -> 0 | I110: 0 | M110: =IF(H110="","",D110*H110) -> 0
A111: =E111&F111 -> Static Pressure Tips | B111: =IF(E111="","",VLOOKUP(A111,'Parts List'!A:E,5,FALSE)) -> N/A | D111: =$D$106*I111 -> 0 | E111: Static Pressure Tips | H111: =IF(E111="","",VLOOKUP(A111,'Parts List'!A:F,6,FALSE)) -> 0 | I111: 0 | M111: =IF(H111="","",D111*H111) -> 0
A112: =E112&F112 -> Current Sw | B112: =IF(E112="","",VLOOKUP(A112,'Parts List'!A:E,5,FALSE)) -> Select Option | D112: =$D$106*I112 -> 0 | E112: Current Sw | H112: =IF(E112="","",VLOOKUP(A112,'Parts List'!A:F,6,FALSE)) -> 0 | I112: 0 | M112: =IF(H112="","",D112*H112) -> 0
A113: =E113&F113 -> Filter Status | B113: =IF(E113="","",VLOOKUP(A113,'Parts List'!A:E,5,FALSE)) -> Select Option | D113: =$D$106*I113 -> 0 | E113: Filter Status | H113: =IF(E113="","",VLOOKUP(A113,'Parts List'!A:F,6,FALSE)) -> 0 | I113: 0 | M113: =IF(H113="","",D113*H113) -> 0
A114: =E114&F114 -> Communicating Room Thermostat | B114: =IF(E114="","",VLOOKUP(A114,'Parts List'!A:E,5,FALSE)) -> Select Option | D114: =$D$106*I114 -> 0 | E114: Communicating Room Thermostat | H114: =IF(E114="","",VLOOKUP(A114,'Parts List'!A:F,6,FALSE)) -> 0 | I114: 0 | J114: =D114 -> 0 | K114: =D114*50 -> 0 | M114: =IF(H114="","",D114*H114) -> 0
...

Sheet Estimate 3
B1: =Totals!B1 -> ESTIMATING SHEET VERSION 8.6 | G1: Salesman: | H1: =Totals!H1 -> 0 | L1: 1 | N1: <- 1=Page Used, 0=Page not used
B2: Job Name: | C2: =Totals!C2 -> 0 | G2: Estimator: | H2: =Totals!H2 -> 0 | L2: =Totals!L2 -> 0
B3: Part Number | D3: QTY. | E3: MATERIAL DESCRIPTON | H3: LIST $ | J3: # of Contrs | K3: # of Points | M3: TOTAL | R3: Electrical Price Check | V3: Tech | Z3: Graphics | AD3: Programming
D5: 0 | E5: VAV Boxes w Heat | F5: Option | I5: #/unit | N5: 1 | O5: Pts/VAV | P5: =D5*N5 -> 0 | Q5: points | R5: =P5*S5 -> 0 | S5: 550 | T5: per VAV | V5: =P5*W5 -> 0 | W5: 1 | X5: per VAV | Z5: =P5*AA5 -> 0 | AA5: 0.25 | AB5: per VAV | AD5: =P5*AE5 -> 0 | AE5: 0.25 | AF5: per VAV
A6: =E6&F6 -> ControllerOptimizer BACnet MSTP VAV Cntr w Act & VP, Bluetooth, 7 UIO, 5 SSR | B6: =IF(E6="","",VLOOKUP(A6,'Parts List'!A:E,5,FALSE)) -> VAA-VA75MB24NMC | D6: =$D$5*I6 -> 0 | E6: Controller | F6: Optimizer BACnet MSTP VAV Cntr w Act & VP, Bluetooth, 7 UIO, 5 SSR | H6: =IF(E6="","",VLOOKUP(A6,'Parts List'!A:F,6,FALSE)) -> 281.3558 | I6: 1 | J6: =D6 -> 0 | K6: =D6*70 -> 0 | M6: =IF(H6="","",D6*H6) -> 0
A7: =E7&F7 -> Temp SensorTR100 Space with LCD | B7: =IF(E7="","",VLOOKUP(A7,'Parts List'!A:E,5,FALSE)) -> TR100-T-G | D7: =$D$5*I7 -> 0 | E7: Temp Sensor | F7: TR100 Space with LCD | H7: =IF(E7="","",VLOOKUP(A7,'Parts List'!A:F,6,FALSE)) -> 128.71265 | I7: 1 | M7: =IF(H7="","",D7*H7) -> 0
A8: =E8&F8 -> Temp SensorDuct Insertion Sensor | B8: =IF(E8="","",VLOOKUP(A8,'Parts List'!A:E,5,FALSE)) -> C7041B2005 | D8: =$D$5*I8 -> 0 | E8: Temp Sensor | F8: Duct Insertion Sensor | H8: =IF(E8="","",VLOOKUP(A8,'Parts List'!A:F,6,FALSE)) -> 23.18855 | I8: 1 | M8: =IF(H8="","",D8*H8) -> 0
A9: =E9&F9 -> Current SwDigital Status Switch | B9: =IF(E9="","",VLOOKUP(A9,'Parts List'!A:E,5,FALSE)) -> H600 | D9: =$D$5*I9 -> 0 | E9: Current Sw | F9: Digital Status Switch | H9: =IF(E9="","",VLOOKUP(A9,'Parts List'!A:F,6,FALSE)) -> 31.43 | I9: 0 | M9: =IF(H9="","",D9*H9) -> 0
A10: =E10&F10 -> RelayRIB Pilot Relay | B10: =IF(E10="","",VLOOKUP(A10,'Parts List'!A:E,5,FALSE)) -> RIBU1C | D10: =$D$5*I10 -> 0 | E10: Relay | F10: RIB Pilot Relay | H10: =IF(E10="","",VLOOKUP(A10,'Parts List'!A:F,6,FALSE)) -> 14.36 | I10: 0 | M10: =IF(H10="","",D10*H10) -> 0
A11: =E11&F11 -> VAV HW Valve 2W & 3-way NSR | B11: =IF(E11="","",VLOOKUP(A11,'Parts List'!A:E,5,FALSE)) -> N/A | D11: =$D$5*I11 -> 0 | E11: VAV HW Valve 2W & 3-way NSR | H11: 150 | I11: 0 | M11: =IF(H11="","",D11*H11) -> 0
A12: =E12&F12 -> Air Flow MonitorRetrofit Flow Ring for VAV Boxes | B12: =IF(E12="","",VLOOKUP(A12,'Parts List'!A:E,5,FALSE)) -> 36FMI | D12: =$D$5*I12 -> 0 | E12: Air Flow Monitor | F12: Retrofit Flow Ring for VAV Boxes | H12: =IF(E12="","",VLOOKUP(A12,'Parts List'!A:F,6,FALSE)) -> 95 | I12: 0 | M12: =IF(H12="","",D12*H12) -> 0
B13: =IF(E13="","",VLOOKUP(A13,'Parts List'!A:E,5,FALSE)) | H13: =IF(E13="","",VLOOKUP(A13,'Parts List'!A:F,6,FALSE)) | M13: =IF(H13="","",D13*H13)
A15: =E15&F15 -> Cooling Only VAV Boxes | D15: 0 | E15: Cooling Only VAV Boxes | I15: #/unit | N15: 1 | O15: Pts/VAV | P15: =D15*N15 -> 0 | Q15: points | R15: =P15*S15 -> 0 | S15: 550 | T15: per VAV | V15: =P15*W15 -> 0 | W15: 1 | X15: per VAV | Z15: =P15*AA15 -> 0 | AA15: 0.25 | AB15: per VAV | AD15: =P15*AE15 -> 0 | AE15: 0.25 | AF15: per VAV
A16: =E16&F16 -> ControllerOptimizer BACnet MSTP VAV Cntr w Act & VP, Bluetooth, 7 UIO, 5 SSR | B16: =IF(E16="","",VLOOKUP(A16,'Parts List'!A:E,5,FALSE)) -> VAA-VA75MB24NMC | D16: =$D$15*I16 -> 0 | E16: Controller | F16: Optimizer BACnet MSTP VAV Cntr w Act & VP, Bluetooth, 7 UIO, 5 SSR | H16: =IF(E16="","",VLOOKUP(A16,'Parts List'!A:F,6,FALSE)) -> 281.3558 | I16: 1 | J16: =D16 -> 0 | K16: =D16*70 -> 0 | M16: =IF(H16="","",D16*H16) -> 0
A17: =E17&F17 -> Temp SensorTR100 Space with LCD | B17: =IF(E17="","",VLOOKUP(A17,'Parts List'!A:E,5,FALSE)) -> TR100-T-G | D17: =$D$15*I17 -> 0 | E17: Temp Sensor | F17: TR100 Space with LCD | H17: =IF(E17="","",VLOOKUP(A17,'Parts List'!A:F,6,FALSE)) -> 128.71265 | I17: 1 | M17: =IF(H17="","",D17*H17) -> 0
A18: =E18&F18 -> Transformer40 VA | B18: =IF(E18="","",VLOOKUP(A18,'Parts List'!A:E,5,FALSE)) -> TR40VA001 | D18: =$D$15*I18 -> 0 | E18: Transformer | F18: 40 VA | H18: =IF(E18="","",VLOOKUP(A18,'Parts List'!A:F,6,FALSE)) -> 17.76 | I18: 0 | M18: =IF(H18="","",D18*H18) -> 0
A19: =E19&F19 -> Air Flow MonitorRetrofit Flow Ring for VAV Boxes | B19: =IF(E19="","",VLOOKUP(A19,'Parts List'!A:E,5,FALSE)) -> 36FMI | D19: =$D$15*I19 -> 0 | E19: Air Flow Monitor | F19: Retrofit Flow Ring for VAV Boxes | H19: =IF(E19="","",VLOOKUP(A19,'Parts List'!A:F,6,FALSE)) -> 95 | I19: 0 | M19: =IF(H19="","",D19*H19) -> 0
B20: =IF(E20="","",VLOOKUP(A20,'Parts List'!A:E,5,FALSE)) | H20: =IF(E20="","",VLOOKUP(A20,'Parts List'!A:F,6,FALSE)) | M20: =IF(H20="","",D20*H20)
D23: 0 | E23: Supply Air Boxes - CRC/Phoenix LV Wiring and Integration | I23: #/unit | N23: 1 | O23: Pts/VAV | P23: =D23*N23 -> 0 | Q23: points | R23: =P23*S23 -> 0 | S23: 750 | T23: per VAV | V23: =P23*W23 -> 0 | W23: 1 | X23: per VAV | Z23: =P23*AA23 -> 0 | AA23: 0.25 | AB23: per VAV | AD23: =P23*AE23 -> 0 | AE23: 0.25 | AF23: per VAV
A24: =E24&F24 | B24: =IF(E24="","",VLOOKUP(A24,'[2]Parts List'!A:E,5,FALSE)) | D24: =$D$23*I24 -> 0 | H24: =IF(E24="","",VLOOKUP(A24,'[2]Parts List'!A:F,6,FALSE)) | I24: 1 | J24: =D24 -> 0 | K24: =D24*50 -> 0 | M24: =IF(H24="","",D24*H24)
D27: 0 | E27: Exhaust Air Boxes - CRC/Phoenix LV Wiring and Integration | I27: #/unit | N27: 1 | O27: Pts/VAV | P27: =D27*N27 -> 0 | Q27: points | R27: =P27*S27 -> 0 | S27: 750 | T27: per VAV | V27: =P27*W27 -> 0 | W27: 1 | X27: per VAV | Z27: =P27*AA27 -> 0 | AA27: 0.25 | AB27: per VAV | AD27: =P27*AE27 -> 0 | AE27: 0.25 | AF27: per VAV
A28: =E28&F28 | B28: =IF(E28="","",VLOOKUP(A28,'[2]Parts List'!A:E,5,FALSE)) | D28: =$D$27*I28 -> 0 | H28: =IF(E28="","",VLOOKUP(A28,'[2]Parts List'!A:F,6,FALSE)) | I28: 1 | M28: =IF(H28="","",D28*H28)
D31: 0 | E31: Return Air Boxes - CRC/Phoenix LV Wiring and Integration | I31: #/unit | N31: 1 | O31: Pts/VAV | P31: =D31*N31 -> 0 | Q31: points | R31: =P31*S31 -> 0 | S31: 750 | T31: per VAV | V31: =P31*W31 -> 0 | W31: 1 | X31: per VAV | Z31: =P31*AA31 -> 0 | AA31: 0.25 | AB31: per VAV | AD31: =P31*AE31 -> 0 | AE31: 0.25 | AF31: per VAV
A32: =E32&F32 | B32: =IF(E32="","",VLOOKUP(A32,'[2]Parts List'!A:E,5,FALSE)) | D32: =$D$31*I32 -> 0 | H32: =IF(E32="","",VLOOKUP(A32,'[2]Parts List'!A:F,6,FALSE)) | I32: 1 | M32: =IF(H32="","",D32*H32)
D35: 0 | E35: OR Room Pressure Monitors - CRC/Phoenix LV Wiring and Integration | I35: #/unit | N35: 1 | O35: Pts/VAV | P35: =D35*N35 -> 0 | Q35: points | R35: =P35*S35 -> 0 | S35: 750 | T35: per VAV | V35: =P35*W35 -> 0 | W35: 1 | X35: per VAV | Z35: =P35*AA35 -> 0 | AA35: 0.25 | AB35: per VAV | AD35: =P35*AE35 -> 0 | AE35: 0.25 | AF35: per VAV
A36: =E36&F36 | B36: =IF(E36="","",VLOOKUP(A36,'[2]Parts List'!A:E,5,FALSE)) | D36: =$D$35*I36 -> 0 | H36: =IF(E36="","",VLOOKUP(A36,'[2]Parts List'!A:F,6,FALSE)) | I36: 1 | M36: =IF(H36="","",D36*H36)
A40: =E40&F40 -> Cooling Only VAV Box Transformers | D40: 0 | E40: Cooling Only VAV Box Transformers | I40: #/unit | N40: =SUM(I41:I43) -> 0 | O40: Pts/Unit | P40: =D40*N40 -> 0 | Q40: points | R40: =P40*S40 -> 0 | S40: 550 | T40: per Unit | V40: =P40*W40 -> 0 | W40: 0 | X40: per unit | Z40: =D40*AA40 -> 0 | AA40: 0 | AB40: per unit | AD40: =D40*AE40 -> 0 | AE40: 0 | AF40: per unit
A41: =E41&F41 -> Transformer(3) - 100 VA w Enclosure | B41: =IF(E41="","",VLOOKUP(A41,'Parts List'!A:E,5,FALSE)) -> PSH300A | D41: =$D$40*I41 -> 0 | E41: Transformer | F41: (3) - 100 VA w Enclosure | H41: =IF(E41="","",VLOOKUP(A41,'Parts List'!A:F,6,FALSE)) -> 314.8 | I41: 0 | M41: =IF(H41="","",D41*H41) -> 0
A42: =E42&F42 -> Transformer(5) - 100 VA w Enclosure | B42: =IF(E42="","",VLOOKUP(A42,'Parts List'!A:E,5,FALSE)) -> PSH500A | D42: =$D$40*I42 -> 0 | E42: Transformer | F42: (5) - 100 VA w Enclosure | H42: =IF(E42="","",VLOOKUP(A42,'Parts List'!A:F,6,FALSE)) -> 430.65 | I42: 0 | M42: =IF(H42="","",D42*H42) -> 0
A43: =E43&F43 | B43: =IF(E43="","",VLOOKUP(A43,'Parts List'!A:E,5,FALSE)) | D43: =$D$40*I43 -> 0 | H43: =IF(E43="","",VLOOKUP(A43,'Parts List'!A:F,6,FALSE)) | I43: 0 | M43: =IF(H43="","",D43*H43)
B44: =IF(E44="","",VLOOKUP(A44,'Parts List'!A:E,5,FALSE)) | H44: =IF(E44="","",VLOOKUP(A44,'Parts List'!A:F,6,FALSE)) | M44: =IF(H44="","",D44*H44)
A46: =E46&F46 -> VAV Air Handling Unit | D46: 0 | E46: VAV Air Handling Unit | I46: #/unit | N46: =SUM(I57:I73)+I52 -> 1 | O46: Pts/Unit | P46: =D46*N46 -> 0 | Q46: points | R46: =P46*S46 -> 0 | S46: 350 | T46: per point | V46: =P46*W46 -> 0 | W46: 1 | X46: per point | Z46: =D46*AA46 -> 0 | AA46: 4 | AB46: per unit | AD46: =D46*AE46 -> 0 | AE46: 6 | AF46: per unit
A47: =E47&F47 -> ControllerOptimizer Plant Cntr, 1 IP, 3 Ethernet Switched+4 RS485 Ports | B47: =IF(E47="","",VLOOKUP(A47,'Parts List'!A:E,5,FALSE)) -> N-ADV-134-H-C | D47: =$D$46*I47 -> 0 | E47: Controller | F47: Optimizer Plant Cntr, 1 IP, 3 Ethernet Switched+4 RS485 Ports | H47: =IF(E47="","",VLOOKUP(A47,'Parts List'!A:F,6,FALSE)) -> 875.1457 | I47: 0 | J47: =D47 -> 0 | K47: =D47*70 -> 0 | M47: =IF(H47="","",D47*H47) -> 0
A48: =E48&F48 -> Optimizer License with 18 Month SMA | B48: =IF(E48="","",VLOOKUP(A48,'Parts List'!A:E,5,FALSE)) -> Select Option | D48: =$D$46*I48 -> 0 | E48: Optimizer License with 18 Month SMA | H48: =IF(E48="","",VLOOKUP(A48,'Parts List'!A:F,6,FALSE)) -> 0 | I48: 0 | J48: =D48 -> 0 | K48: =D48*70 -> 0 | M48: =IF(H48="","",D48*H48) -> 0
A49: =E49&F49 -> I/O ModuleOptimzer Unitary Cntr 5-UI, 5-DI, 4-AO, 4-DO I/O Module | B49: =IF(E49="","",VLOOKUP(A49,'Parts List'!A:E,5,FALSE)) -> ISMA-B-MIX18 | D49: =$D$46*I49 -> 0 | E49: I/O Module | F49: Optimzer Unitary Cntr 5-UI, 5-DI, 4-AO, 4-DO I/O Module | H49: =IF(E49="","",VLOOKUP(A49,'Parts List'!A:F,6,FALSE)) -> 338.81 | I49: 0 | M49: =IF(H49="","",D49*H49) -> 0
A50: =E50&F50 -> Phoenix Controller Core License | B50: =IF(E50="","",VLOOKUP(A50,'Parts List'!A:E,5,FALSE)) -> Select Option | D50: =$D$46*I50 -> 0 | E50: Phoenix Controller Core License | H50: =IF(E50="","",VLOOKUP(A50,'Parts List'!A:F,6,FALSE)) -> 0 | I50: 0 | M50: =IF(H50="","",D50*H50) -> 0
A51: =E51&F51 -> Phoenix ILC SMA | B51: =IF(E51="","",VLOOKUP(A51,'Parts List'!A:E,5,FALSE)) -> Select Option | D51: =$D$46*I51 -> 0 | E51: Phoenix ILC SMA | H51: =IF(E51="","",VLOOKUP(A51,'Parts List'!A:F,6,FALSE)) -> 0 | I51: 0 | M51: =IF(H51="","",D51*H51) -> 0
A52: =E52&F52 -> Panel - Enclosure w SubpanelNema-1 Medium | B52: =IF(E52="","",VLOOKUP(A52,'Parts List'!A:E,5,FALSE)) -> RET1-262007BT-P | D52: =$D$46*I52 -> 0 | E52: Panel - Enclosure w Subpanel | F52: Nema-1 Medium | H52: =IF(E52="","",VLOOKUP(A52,'Parts List'!A:F,6,FALSE)) -> 436.83 | I52: 0 | M52: =IF(H52="","",D52*H52) -> 0
A53: =E53&F53 -> Relay24VAC DPDT with Base | B53: =IF(E53="","",VLOOKUP(A53,'Parts List'!A:E,5,FALSE)) -> RH2B-UAC24 + SH2B-05 | D53: =$D$46*I53 -> 0 | E53: Relay | F53: 24VAC DPDT with Base | H53: =IF(E53="","",VLOOKUP(A53,'Parts List'!A:F,6,FALSE)) -> 8.12 | I53: 0 | M53: =IF(H53="","",D53*H53) -> 0
A54: =E54&F54 -> Transformer75 VA with circuit breaker | B54: =IF(E54="","",VLOOKUP(A54,'Parts List'!A:E,5,FALSE)) -> TR75VA004 | D54: =$D$46*I54 -> 0 | E54: Transformer | F54: 75 VA with circuit breaker | H54: =IF(E54="","",VLOOKUP(A54,'Parts List'!A:F,6,FALSE)) -> 42.14 | I54: 0 | M54: =IF(H54="","",D54*H54) -> 0
A55: =E55&F55 -> Power Supply24VDC Panel Mounted - 1.3 A | B55: =IF(E55="","",VLOOKUP(A55,'Parts List'!A:E,5,FALSE)) -> PS5R-VB24 | D55: =$D$46*I55 -> 0 | E55: Power Supply | F55: 24VDC Panel Mounted - 1.3 A | H55: =IF(E55="","",VLOOKUP(A55,'Parts List'!A:F,6,FALSE)) -> 50.96 | I55: 0 | M55: =IF(H55="","",D55*H55) -> 0
A56: =E56&F56 -> Static Pressure TipsDuct Kit | B56: =IF(E56="","",VLOOKUP(A56,'Parts List'!A:E,5,FALSE)) -> A-302K + A-345k | D56: =$D$46*I56 -> 0 | E56: Static Pressure Tips | F56: Duct Kit | H56: =IF(E56="","",VLOOKUP(A56,'Parts List'!A:F,6,FALSE)) -> 17.9 | I56: 0 | M56: =IF(H56="","",D56*H56) -> 0
A57: =E57&F57 -> ThermostatLow Limit | B57: =IF(E57="","",VLOOKUP(A57,'Parts List'!A:E,5,FALSE)) -> A11A-1C | D57: =$D$46*I57 -> 0 | E57: Thermostat | F57: Low Limit | H57: =IF(E57="","",VLOOKUP(A57,'Parts List'!A:F,6,FALSE)) -> 270.31 | I57: 0 | M57: =IF(H57="","",D57*H57) -> 0
A58: =E58&F58 -> Filter StatusDigital Status | B58: =IF(E58="","",VLOOKUP(A58,'Parts List'!A:E,5,FALSE)) -> AFS-145 | D58: =$D$46*I58 -> 0 | E58: Filter Status | F58: Digital Status | H58: =IF(E58="","",VLOOKUP(A58,'Parts List'!A:F,6,FALSE)) -> 40.9 | I58: 0 | M58: =IF(H58="","",D58*H58) -> 0
A59: =E59&F59 -> Press TransmitterDuct Static Air | B59: =IF(E59="","",VLOOKUP(A59,'Parts List'!A:E,5,FALSE)) -> PX3DXX02 | D59: =$D$46*I59 -> 0 | E59: Press Transmitter | F59: Duct Static Air | H59: =IF(E59="","",VLOOKUP(A59,'Parts List'!A:F,6,FALSE)) -> 130.12 | I59: 0 | M59: =IF(H59="","",D59*H59) -> 0
A60: =E60&F60 -> Press Transmitter | B60: =IF(E60="","",VLOOKUP(A60,'Parts List'!A:E,5,FALSE)) -> Select Option | D60: =$D$46*I60 -> 0 | E60: Press Transmitter | H60: =IF(E60="","",VLOOKUP(A60,'Parts List'!A:F,6,FALSE)) -> 0 | I60: 0 | M60: =IF(H60="","",D60*H60) -> 0
A61: =E61&F61 -> Press TransmitterHigh Static Limit Switch | B61: =IF(E61="","",VLOOKUP(A61,'Parts List'!A:E,5,FALSE)) -> 1900-5-MR | D61: =$D$46*I61 -> 0 | E61: Press Transmitter | F61: High Static Limit Switch | H61: =IF(E61="","",VLOOKUP(A61,'Parts List'!A:F,6,FALSE)) -> 111.93 | I61: 0 | M61: =IF(H61="","",D61*H61) -> 0
A62: =E62&F62 -> Current SwDigital for VFD Status | B62: =IF(E62="","",VLOOKUP(A62,'Parts List'!A:E,5,FALSE)) -> H904 | D62: =$D$46*I62 -> 0 | E62: Current Sw | F62: Digital for VFD Status | H62: =IF(E62="","",VLOOKUP(A62,'Parts List'!A:F,6,FALSE)) -> 88.31 | I62: 0 | M62: =IF(H62="","",D62*H62) -> 0
A63: =E63&F63 -> Damper ActuatorLarge - Spring Return | B63: =IF(E63="","",VLOOKUP(A63,'Parts List'!A:E,5,FALSE)) -> MS7520A2007 | D63: =$D$46*I63 -> 0 | E63: Damper Actuator | F63: Large - Spring Return | H63: =IF(E63="","",VLOOKUP(A63,'Parts List'!A:F,6,FALSE)) -> 446.4658 | I63: 0 | M63: =IF(H63="","",D63*H63) -> 0
A64: =E64&F64 -> Temp SensorAveraging Sensor | B64: =IF(E64="","",VLOOKUP(A64,'Parts List'!A:E,5,FALSE)) -> C7041R2018 | D64: =$D$46*I64 -> 0 | E64: Temp Sensor | F64: Averaging Sensor | H64: =IF(E64="","",VLOOKUP(A64,'Parts List'!A:F,6,FALSE)) -> 166.9283 | I64: 0 | M64: =IF(H64="","",D64*H64) -> 0
A65: =E65&F65 -> Temp SensorDuct Temp/Humidity | B65: =IF(E65="","",VLOOKUP(A65,'Parts List'!A:E,5,FALSE)) -> H7735B2018 | D65: =$D$46*I65 -> 0 | E65: Temp Sensor | F65: Duct Temp/Humidity | H65: =IF(E65="","",VLOOKUP(A65,'Parts List'!A:F,6,FALSE)) -> 266.23465 | I65: 0 | M65: =IF(H65="","",D65*H65) -> 0
A66: =E66&F66 -> Humidity | B66: =IF(E66="","",VLOOKUP(A66,'Parts List'!A:E,5,FALSE)) -> Select Option | D66: =$D$46*I66 -> 0 | E66: Humidity | H66: =IF(E66="","",VLOOKUP(A66,'Parts List'!A:F,6,FALSE)) -> 0 | I66: 0 | M66: =IF(H66="","",D66*H66) -> 0
A67: =E67&F67 -> Humidity | B67: =IF(E67="","",VLOOKUP(A67,'Parts List'!A:E,5,FALSE)) -> Select Option | D67: =$D$46*I67 -> 0 | E67: Humidity | H67: =IF(E67="","",VLOOKUP(A67,'Parts List'!A:F,6,FALSE)) -> 0 | I67: 0 | M67: =IF(H67="","",D67*H67) -> 0
A68: =E68&F68 -> Carbon Dioxide SensorSpace CO2 wo LCD | B68: =IF(E68="","",VLOOKUP(A68,'Parts List'!A:E,5,FALSE)) -> C7263A1008 | D68: =$D$46*I68 -> 0 | E68: Carbon Dioxide Sensor | F68: Space CO2 wo LCD | H68: =IF(E68="","",VLOOKUP(A68,'Parts List'!A:F,6,FALSE)) -> 355.7389 | I68: 0 | M68: =IF(H68="","",D68*H68) -> 0
A69: =E69&F69 -> Carbon Dioxide SensorDuct CO2 wo LCD | B69: =IF(E69="","",VLOOKUP(A69,'Parts List'!A:E,5,FALSE)) -> C7632B1002 | D69: =$D$46*I69 -> 0 | E69: Carbon Dioxide Sensor | F69: Duct CO2 wo LCD | H69: =IF(E69="","",VLOOKUP(A69,'Parts List'!A:F,6,FALSE)) -> 331.2441 | I69: 0 | M69: =IF(H69="","",D69*H69) -> 0
A70: =E70&F70 -> Emergency Stop SwitchFlush Mtd | B70: =IF(E70="","",VLOOKUP(A70,'Parts List'!A:E,5,FALSE)) -> AOW401R + SSG1-67 | D70: =$D$46*I70 -> 0 | E70: Emergency Stop Switch | F70: Flush Mtd | H70: =IF(E70="","",VLOOKUP(A70,'Parts List'!A:F,6,FALSE)) -> 75.69 | I70: 0 | M70: =IF(H70="","",D70*H70) -> 0
A71: =E71&F71 -> Air Flow Monitor | B71: =IF(E71="","",VLOOKUP(A71,'Parts List'!A:E,5,FALSE)) -> Select Option | D71: =$D$46*I71 -> 0 | E71: Air Flow Monitor | H71: =IF(E71="","",VLOOKUP(A71,'Parts List'!A:F,6,FALSE)) -> 0 | I71: 0 | M71: =IF(H71="","",D71*H71) -> 0
A72: =E72&F72 -> See Valve Quote | B72: =IF(E72="","",VLOOKUP(A72,'Parts List'!A:E,5,FALSE)) -> N/A | D72: =$D$46*I72 -> 0 | E72: See Valve Quote | H72: =IF(E72="","",VLOOKUP(A72,'Parts List'!A:F,6,FALSE)) -> 0 | I72: 0 | M72: =IF(H72="","",D72*H72) -> 0
A73: =E73&F73 | B73: =IF(E73="","",VLOOKUP(A73,'Parts List'!A:E,5,FALSE)) | D73: =$D$46*I73 -> 0 | H73: =IF(E73="","",VLOOKUP(A73,'Parts List'!A:F,6,FALSE)) | I73: 1 | M73: =IF(H73="","",D73*H73) | N73: <- Duct Detector Interlock - Used for point count
A74: =E74&F74 | B74: =IF(E74="","",VLOOKUP(A74,'Parts List'!A:E,5,FALSE)) | D74: =$D$46*I74 -> 0 | H74: =IF(E74="","",VLOOKUP(A74,'Parts List'!A:F,6,FALSE)) | I74: 0 | M74: =IF(H74="","",D74*H74)
A75: =E75&F75 | B75: =IF(E75="","",VLOOKUP(A75,'Parts List'!A:E,5,FALSE)) | D75: =$D$46*I75 -> 0 | H75: =IF(E75="","",VLOOKUP(A75,'Parts List'!A:F,6,FALSE)) | I75: 0 | M75: =IF(H75="","",D75*H75)
A76: =E76&F76 | B76: =IF(E76="","",VLOOKUP(A76,'Parts List'!A:E,5,FALSE)) | H76: =IF(E76="","",VLOOKUP(A76,'Parts List'!A:F,6,FALSE)) | M76: =IF(H76="","",D76*H76)
A77: =E77&F77 -> Constant Volume Air Handling Units | D77: 0 | E77: Constant Volume Air Handling Units | I77: #/unit | N77: =SUM(I88:I102)+I83 -> 1 | O77: Pts/Unit | P77: =D77*N77 -> 0 | Q77: units | R77: =P77*S77 -> 0 | S77: 350 | T77: per point | V77: =P77*W77 -> 0 | W77: 1 | X77: per point | Z77: =D77*AA77 -> 0 | AA77: 4 | AB77: per unit | AD77: =D77*AE77 -> 0 | AE77: 6 | AF77: per unit
A78: =E78&F78 -> ControllerOptimizer Plant Cntr, 1 IP, 3 Ethernet Switched+4 RS485 Ports | B78: =IF(E78="","",VLOOKUP(A78,'Parts List'!A:E,5,FALSE)) -> N-ADV-134-H-C | D78: =$D$77*I78 -> 0 | E78: Controller | F78: Optimizer Plant Cntr, 1 IP, 3 Ethernet Switched+4 RS485 Ports | H78: =IF(E78="","",VLOOKUP(A78,'Parts List'!A:F,6,FALSE)) -> 875.1457 | I78: 0 | J78: =D78 -> 0 | K78: =D78*70 -> 0 | M78: =IF(H78="","",D78*H78) -> 0
A79: =E79&F79 -> Optimizer License with 18 Month SMA | B79: =IF(E79="","",VLOOKUP(A79,'Parts List'!A:E,5,FALSE)) -> Select Option | D79: =$D$77*I79 -> 0 | E79: Optimizer License with 18 Month SMA | H79: =IF(E79="","",VLOOKUP(A79,'Parts List'!A:F,6,FALSE)) -> 0 | I79: 0 | J79: =D79 -> 0 | K79: =D79*70 -> 0 | M79: =IF(H79="","",D79*H79) -> 0
A80: =E80&F80 -> I/O ModuleOptimzer Unitary Cntr 5-UI, 5-DI, 4-AO, 4-DO I/O Module | B80: =IF(E80="","",VLOOKUP(A80,'Parts List'!A:E,5,FALSE)) -> ISMA-B-MIX18 | D80: =$D$77*I80 -> 0 | E80: I/O Module | F80: Optimzer Unitary Cntr 5-UI, 5-DI, 4-AO, 4-DO I/O Module | H80: =IF(E80="","",VLOOKUP(A80,'Parts List'!A:F,6,FALSE)) -> 338.81 | I80: 0 | M80: =IF(H80="","",D80*H80) -> 0
A81: =E81&F81 -> Phoenix Controller Core License | B81: =IF(E81="","",VLOOKUP(A81,'Parts List'!A:E,5,FALSE)) -> Select Option | D81: =$D$77*I81 -> 0 | E81: Phoenix Controller Core License | H81: =IF(E81="","",VLOOKUP(A81,'Parts List'!A:F,6,FALSE)) -> 0 | I81: 0 | M81: =IF(H81="","",D81*H81) -> 0
A82: =E82&F82 -> Phoenix ILC SMA | B82: =IF(E82="","",VLOOKUP(A82,'Parts List'!A:E,5,FALSE)) -> Select Option | D82: =$D$77*I82 -> 0 | E82: Phoenix ILC SMA | H82: =IF(E82="","",VLOOKUP(A82,'Parts List'!A:F,6,FALSE)) -> 0 | I82: 0 | M82: =IF(H82="","",D82*H82) -> 0
A83: =E83&F83 -> Panel - Enclosure w SubpanelNema-1 Medium | B83: =IF(E83="","",VLOOKUP(A83,'Parts List'!A:E,5,FALSE)) -> RET1-262007BT-P | D83: =$D$77*I83 -> 0 | E83: Panel - Enclosure w Subpanel | F83: Nema-1 Medium | H83: =IF(E83="","",VLOOKUP(A83,'Parts List'!A:F,6,FALSE)) -> 436.83 | I83: 0 | M83: =IF(H83="","",D83*H83) -> 0
A84: =E84&F84 -> Relay24VAC DPDT with Base | B84: =IF(E84="","",VLOOKUP(A84,'Parts List'!A:E,5,FALSE)) -> RH2B-UAC24 + SH2B-05 | D84: =$D$77*I84 -> 0 | E84: Relay | F84: 24VAC DPDT with Base | H84: =IF(E84="","",VLOOKUP(A84,'Parts List'!A:F,6,FALSE)) -> 8.12 | I84: 0 | M84: =IF(H84="","",D84*H84) -> 0
A85: =E85&F85 -> Transformer75 VA with circuit breaker | B85: =IF(E85="","",VLOOKUP(A85,'Parts List'!A:E,5,FALSE)) -> TR75VA004 | D85: =$D$77*I85 -> 0 | E85: Transformer | F85: 75 VA with circuit breaker | H85: =IF(E85="","",VLOOKUP(A85,'Parts List'!A:F,6,FALSE)) -> 42.14 | I85: 0 | M85: =IF(H85="","",D85*H85) -> 0
A86: =E86&F86 -> Power Supply24VDC Panel Mounted - 1.3 A | B86: =IF(E86="","",VLOOKUP(A86,'Parts List'!A:E,5,FALSE)) -> PS5R-VB24 | D86: =$D$77*I86 -> 0 | E86: Power Supply | F86: 24VDC Panel Mounted - 1.3 A | H86: =IF(E86="","",VLOOKUP(A86,'Parts List'!A:F,6,FALSE)) -> 50.96 | I86: 0 | M86: =IF(H86="","",D86*H86) -> 0
A87: =E87&F87 -> Static Pressure TipsDuct Kit | B87: =IF(E87="","",VLOOKUP(A87,'Parts List'!A:E,5,FALSE)) -> A-302K + A-345k | D87: =$D$77*I87 -> 0 | E87: Static Pressure Tips | F87: Duct Kit | H87: =IF(E87="","",VLOOKUP(A87,'Parts List'!A:F,6,FALSE)) -> 17.9 | I87: 0 | M87: =IF(H87="","",D87*H87) -> 0
A88: =E88&F88 -> ThermostatLow Limit | B88: =IF(E88="","",VLOOKUP(A88,'Parts List'!A:E,5,FALSE)) -> A11A-1C | D88: =$D$77*I88 -> 0 | E88: Thermostat | F88: Low Limit | H88: =IF(E88="","",VLOOKUP(A88,'Parts List'!A:F,6,FALSE)) -> 270.31 | I88: 0 | M88: =IF(H88="","",D88*H88) -> 0
A89: =E89&F89 -> Filter StatusDigital Status | B89: =IF(E89="","",VLOOKUP(A89,'Parts List'!A:E,5,FALSE)) -> AFS-145 | D89: =$D$77*I89 -> 0 | E89: Filter Status | F89: Digital Status | H89: =IF(E89="","",VLOOKUP(A89,'Parts List'!A:F,6,FALSE)) -> 40.9 | I89: 0 | M89: =IF(H89="","",D89*H89) -> 0
A90: =E90&F90 -> Press TransmitterDuct Static Air | B90: =IF(E90="","",VLOOKUP(A90,'Parts List'!A:E,5,FALSE)) -> PX3DXX02 | D90: =$D$77*I90 -> 0 | E90: Press Transmitter | F90: Duct Static Air | H90: =IF(E90="","",VLOOKUP(A90,'Parts List'!A:F,6,FALSE)) -> 130.12 | I90: 0 | M90: =IF(H90="","",D90*H90) -> 0
A91: =E91&F91 -> Current SwDigital for VFD Status | B91: =IF(E91="","",VLOOKUP(A91,'Parts List'!A:E,5,FALSE)) -> H904 | D91: =$D$77*I91 -> 0 | E91: Current Sw | F91: Digital for VFD Status | H91: =IF(E91="","",VLOOKUP(A91,'Parts List'!A:F,6,FALSE)) -> 88.31 | I91: 0 | M91: =IF(H91="","",D91*H91) -> 0
A92: =E92&F92 -> Damper ActuatorLarge - Spring Return | B92: =IF(E92="","",VLOOKUP(A92,'Parts List'!A:E,5,FALSE)) -> MS7520A2007 | D92: =$D$77*I92 -> 0 | E92: Damper Actuator | F92: Large - Spring Return | H92: =IF(E92="","",VLOOKUP(A92,'Parts List'!A:F,6,FALSE)) -> 446.4658 | I92: 0 | M92: =IF(H92="","",D92*H92) -> 0
A93: =E93&F93 -> Temp SensorAveraging Sensor | B93: =IF(E93="","",VLOOKUP(A93,'Parts List'!A:E,5,FALSE)) -> C7041R2018 | D93: =$D$77*I93 -> 0 | E93: Temp Sensor | F93: Averaging Sensor | H93: =IF(E93="","",VLOOKUP(A93,'Parts List'!A:F,6,FALSE)) -> 166.9283 | I93: 0 | M93: =IF(H93="","",D93*H93) -> 0
A94: =E94&F94 -> Temp SensorDuct Temp/Humidity | B94: =IF(E94="","",VLOOKUP(A94,'Parts List'!A:E,5,FALSE)) -> H7735B2018 | D94: =$D$77*I94 -> 0 | E94: Temp Sensor | F94: Duct Temp/Humidity | H94: =IF(E94="","",VLOOKUP(A94,'Parts List'!A:F,6,FALSE)) -> 266.23465 | I94: 0 | M94: =IF(H94="","",D94*H94) -> 0
A95: =E95&F95 -> Humidity | B95: =IF(E95="","",VLOOKUP(A95,'Parts List'!A:E,5,FALSE)) -> Select Option | D95: =$D$77*I95 -> 0 | E95: Humidity | H95: =IF(E95="","",VLOOKUP(A95,'Parts List'!A:F,6,FALSE)) -> 0 | I95: 0 | M95: =IF(H95="","",D95*H95) -> 0
A96: =E96&F96 -> Humidity | B96: =IF(E96="","",VLOOKUP(A96,'Parts List'!A:E,5,FALSE)) -> Select Option | D96: =$D$77*I96 -> 0 | E96: Humidity | H96: =IF(E96="","",VLOOKUP(A96,'Parts List'!A:F,6,FALSE)) -> 0 | I96: 0 | M96: =IF(H96="","",D96*H96) -> 0
A97: =E97&F97 -> Carbon Dioxide SensorSpace CO2 wo LCD | B97: =IF(E97="","",VLOOKUP(A97,'Parts List'!A:E,5,FALSE)) -> C7263A1008 | D97: =$D$77*I97 -> 0 | E97: Carbon Dioxide Sensor | F97: Space CO2 wo LCD | H97: =IF(E97="","",VLOOKUP(A97,'Parts List'!A:F,6,FALSE)) -> 355.7389 | I97: 0 | M97: =IF(H97="","",D97*H97) -> 0
A98: =E98&F98 -> Carbon Dioxide SensorDuct CO2 wo LCD | B98: =IF(E98="","",VLOOKUP(A98,'Parts List'!A:E,5,FALSE)) -> C7632B1002 | D98: =$D$77*I98 -> 0 | E98: Carbon Dioxide Sensor | F98: Duct CO2 wo LCD | H98: =IF(E98="","",VLOOKUP(A98,'Parts List'!A:F,6,FALSE)) -> 331.2441 | I98: 0 | M98: =IF(H98="","",D98*H98) -> 0
A99: =E99&F99 -> Emergency Stop SwitchFlush Mtd | B99: =IF(E99="","",VLOOKUP(A99,'Parts List'!A:E,5,FALSE)) -> AOW401R + SSG1-67 | D99: =$D$77*I99 -> 0 | E99: Emergency Stop Switch | F99: Flush Mtd | H99: =IF(E99="","",VLOOKUP(A99,'Parts List'!A:F,6,FALSE)) -> 75.69 | I99: 0 | M99: =IF(H99="","",D99*H99) -> 0
A100: =E100&F100 -> Air Flow Monitor | B100: =IF(E100="","",VLOOKUP(A100,'Parts List'!A:E,5,FALSE)) -> Select Option | D100: =$D$77*I100 -> 0 | E100: Air Flow Monitor | H100: =IF(E100="","",VLOOKUP(A100,'Parts List'!A:F,6,FALSE)) -> 0 | I100: 0 | M100: =IF(H100="","",D100*H100) -> 0
A101: =E101&F101 -> See Valve Quote | B101: =IF(E101="","",VLOOKUP(A101,'Parts List'!A:E,5,FALSE)) -> N/A | D101: =$D$77*I101 -> 0 | E101: See Valve Quote | H101: =IF(E101="","",VLOOKUP(A101,'Parts List'!A:F,6,FALSE)) -> 0 | I101: 0 | M101: =IF(H101="","",D101*H101) -> 0
A102: =E102&F102 | B102: =IF(E102="","",VLOOKUP(A102,'Parts List'!A:E,5,FALSE)) | D102: =$D$77*I102 -> 0 | H102: =IF(E102="","",VLOOKUP(A102,'Parts List'!A:F,6,FALSE)) | I102: 1 | M102: =IF(H102="","",D102*H102) | N102: <- Duct Detector Interlock - Used for point count
A103: =E103&F103 | B103: =IF(E103="","",VLOOKUP(A103,'Parts List'!A:E,5,FALSE)) | D103: =$D$77*I103 -> 0 | H103: =IF(E103="","",VLOOKUP(A103,'Parts List'!A:F,6,FALSE)) | I103: 0 | M103: =IF(H103="","",D103*H103)
A104: =E104&F104 | B104: =IF(E104="","",VLOOKUP(A104,'Parts List'!A:E,5,FALSE)) | D104: =$D$77*I104 -> 0 | H104: =IF(E104="","",VLOOKUP(A104,'Parts List'!A:F,6,FALSE)) | I104: 0 | M104: =IF(H104="","",D104*H104)
A105: =E105&F105 | B105: =IF(E105="","",VLOOKUP(A105,'Parts List'!A:E,5,FALSE)) | H105: =IF(E105="","",VLOOKUP(A105,'Parts List'!A:F,6,FALSE)) | M105: =IF(H105="","",D105*H105)
A106: =E106&F106 -> Water Source Heat Pumps | D106: 0 | E106: Water Source Heat Pumps | I106: #/unit | N106: =SUM(I112:I120)+I108 -> 0 | O106: Pts/Unit | P106: =D106*N106 -> 0 | Q106: units | R106: =D106*S106 -> 0 | S106: 1500 | T106: per unit | V106: =D106*W106 -> 0 | W106: 3 | X106: per unit | Z106: =D106*AA106 -> 0 | AA106: 1 | AB106: per unit | AD106: =D106*AE106 -> 0 | AE106: 1 | AF106: per unit
A107: =E107&F107 -> Controller | B107: =IF(E107="","",VLOOKUP(A107,'Parts List'!A:E,5,FALSE)) -> Select Option | D107: =$D$106*I107 -> 0 | E107: Controller | H107: =IF(E107="","",VLOOKUP(A107,'Parts List'!A:F,6,FALSE)) -> 0 | I107: 0 | J107: =D107 -> 0 | K107: =D107*70 -> 0 | M107: =IF(H107="","",D107*H107) -> 0
A108: =E108&F108 -> Panel - Enclosure w Subpanel | B108: =IF(E108="","",VLOOKUP(A108,'Parts List'!A:E,5,FALSE)) -> Select Option | D108: =$D$106*I108 -> 0 | E108: Panel - Enclosure w Subpanel | H108: =IF(E108="","",VLOOKUP(A108,'Parts List'!A:F,6,FALSE)) -> 0 | I108: 0 | M108: =IF(H108="","",D108*H108) -> 0
A109: =E109&F109 -> Relay | B109: =IF(E109="","",VLOOKUP(A109,'Parts List'!A:E,5,FALSE)) -> Select Option | D109: =$D$106*I109 -> 0 | E109: Relay | H109: =IF(E109="","",VLOOKUP(A109,'Parts List'!A:F,6,FALSE)) -> 0 | I109: 0 | M109: =IF(H109="","",D109*H109) -> 0
A110: =E110&F110 -> Transformer | B110: =IF(E110="","",VLOOKUP(A110,'Parts List'!A:E,5,FALSE)) -> Select Option | D110: =$D$106*I110 -> 0 | E110: Transformer | H110: =IF(E110="","",VLOOKUP(A110,'Parts List'!A:F,6,FALSE)) -> 0 | I110: 0 | M110: =IF(H110="","",D110*H110) -> 0
A111: =E111&F111 -> Static Pressure Tips | B111: =IF(E111="","",VLOOKUP(A111,'Parts List'!A:E,5,FALSE)) -> N/A | D111: =$D$106*I111 -> 0 | E111: Static Pressure Tips | H111: =IF(E111="","",VLOOKUP(A111,'Parts List'!A:F,6,FALSE)) -> 0 | I111: 0 | M111: =IF(H111="","",D111*H111) -> 0
A112: =E112&F112 -> Current Sw | B112: =IF(E112="","",VLOOKUP(A112,'Parts List'!A:E,5,FALSE)) -> Select Option | D112: =$D$106*I112 -> 0 | E112: Current Sw | H112: =IF(E112="","",VLOOKUP(A112,'Parts List'!A:F,6,FALSE)) -> 0 | I112: 0 | M112: =IF(H112="","",D112*H112) -> 0
A113: =E113&F113 -> Filter Status | B113: =IF(E113="","",VLOOKUP(A113,'Parts List'!A:E,5,FALSE)) -> Select Option | D113: =$D$106*I113 -> 0 | E113: Filter Status | H113: =IF(E113="","",VLOOKUP(A113,'Parts List'!A:F,6,FALSE)) -> 0 | I113: 0 | M113: =IF(H113="","",D113*H113) -> 0
A114: =E114&F114 -> Communicating Room Thermostat | B114: =IF(E114="","",VLOOKUP(A114,'Parts List'!A:E,5,FALSE)) -> Select Option | D114: =$D$106*I114 -> 0 | E114: Communicating Room Thermostat | H114: =IF(E114="","",VLOOKUP(A114,'Parts List'!A:F,6,FALSE)) -> 0 | I114: 0 | J114: =D114 -> 0 | K114: =D114*50 -> 0 | M114: =IF(H114="","",D114*H114) -> 0
...

Sheet Estimate 4
B1: =Totals!B1 -> ESTIMATING SHEET VERSION 8.6 | G1: Salesman: | H1: =Totals!H1 -> 0 | L1: 1 | N1: <- 1=Page Used, 0=Page not used
B2: Job Name: | C2: =Totals!C2 -> 0 | G2: Estimator: | H2: =Totals!H2 -> 0 | L2: =Totals!L2 -> 0
B3: Part Number | D3: QTY. | E3: MATERIAL DESCRIPTON | H3: LIST $ | J3: # of Contrs | K3: # of Points | M3: TOTAL | R3: Electrical Price Check | V3: Tech | Z3: Graphics | AD3: Programming
D5: 0 | E5: VAV Boxes w Heat | F5: Option | I5: #/unit | N5: 1 | O5: Pts/VAV | P5: =D5*N5 -> 0 | Q5: points | R5: =P5*S5 -> 0 | S5: 550 | T5: per VAV | V5: =P5*W5 -> 0 | W5: 1 | X5: per VAV | Z5: =P5*AA5 -> 0 | AA5: 0.25 | AB5: per VAV | AD5: =P5*AE5 -> 0 | AE5: 0.25 | AF5: per VAV
A6: =E6&F6 -> ControllerOptimizer BACnet MSTP VAV Cntr w Act & VP, Bluetooth, 7 UIO, 5 SSR | B6: =IF(E6="","",VLOOKUP(A6,'Parts List'!A:E,5,FALSE)) -> VAA-VA75MB24NMC | D6: =$D$5*I6 -> 0 | E6: Controller | F6: Optimizer BACnet MSTP VAV Cntr w Act & VP, Bluetooth, 7 UIO, 5 SSR | H6: =IF(E6="","",VLOOKUP(A6,'Parts List'!A:F,6,FALSE)) -> 281.3558 | I6: 1 | J6: =D6 -> 0 | K6: =D6*70 -> 0 | M6: =IF(H6="","",D6*H6) -> 0
A7: =E7&F7 -> Temp SensorTR100 Space with LCD | B7: =IF(E7="","",VLOOKUP(A7,'Parts List'!A:E,5,FALSE)) -> TR100-T-G | D7: =$D$5*I7 -> 0 | E7: Temp Sensor | F7: TR100 Space with LCD | H7: =IF(E7="","",VLOOKUP(A7,'Parts List'!A:F,6,FALSE)) -> 128.71265 | I7: 1 | M7: =IF(H7="","",D7*H7) -> 0
A8: =E8&F8 -> Temp SensorDuct Insertion Sensor | B8: =IF(E8="","",VLOOKUP(A8,'Parts List'!A:E,5,FALSE)) -> C7041B2005 | D8: =$D$5*I8 -> 0 | E8: Temp Sensor | F8: Duct Insertion Sensor | H8: =IF(E8="","",VLOOKUP(A8,'Parts List'!A:F,6,FALSE)) -> 23.18855 | I8: 1 | M8: =IF(H8="","",D8*H8) -> 0
A9: =E9&F9 -> Current SwDigital Status Switch | B9: =IF(E9="","",VLOOKUP(A9,'Parts List'!A:E,5,FALSE)) -> H600 | D9: =$D$5*I9 -> 0 | E9: Current Sw | F9: Digital Status Switch | H9: =IF(E9="","",VLOOKUP(A9,'Parts List'!A:F,6,FALSE)) -> 31.43 | I9: 0 | M9: =IF(H9="","",D9*H9) -> 0
A10: =E10&F10 -> RelayRIB Pilot Relay | B10: =IF(E10="","",VLOOKUP(A10,'Parts List'!A:E,5,FALSE)) -> RIBU1C | D10: =$D$5*I10 -> 0 | E10: Relay | F10: RIB Pilot Relay | H10: =IF(E10="","",VLOOKUP(A10,'Parts List'!A:F,6,FALSE)) -> 14.36 | I10: 0 | M10: =IF(H10="","",D10*H10) -> 0
A11: =E11&F11 -> VAV HW Valve 2W & 3-way NSR | B11: =IF(E11="","",VLOOKUP(A11,'Parts List'!A:E,5,FALSE)) -> N/A | D11: =$D$5*I11 -> 0 | E11: VAV HW Valve 2W & 3-way NSR | H11: 150 | I11: 0 | M11: =IF(H11="","",D11*H11) -> 0
A12: =E12&F12 -> Air Flow MonitorRetrofit Flow Ring for VAV Boxes | B12: =IF(E12="","",VLOOKUP(A12,'Parts List'!A:E,5,FALSE)) -> 36FMI | D12: =$D$5*I12 -> 0 | E12: Air Flow Monitor | F12: Retrofit Flow Ring for VAV Boxes | H12: =IF(E12="","",VLOOKUP(A12,'Parts List'!A:F,6,FALSE)) -> 95 | I12: 0 | M12: =IF(H12="","",D12*H12) -> 0
B13: =IF(E13="","",VLOOKUP(A13,'Parts List'!A:E,5,FALSE)) | H13: =IF(E13="","",VLOOKUP(A13,'Parts List'!A:F,6,FALSE)) | M13: =IF(H13="","",D13*H13)
A15: =E15&F15 -> Cooling Only VAV Boxes | D15: 0 | E15: Cooling Only VAV Boxes | I15: #/unit | N15: 1 | O15: Pts/VAV | P15: =D15*N15 -> 0 | Q15: points | R15: =P15*S15 -> 0 | S15: 550 | T15: per VAV | V15: =P15*W15 -> 0 | W15: 1 | X15: per VAV | Z15: =P15*AA15 -> 0 | AA15: 0.25 | AB15: per VAV | AD15: =P15*AE15 -> 0 | AE15: 0.25 | AF15: per VAV
A16: =E16&F16 -> ControllerOptimizer BACnet MSTP VAV Cntr w Act & VP, Bluetooth, 7 UIO, 5 SSR | B16: =IF(E16="","",VLOOKUP(A16,'Parts List'!A:E,5,FALSE)) -> VAA-VA75MB24NMC | D16: =$D$15*I16 -> 0 | E16: Controller | F16: Optimizer BACnet MSTP VAV Cntr w Act & VP, Bluetooth, 7 UIO, 5 SSR | H16: =IF(E16="","",VLOOKUP(A16,'Parts List'!A:F,6,FALSE)) -> 281.3558 | I16: 1 | J16: =D16 -> 0 | K16: =D16*70 -> 0 | M16: =IF(H16="","",D16*H16) -> 0
A17: =E17&F17 -> Temp SensorTR100 Space with LCD | B17: =IF(E17="","",VLOOKUP(A17,'Parts List'!A:E,5,FALSE)) -> TR100-T-G | D17: =$D$15*I17 -> 0 | E17: Temp Sensor | F17: TR100 Space with LCD | H17: =IF(E17="","",VLOOKUP(A17,'Parts List'!A:F,6,FALSE)) -> 128.71265 | I17: 1 | M17: =IF(H17="","",D17*H17) -> 0
A18: =E18&F18 -> Transformer40 VA | B18: =IF(E18="","",VLOOKUP(A18,'Parts List'!A:E,5,FALSE)) -> TR40VA001 | D18: =$D$15*I18 -> 0 | E18: Transformer | F18: 40 VA | H18: =IF(E18="","",VLOOKUP(A18,'Parts List'!A:F,6,FALSE)) -> 17.76 | I18: 0 | M18: =IF(H18="","",D18*H18) -> 0
A19: =E19&F19 -> Air Flow MonitorRetrofit Flow Ring for VAV Boxes | B19: =IF(E19="","",VLOOKUP(A19,'Parts List'!A:E,5,FALSE)) -> 36FMI | D19: =$D$15*I19 -> 0 | E19: Air Flow Monitor | F19: Retrofit Flow Ring for VAV Boxes | H19: =IF(E19="","",VLOOKUP(A19,'Parts List'!A:F,6,FALSE)) -> 95 | I19: 0 | M19: =IF(H19="","",D19*H19) -> 0
B20: =IF(E20="","",VLOOKUP(A20,'Parts List'!A:E,5,FALSE)) | H20: =IF(E20="","",VLOOKUP(A20,'Parts List'!A:F,6,FALSE)) | M20: =IF(H20="","",D20*H20)
D23: 0 | E23: Supply Air Boxes - CRC/Phoenix LV Wiring and Integration | I23: #/unit | N23: 1 | O23: Pts/VAV | P23: =D23*N23 -> 0 | Q23: points | R23: =P23*S23 -> 0 | S23: 750 | T23: per VAV | V23: =P23*W23 -> 0 | W23: 1 | X23: per VAV | Z23: =P23*AA23 -> 0 | AA23: 0.25 | AB23: per VAV | AD23: =P23*AE23 -> 0 | AE23: 0.25 | AF23: per VAV
A24: =E24&F24 | B24: =IF(E24="","",VLOOKUP(A24,'[2]Parts List'!A:E,5,FALSE)) | D24: =$D$23*I24 -> 0 | H24: =IF(E24="","",VLOOKUP(A24,'[2]Parts List'!A:F,6,FALSE)) | I24: 1 | J24: =D24 -> 0 | K24: =D24*50 -> 0 | M24: =IF(H24="","",D24*H24)
D27: 0 | E27: Exhaust Air Boxes - CRC/Phoenix LV Wiring and Integration | I27: #/unit | N27: 1 | O27: Pts/VAV | P27: =D27*N27 -> 0 | Q27: points | R27: =P27*S27 -> 0 | S27: 750 | T27: per VAV | V27: =P27*W27 -> 0 | W27: 1 | X27: per VAV | Z27: =P27*AA27 -> 0 | AA27: 0.25 | AB27: per VAV | AD27: =P27*AE27 -> 0 | AE27: 0.25 | AF27: per VAV
A28: =E28&F28 | B28: =IF(E28="","",VLOOKUP(A28,'[2]Parts List'!A:E,5,FALSE)) | D28: =$D$27*I28 -> 0 | H28: =IF(E28="","",VLOOKUP(A28,'[2]Parts List'!A:F,6,FALSE)) | I28: 1 | M28: =IF(H28="","",D28*H28)
D31: 0 | E31: Return Air Boxes - CRC/Phoenix LV Wiring and Integration | I31: #/unit | N31: 1 | O31: Pts/VAV | P31: =D31*N31 -> 0 | Q31: points | R31: =P31*S31 -> 0 | S31: 750 | T31: per VAV | V31: =P31*W31 -> 0 | W31: 1 | X31: per VAV | Z31: =P31*AA31 -> 0 | AA31: 0.25 | AB31: per VAV | AD31: =P31*AE31 -> 0 | AE31: 0.25 | AF31: per VAV
A32: =E32&F32 | B32: =IF(E32="","",VLOOKUP(A32,'[2]Parts List'!A:E,5,FALSE)) | D32: =$D$31*I32 -> 0 | H32: =IF(E32="","",VLOOKUP(A32,'[2]Parts List'!A:F,6,FALSE)) | I32: 1 | M32: =IF(H32="","",D32*H32)
D35: 0 | E35: OR Room Pressure Monitors - CRC/Phoenix LV Wiring and Integration | I35: #/unit | N35: 1 | O35: Pts/VAV | P35: =D35*N35 -> 0 | Q35: points | R35: =P35*S35 -> 0 | S35: 750 | T35: per VAV | V35: =P35*W35 -> 0 | W35: 1 | X35: per VAV | Z35: =P35*AA35 -> 0 | AA35: 0.25 | AB35: per VAV | AD35: =P35*AE35 -> 0 | AE35: 0.25 | AF35: per VAV
A36: =E36&F36 | B36: =IF(E36="","",VLOOKUP(A36,'[2]Parts List'!A:E,5,FALSE)) | D36: =$D$35*I36 -> 0 | H36: =IF(E36="","",VLOOKUP(A36,'[2]Parts List'!A:F,6,FALSE)) | I36: 1 | M36: =IF(H36="","",D36*H36)
A40: =E40&F40 -> Cooling Only VAV Box Transformers | D40: 0 | E40: Cooling Only VAV Box Transformers | I40: #/unit | N40: =SUM(I41:I43) -> 0 | O40: Pts/Unit | P40: =D40*N40 -> 0 | Q40: points | R40: =P40*S40 -> 0 | S40: 550 | T40: per Unit | V40: =P40*W40 -> 0 | W40: 0 | X40: per unit | Z40: =D40*AA40 -> 0 | AA40: 0 | AB40: per unit | AD40: =D40*AE40 -> 0 | AE40: 0 | AF40: per unit
A41: =E41&F41 -> Transformer(3) - 100 VA w Enclosure | B41: =IF(E41="","",VLOOKUP(A41,'Parts List'!A:E,5,FALSE)) -> PSH300A | D41: =$D$40*I41 -> 0 | E41: Transformer | F41: (3) - 100 VA w Enclosure | H41: =IF(E41="","",VLOOKUP(A41,'Parts List'!A:F,6,FALSE)) -> 314.8 | I41: 0 | M41: =IF(H41="","",D41*H41) -> 0
A42: =E42&F42 -> Transformer(5) - 100 VA w Enclosure | B42: =IF(E42="","",VLOOKUP(A42,'Parts List'!A:E,5,FALSE)) -> PSH500A | D42: =$D$40*I42 -> 0 | E42: Transformer | F42: (5) - 100 VA w Enclosure | H42: =IF(E42="","",VLOOKUP(A42,'Parts List'!A:F,6,FALSE)) -> 430.65 | I42: 0 | M42: =IF(H42="","",D42*H42) -> 0
A43: =E43&F43 | B43: =IF(E43="","",VLOOKUP(A43,'Parts List'!A:E,5,FALSE)) | D43: =$D$40*I43 -> 0 | H43: =IF(E43="","",VLOOKUP(A43,'Parts List'!A:F,6,FALSE)) | I43: 0 | M43: =IF(H43="","",D43*H43)
B44: =IF(E44="","",VLOOKUP(A44,'Parts List'!A:E,5,FALSE)) | H44: =IF(E44="","",VLOOKUP(A44,'Parts List'!A:F,6,FALSE)) | M44: =IF(H44="","",D44*H44)
A46: =E46&F46 -> VAV Air Handling Unit | D46: 0 | E46: VAV Air Handling Unit | I46: #/unit | N46: =SUM(I57:I73)+I52 -> 1 | O46: Pts/Unit | P46: =D46*N46 -> 0 | Q46: points | R46: =P46*S46 -> 0 | S46: 350 | T46: per point | V46: =P46*W46 -> 0 | W46: 1 | X46: per point | Z46: =D46*AA46 -> 0 | AA46: 4 | AB46: per unit | AD46: =D46*AE46 -> 0 | AE46: 6 | AF46: per unit
A47: =E47&F47 -> ControllerOptimizer Plant Cntr, 1 IP, 3 Ethernet Switched+4 RS485 Ports | B47: =IF(E47="","",VLOOKUP(A47,'Parts List'!A:E,5,FALSE)) -> N-ADV-134-H-C | D47: =$D$46*I47 -> 0 | E47: Controller | F47: Optimizer Plant Cntr, 1 IP, 3 Ethernet Switched+4 RS485 Ports | H47: =IF(E47="","",VLOOKUP(A47,'Parts List'!A:F,6,FALSE)) -> 875.1457 | I47: 0 | J47: =D47 -> 0 | K47: =D47*70 -> 0 | M47: =IF(H47="","",D47*H47) -> 0
A48: =E48&F48 -> Optimizer License with 18 Month SMA | B48: =IF(E48="","",VLOOKUP(A48,'Parts List'!A:E,5,FALSE)) -> Select Option | D48: =$D$46*I48 -> 0 | E48: Optimizer License with 18 Month SMA | H48: =IF(E48="","",VLOOKUP(A48,'Parts List'!A:F,6,FALSE)) -> 0 | I48: 0 | J48: =D48 -> 0 | K48: =D48*70 -> 0 | M48: =IF(H48="","",D48*H48) -> 0
A49: =E49&F49 -> I/O ModuleOptimzer Unitary Cntr 5-UI, 5-DI, 4-AO, 4-DO I/O Module | B49: =IF(E49="","",VLOOKUP(A49,'Parts List'!A:E,5,FALSE)) -> ISMA-B-MIX18 | D49: =$D$46*I49 -> 0 | E49: I/O Module | F49: Optimzer Unitary Cntr 5-UI, 5-DI, 4-AO, 4-DO I/O Module | H49: =IF(E49="","",VLOOKUP(A49,'Parts List'!A:F,6,FALSE)) -> 338.81 | I49: 0 | M49: =IF(H49="","",D49*H49) -> 0
A50: =E50&F50 -> Phoenix Controller Core License | B50: =IF(E50="","",VLOOKUP(A50,'Parts List'!A:E,5,FALSE)) -> Select Option | D50: =$D$46*I50 -> 0 | E50: Phoenix Controller Core License | H50: =IF(E50="","",VLOOKUP(A50,'Parts List'!A:F,6,FALSE)) -> 0 | I50: 0 | M50: =IF(H50="","",D50*H50) -> 0
A51: =E51&F51 -> Phoenix ILC SMA | B51: =IF(E51="","",VLOOKUP(A51,'Parts List'!A:E,5,FALSE)) -> Select Option | D51: =$D$46*I51 -> 0 | E51: Phoenix ILC SMA | H51: =IF(E51="","",VLOOKUP(A51,'Parts List'!A:F,6,FALSE)) -> 0 | I51: 0 | M51: =IF(H51="","",D51*H51) -> 0
A52: =E52&F52 -> Panel - Enclosure w SubpanelNema-1 Medium | B52: =IF(E52="","",VLOOKUP(A52,'Parts List'!A:E,5,FALSE)) -> RET1-262007BT-P | D52: =$D$46*I52 -> 0 | E52: Panel - Enclosure w Subpanel | F52: Nema-1 Medium | H52: =IF(E52="","",VLOOKUP(A52,'Parts List'!A:F,6,FALSE)) -> 436.83 | I52: 0 | M52: =IF(H52="","",D52*H52) -> 0
A53: =E53&F53 -> Relay24VAC DPDT with Base | B53: =IF(E53="","",VLOOKUP(A53,'Parts List'!A:E,5,FALSE)) -> RH2B-UAC24 + SH2B-05 | D53: =$D$46*I53 -> 0 | E53: Relay | F53: 24VAC DPDT with Base | H53: =IF(E53="","",VLOOKUP(A53,'Parts List'!A:F,6,FALSE)) -> 8.12 | I53: 0 | M53: =IF(H53="","",D53*H53) -> 0
A54: =E54&F54 -> Transformer75 VA with circuit breaker | B54: =IF(E54="","",VLOOKUP(A54,'Parts List'!A:E,5,FALSE)) -> TR75VA004 | D54: =$D$46*I54 -> 0 | E54: Transformer | F54: 75 VA with circuit breaker | H54: =IF(E54="","",VLOOKUP(A54,'Parts List'!A:F,6,FALSE)) -> 42.14 | I54: 0 | M54: =IF(H54="","",D54*H54) -> 0
A55: =E55&F55 -> Power Supply24VDC Panel Mounted - 1.3 A | B55: =IF(E55="","",VLOOKUP(A55,'Parts List'!A:E,5,FALSE)) -> PS5R-VB24 | D55: =$D$46*I55 -> 0 | E55: Power Supply | F55: 24VDC Panel Mounted - 1.3 A | H55: =IF(E55="","",VLOOKUP(A55,'Parts List'!A:F,6,FALSE)) -> 50.96 | I55: 0 | M55: =IF(H55="","",D55*H55) -> 0
A56: =E56&F56 -> Static Pressure TipsDuct Kit | B56: =IF(E56="","",VLOOKUP(A56,'Parts List'!A:E,5,FALSE)) -> A-302K + A-345k | D56: =$D$46*I56 -> 0 | E56: Static Pressure Tips | F56: Duct Kit | H56: =IF(E56="","",VLOOKUP(A56,'Parts List'!A:F,6,FALSE)) -> 17.9 | I56: 0 | M56: =IF(H56="","",D56*H56) -> 0
A57: =E57&F57 -> ThermostatLow Limit | B57: =IF(E57="","",VLOOKUP(A57,'Parts List'!A:E,5,FALSE)) -> A11A-1C | D57: =$D$46*I57 -> 0 | E57: Thermostat | F57: Low Limit | H57: =IF(E57="","",VLOOKUP(A57,'Parts List'!A:F,6,FALSE)) -> 270.31 | I57: 0 | M57: =IF(H57="","",D57*H57) -> 0
A58: =E58&F58 -> Filter StatusDigital Status | B58: =IF(E58="","",VLOOKUP(A58,'Parts List'!A:E,5,FALSE)) -> AFS-145 | D58: =$D$46*I58 -> 0 | E58: Filter Status | F58: Digital Status | H58: =IF(E58="","",VLOOKUP(A58,'Parts List'!A:F,6,FALSE)) -> 40.9 | I58: 0 | M58: =IF(H58="","",D58*H58) -> 0
A59: =E59&F59 -> Press TransmitterDuct Static Air | B59: =IF(E59="","",VLOOKUP(A59,'Parts List'!A:E,5,FALSE)) -> PX3DXX02 | D59: =$D$46*I59 -> 0 | E59: Press Transmitter | F59: Duct Static Air | H59: =IF(E59="","",VLOOKUP(A59,'Parts List'!A:F,6,FALSE)) -> 130.12 | I59: 0 | M59: =IF(H59="","",D59*H59) -> 0
A60: =E60&F60 -> Press Transmitter | B60: =IF(E60="","",VLOOKUP(A60,'Parts List'!A:E,5,FALSE)) -> Select Option | D60: =$D$46*I60 -> 0 | E60: Press Transmitter | H60: =IF(E60="","",VLOOKUP(A60,'Parts List'!A:F,6,FALSE)) -> 0 | I60: 0 | M60: =IF(H60="","",D60*H60) -> 0
A61: =E61&F61 -> Press TransmitterHigh Static Limit Switch | B61: =IF(E61="","",VLOOKUP(A61,'Parts List'!A:E,5,FALSE)) -> 1900-5-MR | D61: =$D$46*I61 -> 0 | E61: Press Transmitter | F61: High Static Limit Switch | H61: =IF(E61="","",VLOOKUP(A61,'Parts List'!A:F,6,FALSE)) -> 111.93 | I61: 0 | M61: =IF(H61="","",D61*H61) -> 0
A62: =E62&F62 -> Current SwDigital for VFD Status | B62: =IF(E62="","",VLOOKUP(A62,'Parts List'!A:E,5,FALSE)) -> H904 | D62: =$D$46*I62 -> 0 | E62: Current Sw | F62: Digital for VFD Status | H62: =IF(E62="","",VLOOKUP(A62,'Parts List'!A:F,6,FALSE)) -> 88.31 | I62: 0 | M62: =IF(H62="","",D62*H62) -> 0
A63: =E63&F63 -> Damper ActuatorLarge - Spring Return | B63: =IF(E63="","",VLOOKUP(A63,'Parts List'!A:E,5,FALSE)) -> MS7520A2007 | D63: =$D$46*I63 -> 0 | E63: Damper Actuator | F63: Large - Spring Return | H63: =IF(E63="","",VLOOKUP(A63,'Parts List'!A:F,6,FALSE)) -> 446.4658 | I63: 0 | M63: =IF(H63="","",D63*H63) -> 0
A64: =E64&F64 -> Temp SensorAveraging Sensor | B64: =IF(E64="","",VLOOKUP(A64,'Parts List'!A:E,5,FALSE)) -> C7041R2018 | D64: =$D$46*I64 -> 0 | E64: Temp Sensor | F64: Averaging Sensor | H64: =IF(E64="","",VLOOKUP(A64,'Parts List'!A:F,6,FALSE)) -> 166.9283 | I64: 0 | M64: =IF(H64="","",D64*H64) -> 0
A65: =E65&F65 -> Temp SensorDuct Temp/Humidity | B65: =IF(E65="","",VLOOKUP(A65,'Parts List'!A:E,5,FALSE)) -> H7735B2018 | D65: =$D$46*I65 -> 0 | E65: Temp Sensor | F65: Duct Temp/Humidity | H65: =IF(E65="","",VLOOKUP(A65,'Parts List'!A:F,6,FALSE)) -> 266.23465 | I65: 0 | M65: =IF(H65="","",D65*H65) -> 0
A66: =E66&F66 -> Humidity | B66: =IF(E66="","",VLOOKUP(A66,'Parts List'!A:E,5,FALSE)) -> Select Option | D66: =$D$46*I66 -> 0 | E66: Humidity | H66: =IF(E66="","",VLOOKUP(A66,'Parts List'!A:F,6,FALSE)) -> 0 | I66: 0 | M66: =IF(H66="","",D66*H66) -> 0
A67: =E67&F67 -> Humidity | B67: =IF(E67="","",VLOOKUP(A67,'Parts List'!A:E,5,FALSE)) -> Select Option | D67: =$D$46*I67 -> 0 | E67: Humidity | H67: =IF(E67="","",VLOOKUP(A67,'Parts List'!A:F,6,FALSE)) -> 0 | I67: 0 | M67: =IF(H67="","",D67*H67) -> 0
A68: =E68&F68 -> Carbon Dioxide SensorSpace CO2 wo LCD | B68: =IF(E68="","",VLOOKUP(A68,'Parts List'!A:E,5,FALSE)) -> C7263A1008 | D68: =$D$46*I68 -> 0 | E68: Carbon Dioxide Sensor | F68: Space CO2 wo LCD | H68: =IF(E68="","",VLOOKUP(A68,'Parts List'!A:F,6,FALSE)) -> 355.7389 | I68: 0 | M68: =IF(H68="","",D68*H68) -> 0
A69: =E69&F69 -> Carbon Dioxide SensorDuct CO2 wo LCD | B69: =IF(E69="","",VLOOKUP(A69,'Parts List'!A:E,5,FALSE)) -> C7632B1002 | D69: =$D$46*I69 -> 0 | E69: Carbon Dioxide Sensor | F69: Duct CO2 wo LCD | H69: =IF(E69="","",VLOOKUP(A69,'Parts List'!A:F,6,FALSE)) -> 331.2441 | I69: 0 | M69: =IF(H69="","",D69*H69) -> 0
A70: =E70&F70 -> Emergency Stop SwitchFlush Mtd | B70: =IF(E70="","",VLOOKUP(A70,'Parts List'!A:E,5,FALSE)) -> AOW401R + SSG1-67 | D70: =$D$46*I70 -> 0 | E70: Emergency Stop Switch | F70: Flush Mtd | H70: =IF(E70="","",VLOOKUP(A70,'Parts List'!A:F,6,FALSE)) -> 75.69 | I70: 0 | M70: =IF(H70="","",D70*H70) -> 0
A71: =E71&F71 -> Air Flow Monitor | B71: =IF(E71="","",VLOOKUP(A71,'Parts List'!A:E,5,FALSE)) -> Select Option | D71: =$D$46*I71 -> 0 | E71: Air Flow Monitor | H71: =IF(E71="","",VLOOKUP(A71,'Parts List'!A:F,6,FALSE)) -> 0 | I71: 0 | M71: =IF(H71="","",D71*H71) -> 0
A72: =E72&F72 -> See Valve Quote | B72: =IF(E72="","",VLOOKUP(A72,'Parts List'!A:E,5,FALSE)) -> N/A | D72: =$D$46*I72 -> 0 | E72: See Valve Quote | H72: =IF(E72="","",VLOOKUP(A72,'Parts List'!A:F,6,FALSE)) -> 0 | I72: 0 | M72: =IF(H72="","",D72*H72) -> 0
A73: =E73&F73 | B73: =IF(E73="","",VLOOKUP(A73,'Parts List'!A:E,5,FALSE)) | D73: =$D$46*I73 -> 0 | H73: =IF(E73="","",VLOOKUP(A73,'Parts List'!A:F,6,FALSE)) | I73: 1 | M73: =IF(H73="","",D73*H73) | N73: <- Duct Detector Interlock - Used for point count
A74: =E74&F74 | B74: =IF(E74="","",VLOOKUP(A74,'Parts List'!A:E,5,FALSE)) | D74: =$D$46*I74 -> 0 | H74: =IF(E74="","",VLOOKUP(A74,'Parts List'!A:F,6,FALSE)) | I74: 0 | M74: =IF(H74="","",D74*H74)
A75: =E75&F75 | B75: =IF(E75="","",VLOOKUP(A75,'Parts List'!A:E,5,FALSE)) | D75: =$D$46*I75 -> 0 | H75: =IF(E75="","",VLOOKUP(A75,'Parts List'!A:F,6,FALSE)) | I75: 0 | M75: =IF(H75="","",D75*H75)
A76: =E76&F76 | B76: =IF(E76="","",VLOOKUP(A76,'Parts List'!A:E,5,FALSE)) | H76: =IF(E76="","",VLOOKUP(A76,'Parts List'!A:F,6,FALSE)) | M76: =IF(H76="","",D76*H76)
A77: =E77&F77 -> Constant Volume Air Handling Units | D77: 0 | E77: Constant Volume Air Handling Units | I77: #/unit | N77: =SUM(I88:I102)+I83 -> 1 | O77: Pts/Unit | P77: =D77*N77 -> 0 | Q77: units | R77: =P77*S77 -> 0 | S77: 350 | T77: per point | V77: =P77*W77 -> 0 | W77: 1 | X77: per point | Z77: =D77*AA77 -> 0 | AA77: 4 | AB77: per unit | AD77: =D77*AE77 -> 0 | AE77: 6 | AF77: per unit
A78: =E78&F78 -> ControllerOptimizer Plant Cntr, 1 IP, 3 Ethernet Switched+4 RS485 Ports | B78: =IF(E78="","",VLOOKUP(A78,'Parts List'!A:E,5,FALSE)) -> N-ADV-134-H-C | D78: =$D$77*I78 -> 0 | E78: Controller | F78: Optimizer Plant Cntr, 1 IP, 3 Ethernet Switched+4 RS485 Ports | H78: =IF(E78="","",VLOOKUP(A78,'Parts List'!A:F,6,FALSE)) -> 875.1457 | I78: 0 | J78: =D78 -> 0 | K78: =D78*70 -> 0 | M78: =IF(H78="","",D78*H78) -> 0
A79: =E79&F79 -> Optimizer License with 18 Month SMA | B79: =IF(E79="","",VLOOKUP(A79,'Parts List'!A:E,5,FALSE)) -> Select Option | D79: =$D$77*I79 -> 0 | E79: Optimizer License with 18 Month SMA | H79: =IF(E79="","",VLOOKUP(A79,'Parts List'!A:F,6,FALSE)) -> 0 | I79: 0 | J79: =D79 -> 0 | K79: =D79*70 -> 0 | M79: =IF(H79="","",D79*H79) -> 0
A80: =E80&F80 -> I/O ModuleOptimzer Unitary Cntr 5-UI, 5-DI, 4-AO, 4-DO I/O Module | B80: =IF(E80="","",VLOOKUP(A80,'Parts List'!A:E,5,FALSE)) -> ISMA-B-MIX18 | D80: =$D$77*I80 -> 0 | E80: I/O Module | F80: Optimzer Unitary Cntr 5-UI, 5-DI, 4-AO, 4-DO I/O Module | H80: =IF(E80="","",VLOOKUP(A80,'Parts List'!A:F,6,FALSE)) -> 338.81 | I80: 0 | M80: =IF(H80="","",D80*H80) -> 0
A81: =E81&F81 -> Phoenix Controller Core License | B81: =IF(E81="","",VLOOKUP(A81,'Parts List'!A:E,5,FALSE)) -> Select Option | D81: =$D$77*I81 -> 0 | E81: Phoenix Controller Core License | H81: =IF(E81="","",VLOOKUP(A81,'Parts List'!A:F,6,FALSE)) -> 0 | I81: 0 | M81: =IF(H81="","",D81*H81) -> 0
A82: =E82&F82 -> Phoenix ILC SMA | B82: =IF(E82="","",VLOOKUP(A82,'Parts List'!A:E,5,FALSE)) -> Select Option | D82: =$D$77*I82 -> 0 | E82: Phoenix ILC SMA | H82: =IF(E82="","",VLOOKUP(A82,'Parts List'!A:F,6,FALSE)) -> 0 | I82: 0 | M82: =IF(H82="","",D82*H82) -> 0
A83: =E83&F83 -> Panel - Enclosure w SubpanelNema-1 Medium | B83: =IF(E83="","",VLOOKUP(A83,'Parts List'!A:E,5,FALSE)) -> RET1-262007BT-P | D83: =$D$77*I83 -> 0 | E83: Panel - Enclosure w Subpanel | F83: Nema-1 Medium | H83: =IF(E83="","",VLOOKUP(A83,'Parts List'!A:F,6,FALSE)) -> 436.83 | I83: 0 | M83: =IF(H83="","",D83*H83) -> 0
A84: =E84&F84 -> Relay24VAC DPDT with Base | B84: =IF(E84="","",VLOOKUP(A84,'Parts List'!A:E,5,FALSE)) -> RH2B-UAC24 + SH2B-05 | D84: =$D$77*I84 -> 0 | E84: Relay | F84: 24VAC DPDT with Base | H84: =IF(E84="","",VLOOKUP(A84,'Parts List'!A:F,6,FALSE)) -> 8.12 | I84: 0 | M84: =IF(H84="","",D84*H84) -> 0
A85: =E85&F85 -> Transformer75 VA with circuit breaker | B85: =IF(E85="","",VLOOKUP(A85,'Parts List'!A:E,5,FALSE)) -> TR75VA004 | D85: =$D$77*I85 -> 0 | E85: Transformer | F85: 75 VA with circuit breaker | H85: =IF(E85="","",VLOOKUP(A85,'Parts List'!A:F,6,FALSE)) -> 42.14 | I85: 0 | M85: =IF(H85="","",D85*H85) -> 0
A86: =E86&F86 -> Power Supply24VDC Panel Mounted - 1.3 A | B86: =IF(E86="","",VLOOKUP(A86,'Parts List'!A:E,5,FALSE)) -> PS5R-VB24 | D86: =$D$77*I86 -> 0 | E86: Power Supply | F86: 24VDC Panel Mounted - 1.3 A | H86: =IF(E86="","",VLOOKUP(A86,'Parts List'!A:F,6,FALSE)) -> 50.96 | I86: 0 | M86: =IF(H86="","",D86*H86) -> 0
A87: =E87&F87 -> Static Pressure TipsDuct Kit | B87: =IF(E87="","",VLOOKUP(A87,'Parts List'!A:E,5,FALSE)) -> A-302K + A-345k | D87: =$D$77*I87 -> 0 | E87: Static Pressure Tips | F87: Duct Kit | H87: =IF(E87="","",VLOOKUP(A87,'Parts List'!A:F,6,FALSE)) -> 17.9 | I87: 0 | M87: =IF(H87="","",D87*H87) -> 0
A88: =E88&F88 -> ThermostatLow Limit | B88: =IF(E88="","",VLOOKUP(A88,'Parts List'!A:E,5,FALSE)) -> A11A-1C | D88: =$D$77*I88 -> 0 | E88: Thermostat | F88: Low Limit | H88: =IF(E88="","",VLOOKUP(A88,'Parts List'!A:F,6,FALSE)) -> 270.31 | I88: 0 | M88: =IF(H88="","",D88*H88) -> 0
A89: =E89&F89 -> Filter StatusDigital Status | B89: =IF(E89="","",VLOOKUP(A89,'Parts List'!A:E,5,FALSE)) -> AFS-145 | D89: =$D$77*I89 -> 0 | E89: Filter Status | F89: Digital Status | H89: =IF(E89="","",VLOOKUP(A89,'Parts List'!A:F,6,FALSE)) -> 40.9 | I89: 0 | M89: =IF(H89="","",D89*H89) -> 0
A90: =E90&F90 -> Press TransmitterDuct Static Air | B90: =IF(E90="","",VLOOKUP(A90,'Parts List'!A:E,5,FALSE)) -> PX3DXX02 | D90: =$D$77*I90 -> 0 | E90: Press Transmitter | F90: Duct Static Air | H90: =IF(E90="","",VLOOKUP(A90,'Parts List'!A:F,6,FALSE)) -> 130.12 | I90: 0 | M90: =IF(H90="","",D90*H90) -> 0
A91: =E91&F91 -> Current SwDigital for VFD Status | B91: =IF(E91="","",VLOOKUP(A91,'Parts List'!A:E,5,FALSE)) -> H904 | D91: =$D$77*I91 -> 0 | E91: Current Sw | F91: Digital for VFD Status | H91: =IF(E91="","",VLOOKUP(A91,'Parts List'!A:F,6,FALSE)) -> 88.31 | I91: 0 | M91: =IF(H91="","",D91*H91) -> 0
A92: =E92&F92 -> Damper ActuatorLarge - Spring Return | B92: =IF(E92="","",VLOOKUP(A92,'Parts List'!A:E,5,FALSE)) -> MS7520A2007 | D92: =$D$77*I92 -> 0 | E92: Damper Actuator | F92: Large - Spring Return | H92: =IF(E92="","",VLOOKUP(A92,'Parts List'!A:F,6,FALSE)) -> 446.4658 | I92: 0 | M92: =IF(H92="","",D92*H92) -> 0
A93: =E93&F93 -> Temp SensorAveraging Sensor | B93: =IF(E93="","",VLOOKUP(A93,'Parts List'!A:E,5,FALSE)) -> C7041R2018 | D93: =$D$77*I93 -> 0 | E93: Temp Sensor | F93: Averaging Sensor | H93: =IF(E93="","",VLOOKUP(A93,'Parts List'!A:F,6,FALSE)) -> 166.9283 | I93: 0 | M93: =IF(H93="","",D93*H93) -> 0
A94: =E94&F94 -> Temp SensorDuct Temp/Humidity | B94: =IF(E94="","",VLOOKUP(A94,'Parts List'!A:E,5,FALSE)) -> H7735B2018 | D94: =$D$77*I94 -> 0 | E94: Temp Sensor | F94: Duct Temp/Humidity | H94: =IF(E94="","",VLOOKUP(A94,'Parts List'!A:F,6,FALSE)) -> 266.23465 | I94: 0 | M94: =IF(H94="","",D94*H94) -> 0
A95: =E95&F95 -> Humidity | B95: =IF(E95="","",VLOOKUP(A95,'Parts List'!A:E,5,FALSE)) -> Select Option | D95: =$D$77*I95 -> 0 | E95: Humidity | H95: =IF(E95="","",VLOOKUP(A95,'Parts List'!A:F,6,FALSE)) -> 0 | I95: 0 | M95: =IF(H95="","",D95*H95) -> 0
A96: =E96&F96 -> Humidity | B96: =IF(E96="","",VLOOKUP(A96,'Parts List'!A:E,5,FALSE)) -> Select Option | D96: =$D$77*I96 -> 0 | E96: Humidity | H96: =IF(E96="","",VLOOKUP(A96,'Parts List'!A:F,6,FALSE)) -> 0 | I96: 0 | M96: =IF(H96="","",D96*H96) -> 0
A97: =E97&F97 -> Carbon Dioxide SensorSpace CO2 wo LCD | B97: =IF(E97="","",VLOOKUP(A97,'Parts List'!A:E,5,FALSE)) -> C7263A1008 | D97: =$D$77*I97 -> 0 | E97: Carbon Dioxide Sensor | F97: Space CO2 wo LCD | H97: =IF(E97="","",VLOOKUP(A97,'Parts List'!A:F,6,FALSE)) -> 355.7389 | I97: 0 | M97: =IF(H97="","",D97*H97) -> 0
A98: =E98&F98 -> Carbon Dioxide SensorDuct CO2 wo LCD | B98: =IF(E98="","",VLOOKUP(A98,'Parts List'!A:E,5,FALSE)) -> C7632B1002 | D98: =$D$77*I98 -> 0 | E98: Carbon Dioxide Sensor | F98: Duct CO2 wo LCD | H98: =IF(E98="","",VLOOKUP(A98,'Parts List'!A:F,6,FALSE)) -> 331.2441 | I98: 0 | M98: =IF(H98="","",D98*H98) -> 0
A99: =E99&F99 -> Emergency Stop SwitchFlush Mtd | B99: =IF(E99="","",VLOOKUP(A99,'Parts List'!A:E,5,FALSE)) -> AOW401R + SSG1-67 | D99: =$D$77*I99 -> 0 | E99: Emergency Stop Switch | F99: Flush Mtd | H99: =IF(E99="","",VLOOKUP(A99,'Parts List'!A:F,6,FALSE)) -> 75.69 | I99: 0 | M99: =IF(H99="","",D99*H99) -> 0
A100: =E100&F100 -> Air Flow Monitor | B100: =IF(E100="","",VLOOKUP(A100,'Parts List'!A:E,5,FALSE)) -> Select Option | D100: =$D$77*I100 -> 0 | E100: Air Flow Monitor | H100: =IF(E100="","",VLOOKUP(A100,'Parts List'!A:F,6,FALSE)) -> 0 | I100: 0 | M100: =IF(H100="","",D100*H100) -> 0
A101: =E101&F101 -> See Valve Quote | B101: =IF(E101="","",VLOOKUP(A101,'Parts List'!A:E,5,FALSE)) -> N/A | D101: =$D$77*I101 -> 0 | E101: See Valve Quote | H101: =IF(E101="","",VLOOKUP(A101,'Parts List'!A:F,6,FALSE)) -> 0 | I101: 0 | M101: =IF(H101="","",D101*H101) -> 0
A102: =E102&F102 | B102: =IF(E102="","",VLOOKUP(A102,'Parts List'!A:E,5,FALSE)) | D102: =$D$77*I102 -> 0 | H102: =IF(E102="","",VLOOKUP(A102,'Parts List'!A:F,6,FALSE)) | I102: 1 | M102: =IF(H102="","",D102*H102) | N102: <- Duct Detector Interlock - Used for point count
A103: =E103&F103 | B103: =IF(E103="","",VLOOKUP(A103,'Parts List'!A:E,5,FALSE)) | D103: =$D$77*I103 -> 0 | H103: =IF(E103="","",VLOOKUP(A103,'Parts List'!A:F,6,FALSE)) | I103: 0 | M103: =IF(H103="","",D103*H103)
A104: =E104&F104 | B104: =IF(E104="","",VLOOKUP(A104,'Parts List'!A:E,5,FALSE)) | D104: =$D$77*I104 -> 0 | H104: =IF(E104="","",VLOOKUP(A104,'Parts List'!A:F,6,FALSE)) | I104: 0 | M104: =IF(H104="","",D104*H104)
A105: =E105&F105 | B105: =IF(E105="","",VLOOKUP(A105,'Parts List'!A:E,5,FALSE)) | H105: =IF(E105="","",VLOOKUP(A105,'Parts List'!A:F,6,FALSE)) | M105: =IF(H105="","",D105*H105)
A106: =E106&F106 -> Water Source Heat Pumps | D106: 0 | E106: Water Source Heat Pumps | I106: #/unit | N106: =SUM(I112:I120)+I108 -> 0 | O106: Pts/Unit | P106: =D106*N106 -> 0 | Q106: units | R106: =D106*S106 -> 0 | S106: 1500 | T106: per unit | V106: =D106*W106 -> 0 | W106: 3 | X106: per unit | Z106: =D106*AA106 -> 0 | AA106: 1 | AB106: per unit | AD106: =D106*AE106 -> 0 | AE106: 1 | AF106: per unit
A107: =E107&F107 -> Controller | B107: =IF(E107="","",VLOOKUP(A107,'Parts List'!A:E,5,FALSE)) -> Select Option | D107: =$D$106*I107 -> 0 | E107: Controller | H107: =IF(E107="","",VLOOKUP(A107,'Parts List'!A:F,6,FALSE)) -> 0 | I107: 0 | J107: =D107 -> 0 | K107: =D107*70 -> 0 | M107: =IF(H107="","",D107*H107) -> 0
A108: =E108&F108 -> Panel - Enclosure w Subpanel | B108: =IF(E108="","",VLOOKUP(A108,'Parts List'!A:E,5,FALSE)) -> Select Option | D108: =$D$106*I108 -> 0 | E108: Panel - Enclosure w Subpanel | H108: =IF(E108="","",VLOOKUP(A108,'Parts List'!A:F,6,FALSE)) -> 0 | I108: 0 | M108: =IF(H108="","",D108*H108) -> 0
A109: =E109&F109 -> Relay | B109: =IF(E109="","",VLOOKUP(A109,'Parts List'!A:E,5,FALSE)) -> Select Option | D109: =$D$106*I109 -> 0 | E109: Relay | H109: =IF(E109="","",VLOOKUP(A109,'Parts List'!A:F,6,FALSE)) -> 0 | I109: 0 | M109: =IF(H109="","",D109*H109) -> 0
A110: =E110&F110 -> Transformer | B110: =IF(E110="","",VLOOKUP(A110,'Parts List'!A:E,5,FALSE)) -> Select Option | D110: =$D$106*I110 -> 0 | E110: Transformer | H110: =IF(E110="","",VLOOKUP(A110,'Parts List'!A:F,6,FALSE)) -> 0 | I110: 0 | M110: =IF(H110="","",D110*H110) -> 0
A111: =E111&F111 -> Static Pressure Tips | B111: =IF(E111="","",VLOOKUP(A111,'Parts List'!A:E,5,FALSE)) -> N/A | D111: =$D$106*I111 -> 0 | E111: Static Pressure Tips | H111: =IF(E111="","",VLOOKUP(A111,'Parts List'!A:F,6,FALSE)) -> 0 | I111: 0 | M111: =IF(H111="","",D111*H111) -> 0
A112: =E112&F112 -> Current Sw | B112: =IF(E112="","",VLOOKUP(A112,'Parts List'!A:E,5,FALSE)) -> Select Option | D112: =$D$106*I112 -> 0 | E112: Current Sw | H112: =IF(E112="","",VLOOKUP(A112,'Parts List'!A:F,6,FALSE)) -> 0 | I112: 0 | M112: =IF(H112="","",D112*H112) -> 0
A113: =E113&F113 -> Filter Status | B113: =IF(E113="","",VLOOKUP(A113,'Parts List'!A:E,5,FALSE)) -> Select Option | D113: =$D$106*I113 -> 0 | E113: Filter Status | H113: =IF(E113="","",VLOOKUP(A113,'Parts List'!A:F,6,FALSE)) -> 0 | I113: 0 | M113: =IF(H113="","",D113*H113) -> 0
A114: =E114&F114 -> Communicating Room Thermostat | B114: =IF(E114="","",VLOOKUP(A114,'Parts List'!A:E,5,FALSE)) -> Select Option | D114: =$D$106*I114 -> 0 | E114: Communicating Room Thermostat | H114: =IF(E114="","",VLOOKUP(A114,'Parts List'!A:F,6,FALSE)) -> 0 | I114: 0 | J114: =D114 -> 0 | K114: =D114*50 -> 0 | M114: =IF(H114="","",D114*H114) -> 0
...

Sheet Estimate 5
B1: =Totals!B1 -> ESTIMATING SHEET VERSION 8.6 | G1: Salesman: | H1: =Totals!H1 -> 0 | L1: 1 | N1: <- 1=Page Used, 0=Page not used
B2: Job Name: | C2: =Totals!C2 -> 0 | G2: Estimator: | H2: =Totals!H2 -> 0 | L2: =Totals!L2 -> 0
B3: Part Number | D3: QTY. | E3: MATERIAL DESCRIPTON | H3: LIST $ | J3: # of Contrs | K3: # of Points | M3: TOTAL | R3: Electrical Price Check | V3: Tech | Z3: Graphics | AD3: Programming
D5: 0 | E5: VAV Boxes w Heat | F5: Option | I5: #/unit | N5: 1 | O5: Pts/VAV | P5: =D5*N5 -> 0 | Q5: points | R5: =P5*S5 -> 0 | S5: 550 | T5: per VAV | V5: =P5*W5 -> 0 | W5: 1 | X5: per VAV | Z5: =P5*AA5 -> 0 | AA5: 0.25 | AB5: per VAV | AD5: =P5*AE5 -> 0 | AE5: 0.25 | AF5: per VAV
A6: =E6&F6 -> ControllerOptimizer BACnet MSTP VAV Cntr w Act & VP, Bluetooth, 7 UIO, 5 SSR | B6: =IF(E6="","",VLOOKUP(A6,'Parts List'!A:E,5,FALSE)) -> VAA-VA75MB24NMC | D6: =$D$5*I6 -> 0 | E6: Controller | F6: Optimizer BACnet MSTP VAV Cntr w Act & VP, Bluetooth, 7 UIO, 5 SSR | H6: =IF(E6="","",VLOOKUP(A6,'Parts List'!A:F,6,FALSE)) -> 281.3558 | I6: 1 | J6: =D6 -> 0 | K6: =D6*70 -> 0 | M6: =IF(H6="","",D6*H6) -> 0
A7: =E7&F7 -> Temp SensorTR100 Space with LCD | B7: =IF(E7="","",VLOOKUP(A7,'Parts List'!A:E,5,FALSE)) -> TR100-T-G | D7: =$D$5*I7 -> 0 | E7: Temp Sensor | F7: TR100 Space with LCD | H7: =IF(E7="","",VLOOKUP(A7,'Parts List'!A:F,6,FALSE)) -> 128.71265 | I7: 1 | M7: =IF(H7="","",D7*H7) -> 0
A8: =E8&F8 -> Temp SensorDuct Insertion Sensor | B8: =IF(E8="","",VLOOKUP(A8,'Parts List'!A:E,5,FALSE)) -> C7041B2005 | D8: =$D$5*I8 -> 0 | E8: Temp Sensor | F8: Duct Insertion Sensor | H8: =IF(E8="","",VLOOKUP(A8,'Parts List'!A:F,6,FALSE)) -> 23.18855 | I8: 1 | M8: =IF(H8="","",D8*H8) -> 0
A9: =E9&F9 -> Current SwDigital Status Switch | B9: =IF(E9="","",VLOOKUP(A9,'Parts List'!A:E,5,FALSE)) -> H600 | D9: =$D$5*I9 -> 0 | E9: Current Sw | F9: Digital Status Switch | H9: =IF(E9="","",VLOOKUP(A9,'Parts List'!A:F,6,FALSE)) -> 31.43 | I9: 0 | M9: =IF(H9="","",D9*H9) -> 0
A10: =E10&F10 -> RelayRIB Pilot Relay | B10: =IF(E10="","",VLOOKUP(A10,'Parts List'!A:E,5,FALSE)) -> RIBU1C | D10: =$D$5*I10 -> 0 | E10: Relay | F10: RIB Pilot Relay | H10: =IF(E10="","",VLOOKUP(A10,'Parts List'!A:F,6,FALSE)) -> 14.36 | I10: 0 | M10: =IF(H10="","",D10*H10) -> 0
A11: =E11&F11 -> VAV HW Valve 2W & 3-way NSR | B11: =IF(E11="","",VLOOKUP(A11,'Parts List'!A:E,5,FALSE)) -> N/A | D11: =$D$5*I11 -> 0 | E11: VAV HW Valve 2W & 3-way NSR | H11: 150 | I11: 0 | M11: =IF(H11="","",D11*H11) -> 0
A12: =E12&F12 -> Air Flow MonitorRetrofit Flow Ring for VAV Boxes | B12: =IF(E12="","",VLOOKUP(A12,'Parts List'!A:E,5,FALSE)) -> 36FMI | D12: =$D$5*I12 -> 0 | E12: Air Flow Monitor | F12: Retrofit Flow Ring for VAV Boxes | H12: =IF(E12="","",VLOOKUP(A12,'Parts List'!A:F,6,FALSE)) -> 95 | I12: 0 | M12: =IF(H12="","",D12*H12) -> 0
B13: =IF(E13="","",VLOOKUP(A13,'Parts List'!A:E,5,FALSE)) | H13: =IF(E13="","",VLOOKUP(A13,'Parts List'!A:F,6,FALSE)) | M13: =IF(H13="","",D13*H13)
A15: =E15&F15 -> Cooling Only VAV Boxes | D15: 0 | E15: Cooling Only VAV Boxes | I15: #/unit | N15: 1 | O15: Pts/VAV | P15: =D15*N15 -> 0 | Q15: points | R15: =P15*S15 -> 0 | S15: 550 | T15: per VAV | V15: =P15*W15 -> 0 | W15: 1 | X15: per VAV | Z15: =P15*AA15 -> 0 | AA15: 0.25 | AB15: per VAV | AD15: =P15*AE15 -> 0 | AE15: 0.25 | AF15: per VAV
A16: =E16&F16 -> ControllerOptimizer BACnet MSTP VAV Cntr w Act & VP, Bluetooth, 7 UIO, 5 SSR | B16: =IF(E16="","",VLOOKUP(A16,'Parts List'!A:E,5,FALSE)) -> VAA-VA75MB24NMC | D16: =$D$15*I16 -> 0 | E16: Controller | F16: Optimizer BACnet MSTP VAV Cntr w Act & VP, Bluetooth, 7 UIO, 5 SSR | H16: =IF(E16="","",VLOOKUP(A16,'Parts List'!A:F,6,FALSE)) -> 281.3558 | I16: 1 | J16: =D16 -> 0 | K16: =D16*70 -> 0 | M16: =IF(H16="","",D16*H16) -> 0
A17: =E17&F17 -> Temp SensorTR100 Space with LCD | B17: =IF(E17="","",VLOOKUP(A17,'Parts List'!A:E,5,FALSE)) -> TR100-T-G | D17: =$D$15*I17 -> 0 | E17: Temp Sensor | F17: TR100 Space with LCD | H17: =IF(E17="","",VLOOKUP(A17,'Parts List'!A:F,6,FALSE)) -> 128.71265 | I17: 1 | M17: =IF(H17="","",D17*H17) -> 0
A18: =E18&F18 -> Transformer40 VA | B18: =IF(E18="","",VLOOKUP(A18,'Parts List'!A:E,5,FALSE)) -> TR40VA001 | D18: =$D$15*I18 -> 0 | E18: Transformer | F18: 40 VA | H18: =IF(E18="","",VLOOKUP(A18,'Parts List'!A:F,6,FALSE)) -> 17.76 | I18: 0 | M18: =IF(H18="","",D18*H18) -> 0
A19: =E19&F19 -> Air Flow MonitorRetrofit Flow Ring for VAV Boxes | B19: =IF(E19="","",VLOOKUP(A19,'Parts List'!A:E,5,FALSE)) -> 36FMI | D19: =$D$15*I19 -> 0 | E19: Air Flow Monitor | F19: Retrofit Flow Ring for VAV Boxes | H19: =IF(E19="","",VLOOKUP(A19,'Parts List'!A:F,6,FALSE)) -> 95 | I19: 0 | M19: =IF(H19="","",D19*H19) -> 0
B20: =IF(E20="","",VLOOKUP(A20,'Parts List'!A:E,5,FALSE)) | H20: =IF(E20="","",VLOOKUP(A20,'Parts List'!A:F,6,FALSE)) | M20: =IF(H20="","",D20*H20)
D23: 0 | E23: Supply Air Boxes - CRC/Phoenix LV Wiring and Integration | I23: #/unit | N23: 1 | O23: Pts/VAV | P23: =D23*N23 -> 0 | Q23: points | R23: =P23*S23 -> 0 | S23: 750 | T23: per VAV | V23: =P23*W23 -> 0 | W23: 1 | X23: per VAV | Z23: =P23*AA23 -> 0 | AA23: 0.25 | AB23: per VAV | AD23: =P23*AE23 -> 0 | AE23: 0.25 | AF23: per VAV
A24: =E24&F24 | B24: =IF(E24="","",VLOOKUP(A24,'[2]Parts List'!A:E,5,FALSE)) | D24: =$D$23*I24 -> 0 | H24: =IF(E24="","",VLOOKUP(A24,'[2]Parts List'!A:F,6,FALSE)) | I24: 1 | J24: =D24 -> 0 | K24: =D24*50 -> 0 | M24: =IF(H24="","",D24*H24)
D27: 0 | E27: Exhaust Air Boxes - CRC/Phoenix LV Wiring and Integration | I27: #/unit | N27: 1 | O27: Pts/VAV | P27: =D27*N27 -> 0 | Q27: points | R27: =P27*S27 -> 0 | S27: 750 | T27: per VAV | V27: =P27*W27 -> 0 | W27: 1 | X27: per VAV | Z27: =P27*AA27 -> 0 | AA27: 0.25 | AB27: per VAV | AD27: =P27*AE27 -> 0 | AE27: 0.25 | AF27: per VAV
A28: =E28&F28 | B28: =IF(E28="","",VLOOKUP(A28,'[2]Parts List'!A:E,5,FALSE)) | D28: =$D$27*I28 -> 0 | H28: =IF(E28="","",VLOOKUP(A28,'[2]Parts List'!A:F,6,FALSE)) | I28: 1 | M28: =IF(H28="","",D28*H28)
D31: 0 | E31: Return Air Boxes - CRC/Phoenix LV Wiring and Integration | I31: #/unit | N31: 1 | O31: Pts/VAV | P31: =D31*N31 -> 0 | Q31: points | R31: =P31*S31 -> 0 | S31: 750 | T31: per VAV | V31: =P31*W31 -> 0 | W31: 1 | X31: per VAV | Z31: =P31*AA31 -> 0 | AA31: 0.25 | AB31: per VAV | AD31: =P31*AE31 -> 0 | AE31: 0.25 | AF31: per VAV
A32: =E32&F32 | B32: =IF(E32="","",VLOOKUP(A32,'[2]Parts List'!A:E,5,FALSE)) | D32: =$D$31*I32 -> 0 | H32: =IF(E32="","",VLOOKUP(A32,'[2]Parts List'!A:F,6,FALSE)) | I32: 1 | M32: =IF(H32="","",D32*H32)
D35: 0 | E35: OR Room Pressure Monitors - CRC/Phoenix LV Wiring and Integration | I35: #/unit | N35: 1 | O35: Pts/VAV | P35: =D35*N35 -> 0 | Q35: points | R35: =P35*S35 -> 0 | S35: 750 | T35: per VAV | V35: =P35*W35 -> 0 | W35: 1 | X35: per VAV | Z35: =P35*AA35 -> 0 | AA35: 0.25 | AB35: per VAV | AD35: =P35*AE35 -> 0 | AE35: 0.25 | AF35: per VAV
A36: =E36&F36 | B36: =IF(E36="","",VLOOKUP(A36,'[2]Parts List'!A:E,5,FALSE)) | D36: =$D$35*I36 -> 0 | H36: =IF(E36="","",VLOOKUP(A36,'[2]Parts List'!A:F,6,FALSE)) | I36: 1 | M36: =IF(H36="","",D36*H36)
A40: =E40&F40 -> Cooling Only VAV Box Transformers | D40: 0 | E40: Cooling Only VAV Box Transformers | I40: #/unit | N40: =SUM(I41:I43) -> 0 | O40: Pts/Unit | P40: =D40*N40 -> 0 | Q40: points | R40: =P40*S40 -> 0 | S40: 550 | T40: per Unit | V40: =P40*W40 -> 0 | W40: 0 | X40: per unit | Z40: =D40*AA40 -> 0 | AA40: 0 | AB40: per unit | AD40: =D40*AE40 -> 0 | AE40: 0 | AF40: per unit
A41: =E41&F41 -> Transformer(3) - 100 VA w Enclosure | B41: =IF(E41="","",VLOOKUP(A41,'Parts List'!A:E,5,FALSE)) -> PSH300A | D41: =$D$40*I41 -> 0 | E41: Transformer | F41: (3) - 100 VA w Enclosure | H41: =IF(E41="","",VLOOKUP(A41,'Parts List'!A:F,6,FALSE)) -> 314.8 | I41: 0 | M41: =IF(H41="","",D41*H41) -> 0
A42: =E42&F42 -> Transformer(5) - 100 VA w Enclosure | B42: =IF(E42="","",VLOOKUP(A42,'Parts List'!A:E,5,FALSE)) -> PSH500A | D42: =$D$40*I42 -> 0 | E42: Transformer | F42: (5) - 100 VA w Enclosure | H42: =IF(E42="","",VLOOKUP(A42,'Parts List'!A:F,6,FALSE)) -> 430.65 | I42: 0 | M42: =IF(H42="","",D42*H42) -> 0
A43: =E43&F43 | B43: =IF(E43="","",VLOOKUP(A43,'Parts List'!A:E,5,FALSE)) | D43: =$D$40*I43 -> 0 | H43: =IF(E43="","",VLOOKUP(A43,'Parts List'!A:F,6,FALSE)) | I43: 0 | M43: =IF(H43="","",D43*H43)
B44: =IF(E44="","",VLOOKUP(A44,'Parts List'!A:E,5,FALSE)) | H44: =IF(E44="","",VLOOKUP(A44,'Parts List'!A:F,6,FALSE)) | M44: =IF(H44="","",D44*H44)
A46: =E46&F46 -> VAV Air Handling Unit | D46: 0 | E46: VAV Air Handling Unit | I46: #/unit | N46: =SUM(I57:I73)+I52 -> 1 | O46: Pts/Unit | P46: =D46*N46 -> 0 | Q46: points | R46: =P46*S46 -> 0 | S46: 350 | T46: per point | V46: =P46*W46 -> 0 | W46: 1 | X46: per point | Z46: =D46*AA46 -> 0 | AA46: 4 | AB46: per unit | AD46: =D46*AE46 -> 0 | AE46: 6 | AF46: per unit
A47: =E47&F47 -> ControllerOptimizer Plant Cntr, 1 IP, 3 Ethernet Switched+4 RS485 Ports | B47: =IF(E47="","",VLOOKUP(A47,'Parts List'!A:E,5,FALSE)) -> N-ADV-134-H-C | D47: =$D$46*I47 -> 0 | E47: Controller | F47: Optimizer Plant Cntr, 1 IP, 3 Ethernet Switched+4 RS485 Ports | H47: =IF(E47="","",VLOOKUP(A47,'Parts List'!A:F,6,FALSE)) -> 875.1457 | I47: 0 | J47: =D47 -> 0 | K47: =D47*70 -> 0 | M47: =IF(H47="","",D47*H47) -> 0
A48: =E48&F48 -> Optimizer License with 18 Month SMA | B48: =IF(E48="","",VLOOKUP(A48,'Parts List'!A:E,5,FALSE)) -> Select Option | D48: =$D$46*I48 -> 0 | E48: Optimizer License with 18 Month SMA | H48: =IF(E48="","",VLOOKUP(A48,'Parts List'!A:F,6,FALSE)) -> 0 | I48: 0 | J48: =D48 -> 0 | K48: =D48*70 -> 0 | M48: =IF(H48="","",D48*H48) -> 0
A49: =E49&F49 -> I/O ModuleOptimzer Unitary Cntr 5-UI, 5-DI, 4-AO, 4-DO I/O Module | B49: =IF(E49="","",VLOOKUP(A49,'Parts List'!A:E,5,FALSE)) -> ISMA-B-MIX18 | D49: =$D$46*I49 -> 0 | E49: I/O Module | F49: Optimzer Unitary Cntr 5-UI, 5-DI, 4-AO, 4-DO I/O Module | H49: =IF(E49="","",VLOOKUP(A49,'Parts List'!A:F,6,FALSE)) -> 338.81 | I49: 0 | M49: =IF(H49="","",D49*H49) -> 0
A50: =E50&F50 -> Phoenix Controller Core License | B50: =IF(E50="","",VLOOKUP(A50,'Parts List'!A:E,5,FALSE)) -> Select Option | D50: =$D$46*I50 -> 0 | E50: Phoenix Controller Core License | H50: =IF(E50="","",VLOOKUP(A50,'Parts List'!A:F,6,FALSE)) -> 0 | I50: 0 | M50: =IF(H50="","",D50*H50) -> 0
A51: =E51&F51 -> Phoenix ILC SMA | B51: =IF(E51="","",VLOOKUP(A51,'Parts List'!A:E,5,FALSE)) -> Select Option | D51: =$D$46*I51 -> 0 | E51: Phoenix ILC SMA | H51: =IF(E51="","",VLOOKUP(A51,'Parts List'!A:F,6,FALSE)) -> 0 | I51: 0 | M51: =IF(H51="","",D51*H51) -> 0
A52: =E52&F52 -> Panel - Enclosure w SubpanelNema-1 Medium | B52: =IF(E52="","",VLOOKUP(A52,'Parts List'!A:E,5,FALSE)) -> RET1-262007BT-P | D52: =$D$46*I52 -> 0 | E52: Panel - Enclosure w Subpanel | F52: Nema-1 Medium | H52: =IF(E52="","",VLOOKUP(A52,'Parts List'!A:F,6,FALSE)) -> 436.83 | I52: 0 | M52: =IF(H52="","",D52*H52) -> 0
A53: =E53&F53 -> Relay24VAC DPDT with Base | B53: =IF(E53="","",VLOOKUP(A53,'Parts List'!A:E,5,FALSE)) -> RH2B-UAC24 + SH2B-05 | D53: =$D$46*I53 -> 0 | E53: Relay | F53: 24VAC DPDT with Base | H53: =IF(E53="","",VLOOKUP(A53,'Parts List'!A:F,6,FALSE)) -> 8.12 | I53: 0 | M53: =IF(H53="","",D53*H53) -> 0
A54: =E54&F54 -> Transformer75 VA with circuit breaker | B54: =IF(E54="","",VLOOKUP(A54,'Parts List'!A:E,5,FALSE)) -> TR75VA004 | D54: =$D$46*I54 -> 0 | E54: Transformer | F54: 75 VA with circuit breaker | H54: =IF(E54="","",VLOOKUP(A54,'Parts List'!A:F,6,FALSE)) -> 42.14 | I54: 0 | M54: =IF(H54="","",D54*H54) -> 0
A55: =E55&F55 -> Power Supply24VDC Panel Mounted - 1.3 A | B55: =IF(E55="","",VLOOKUP(A55,'Parts List'!A:E,5,FALSE)) -> PS5R-VB24 | D55: =$D$46*I55 -> 0 | E55: Power Supply | F55: 24VDC Panel Mounted - 1.3 A | H55: =IF(E55="","",VLOOKUP(A55,'Parts List'!A:F,6,FALSE)) -> 50.96 | I55: 0 | M55: =IF(H55="","",D55*H55) -> 0
A56: =E56&F56 -> Static Pressure TipsDuct Kit | B56: =IF(E56="","",VLOOKUP(A56,'Parts List'!A:E,5,FALSE)) -> A-302K + A-345k | D56: =$D$46*I56 -> 0 | E56: Static Pressure Tips | F56: Duct Kit | H56: =IF(E56="","",VLOOKUP(A56,'Parts List'!A:F,6,FALSE)) -> 17.9 | I56: 0 | M56: =IF(H56="","",D56*H56) -> 0
A57: =E57&F57 -> ThermostatLow Limit | B57: =IF(E57="","",VLOOKUP(A57,'Parts List'!A:E,5,FALSE)) -> A11A-1C | D57: =$D$46*I57 -> 0 | E57: Thermostat | F57: Low Limit | H57: =IF(E57="","",VLOOKUP(A57,'Parts List'!A:F,6,FALSE)) -> 270.31 | I57: 0 | M57: =IF(H57="","",D57*H57) -> 0
A58: =E58&F58 -> Filter StatusDigital Status | B58: =IF(E58="","",VLOOKUP(A58,'Parts List'!A:E,5,FALSE)) -> AFS-145 | D58: =$D$46*I58 -> 0 | E58: Filter Status | F58: Digital Status | H58: =IF(E58="","",VLOOKUP(A58,'Parts List'!A:F,6,FALSE)) -> 40.9 | I58: 0 | M58: =IF(H58="","",D58*H58) -> 0
A59: =E59&F59 -> Press TransmitterDuct Static Air | B59: =IF(E59="","",VLOOKUP(A59,'Parts List'!A:E,5,FALSE)) -> PX3DXX02 | D59: =$D$46*I59 -> 0 | E59: Press Transmitter | F59: Duct Static Air | H59: =IF(E59="","",VLOOKUP(A59,'Parts List'!A:F,6,FALSE)) -> 130.12 | I59: 0 | M59: =IF(H59="","",D59*H59) -> 0
A60: =E60&F60 -> Press Transmitter | B60: =IF(E60="","",VLOOKUP(A60,'Parts List'!A:E,5,FALSE)) -> Select Option | D60: =$D$46*I60 -> 0 | E60: Press Transmitter | H60: =IF(E60="","",VLOOKUP(A60,'Parts List'!A:F,6,FALSE)) -> 0 | I60: 0 | M60: =IF(H60="","",D60*H60) -> 0
A61: =E61&F61 -> Press TransmitterHigh Static Limit Switch | B61: =IF(E61="","",VLOOKUP(A61,'Parts List'!A:E,5,FALSE)) -> 1900-5-MR | D61: =$D$46*I61 -> 0 | E61: Press Transmitter | F61: High Static Limit Switch | H61: =IF(E61="","",VLOOKUP(A61,'Parts List'!A:F,6,FALSE)) -> 111.93 | I61: 0 | M61: =IF(H61="","",D61*H61) -> 0
A62: =E62&F62 -> Current SwDigital for VFD Status | B62: =IF(E62="","",VLOOKUP(A62,'Parts List'!A:E,5,FALSE)) -> H904 | D62: =$D$46*I62 -> 0 | E62: Current Sw | F62: Digital for VFD Status | H62: =IF(E62="","",VLOOKUP(A62,'Parts List'!A:F,6,FALSE)) -> 88.31 | I62: 0 | M62: =IF(H62="","",D62*H62) -> 0
A63: =E63&F63 -> Damper ActuatorLarge - Spring Return | B63: =IF(E63="","",VLOOKUP(A63,'Parts List'!A:E,5,FALSE)) -> MS7520A2007 | D63: =$D$46*I63 -> 0 | E63: Damper Actuator | F63: Large - Spring Return | H63: =IF(E63="","",VLOOKUP(A63,'Parts List'!A:F,6,FALSE)) -> 446.4658 | I63: 0 | M63: =IF(H63="","",D63*H63) -> 0
A64: =E64&F64 -> Temp SensorAveraging Sensor | B64: =IF(E64="","",VLOOKUP(A64,'Parts List'!A:E,5,FALSE)) -> C7041R2018 | D64: =$D$46*I64 -> 0 | E64: Temp Sensor | F64: Averaging Sensor | H64: =IF(E64="","",VLOOKUP(A64,'Parts List'!A:F,6,FALSE)) -> 166.9283 | I64: 0 | M64: =IF(H64="","",D64*H64) -> 0
A65: =E65&F65 -> Temp SensorDuct Temp/Humidity | B65: =IF(E65="","",VLOOKUP(A65,'Parts List'!A:E,5,FALSE)) -> H7735B2018 | D65: =$D$46*I65 -> 0 | E65: Temp Sensor | F65: Duct Temp/Humidity | H65: =IF(E65="","",VLOOKUP(A65,'Parts List'!A:F,6,FALSE)) -> 266.23465 | I65: 0 | M65: =IF(H65="","",D65*H65) -> 0
A66: =E66&F66 -> Humidity | B66: =IF(E66="","",VLOOKUP(A66,'Parts List'!A:E,5,FALSE)) -> Select Option | D66: =$D$46*I66 -> 0 | E66: Humidity | H66: =IF(E66="","",VLOOKUP(A66,'Parts List'!A:F,6,FALSE)) -> 0 | I66: 0 | M66: =IF(H66="","",D66*H66) -> 0
A67: =E67&F67 -> Humidity | B67: =IF(E67="","",VLOOKUP(A67,'Parts List'!A:E,5,FALSE)) -> Select Option | D67: =$D$46*I67 -> 0 | E67: Humidity | H67: =IF(E67="","",VLOOKUP(A67,'Parts List'!A:F,6,FALSE)) -> 0 | I67: 0 | M67: =IF(H67="","",D67*H67) -> 0
A68: =E68&F68 -> Carbon Dioxide SensorSpace CO2 wo LCD | B68: =IF(E68="","",VLOOKUP(A68,'Parts List'!A:E,5,FALSE)) -> C7263A1008 | D68: =$D$46*I68 -> 0 | E68: Carbon Dioxide Sensor | F68: Space CO2 wo LCD | H68: =IF(E68="","",VLOOKUP(A68,'Parts List'!A:F,6,FALSE)) -> 355.7389 | I68: 0 | M68: =IF(H68="","",D68*H68) -> 0
A69: =E69&F69 -> Carbon Dioxide SensorDuct CO2 wo LCD | B69: =IF(E69="","",VLOOKUP(A69,'Parts List'!A:E,5,FALSE)) -> C7632B1002 | D69: =$D$46*I69 -> 0 | E69: Carbon Dioxide Sensor | F69: Duct CO2 wo LCD | H69: =IF(E69="","",VLOOKUP(A69,'Parts List'!A:F,6,FALSE)) -> 331.2441 | I69: 0 | M69: =IF(H69="","",D69*H69) -> 0
A70: =E70&F70 -> Emergency Stop SwitchFlush Mtd | B70: =IF(E70="","",VLOOKUP(A70,'Parts List'!A:E,5,FALSE)) -> AOW401R + SSG1-67 | D70: =$D$46*I70 -> 0 | E70: Emergency Stop Switch | F70: Flush Mtd | H70: =IF(E70="","",VLOOKUP(A70,'Parts List'!A:F,6,FALSE)) -> 75.69 | I70: 0 | M70: =IF(H70="","",D70*H70) -> 0
A71: =E71&F71 -> Air Flow Monitor | B71: =IF(E71="","",VLOOKUP(A71,'Parts List'!A:E,5,FALSE)) -> Select Option | D71: =$D$46*I71 -> 0 | E71: Air Flow Monitor | H71: =IF(E71="","",VLOOKUP(A71,'Parts List'!A:F,6,FALSE)) -> 0 | I71: 0 | M71: =IF(H71="","",D71*H71) -> 0
A72: =E72&F72 -> See Valve Quote | B72: =IF(E72="","",VLOOKUP(A72,'Parts List'!A:E,5,FALSE)) -> N/A | D72: =$D$46*I72 -> 0 | E72: See Valve Quote | H72: =IF(E72="","",VLOOKUP(A72,'Parts List'!A:F,6,FALSE)) -> 0 | I72: 0 | M72: =IF(H72="","",D72*H72) -> 0
A73: =E73&F73 | B73: =IF(E73="","",VLOOKUP(A73,'Parts List'!A:E,5,FALSE)) | D73: =$D$46*I73 -> 0 | H73: =IF(E73="","",VLOOKUP(A73,'Parts List'!A:F,6,FALSE)) | I73: 1 | M73: =IF(H73="","",D73*H73) | N73: <- Duct Detector Interlock - Used for point count
A74: =E74&F74 | B74: =IF(E74="","",VLOOKUP(A74,'Parts List'!A:E,5,FALSE)) | D74: =$D$46*I74 -> 0 | H74: =IF(E74="","",VLOOKUP(A74,'Parts List'!A:F,6,FALSE)) | I74: 0 | M74: =IF(H74="","",D74*H74)
A75: =E75&F75 | B75: =IF(E75="","",VLOOKUP(A75,'Parts List'!A:E,5,FALSE)) | D75: =$D$46*I75 -> 0 | H75: =IF(E75="","",VLOOKUP(A75,'Parts List'!A:F,6,FALSE)) | I75: 0 | M75: =IF(H75="","",D75*H75)
A76: =E76&F76 | B76: =IF(E76="","",VLOOKUP(A76,'Parts List'!A:E,5,FALSE)) | H76: =IF(E76="","",VLOOKUP(A76,'Parts List'!A:F,6,FALSE)) | M76: =IF(H76="","",D76*H76)
A77: =E77&F77 -> Constant Volume Air Handling Units | D77: 0 | E77: Constant Volume Air Handling Units | I77: #/unit | N77: =SUM(I88:I102)+I83 -> 1 | O77: Pts/Unit | P77: =D77*N77 -> 0 | Q77: units | R77: =P77*S77 -> 0 | S77: 350 | T77: per point | V77: =P77*W77 -> 0 | W77: 1 | X77: per point | Z77: =D77*AA77 -> 0 | AA77: 4 | AB77: per unit | AD77: =D77*AE77 -> 0 | AE77: 6 | AF77: per unit
A78: =E78&F78 -> ControllerOptimizer Plant Cntr, 1 IP, 3 Ethernet Switched+4 RS485 Ports | B78: =IF(E78="","",VLOOKUP(A78,'Parts List'!A:E,5,FALSE)) -> N-ADV-134-H-C | D78: =$D$77*I78 -> 0 | E78: Controller | F78: Optimizer Plant Cntr, 1 IP, 3 Ethernet Switched+4 RS485 Ports | H78: =IF(E78="","",VLOOKUP(A78,'Parts List'!A:F,6,FALSE)) -> 875.1457 | I78: 0 | J78: =D78 -> 0 | K78: =D78*70 -> 0 | M78: =IF(H78="","",D78*H78) -> 0
A79: =E79&F79 -> Optimizer License with 18 Month SMA | B79: =IF(E79="","",VLOOKUP(A79,'Parts List'!A:E,5,FALSE)) -> Select Option | D79: =$D$77*I79 -> 0 | E79: Optimizer License with 18 Month SMA | H79: =IF(E79="","",VLOOKUP(A79,'Parts List'!A:F,6,FALSE)) -> 0 | I79: 0 | J79: =D79 -> 0 | K79: =D79*70 -> 0 | M79: =IF(H79="","",D79*H79) -> 0
A80: =E80&F80 -> I/O ModuleOptimzer Unitary Cntr 5-UI, 5-DI, 4-AO, 4-DO I/O Module | B80: =IF(E80="","",VLOOKUP(A80,'Parts List'!A:E,5,FALSE)) -> ISMA-B-MIX18 | D80: =$D$77*I80 -> 0 | E80: I/O Module | F80: Optimzer Unitary Cntr 5-UI, 5-DI, 4-AO, 4-DO I/O Module | H80: =IF(E80="","",VLOOKUP(A80,'Parts List'!A:F,6,FALSE)) -> 338.81 | I80: 0 | M80: =IF(H80="","",D80*H80) -> 0
A81: =E81&F81 -> Phoenix Controller Core License | B81: =IF(E81="","",VLOOKUP(A81,'Parts List'!A:E,5,FALSE)) -> Select Option | D81: =$D$77*I81 -> 0 | E81: Phoenix Controller Core License | H81: =IF(E81="","",VLOOKUP(A81,'Parts List'!A:F,6,FALSE)) -> 0 | I81: 0 | M81: =IF(H81="","",D81*H81) -> 0
A82: =E82&F82 -> Phoenix ILC SMA | B82: =IF(E82="","",VLOOKUP(A82,'Parts List'!A:E,5,FALSE)) -> Select Option | D82: =$D$77*I82 -> 0 | E82: Phoenix ILC SMA | H82: =IF(E82="","",VLOOKUP(A82,'Parts List'!A:F,6,FALSE)) -> 0 | I82: 0 | M82: =IF(H82="","",D82*H82) -> 0
A83: =E83&F83 -> Panel - Enclosure w SubpanelNema-1 Medium | B83: =IF(E83="","",VLOOKUP(A83,'Parts List'!A:E,5,FALSE)) -> RET1-262007BT-P | D83: =$D$77*I83 -> 0 | E83: Panel - Enclosure w Subpanel | F83: Nema-1 Medium | H83: =IF(E83="","",VLOOKUP(A83,'Parts List'!A:F,6,FALSE)) -> 436.83 | I83: 0 | M83: =IF(H83="","",D83*H83) -> 0
A84: =E84&F84 -> Relay24VAC DPDT with Base | B84: =IF(E84="","",VLOOKUP(A84,'Parts List'!A:E,5,FALSE)) -> RH2B-UAC24 + SH2B-05 | D84: =$D$77*I84 -> 0 | E84: Relay | F84: 24VAC DPDT with Base | H84: =IF(E84="","",VLOOKUP(A84,'Parts List'!A:F,6,FALSE)) -> 8.12 | I84: 0 | M84: =IF(H84="","",D84*H84) -> 0
A85: =E85&F85 -> Transformer75 VA with circuit breaker | B85: =IF(E85="","",VLOOKUP(A85,'Parts List'!A:E,5,FALSE)) -> TR75VA004 | D85: =$D$77*I85 -> 0 | E85: Transformer | F85: 75 VA with circuit breaker | H85: =IF(E85="","",VLOOKUP(A85,'Parts List'!A:F,6,FALSE)) -> 42.14 | I85: 0 | M85: =IF(H85="","",D85*H85) -> 0
A86: =E86&F86 -> Power Supply24VDC Panel Mounted - 1.3 A | B86: =IF(E86="","",VLOOKUP(A86,'Parts List'!A:E,5,FALSE)) -> PS5R-VB24 | D86: =$D$77*I86 -> 0 | E86: Power Supply | F86: 24VDC Panel Mounted - 1.3 A | H86: =IF(E86="","",VLOOKUP(A86,'Parts List'!A:F,6,FALSE)) -> 50.96 | I86: 0 | M86: =IF(H86="","",D86*H86) -> 0
A87: =E87&F87 -> Static Pressure TipsDuct Kit | B87: =IF(E87="","",VLOOKUP(A87,'Parts List'!A:E,5,FALSE)) -> A-302K + A-345k | D87: =$D$77*I87 -> 0 | E87: Static Pressure Tips | F87: Duct Kit | H87: =IF(E87="","",VLOOKUP(A87,'Parts List'!A:F,6,FALSE)) -> 17.9 | I87: 0 | M87: =IF(H87="","",D87*H87) -> 0
A88: =E88&F88 -> ThermostatLow Limit | B88: =IF(E88="","",VLOOKUP(A88,'Parts List'!A:E,5,FALSE)) -> A11A-1C | D88: =$D$77*I88 -> 0 | E88: Thermostat | F88: Low Limit | H88: =IF(E88="","",VLOOKUP(A88,'Parts List'!A:F,6,FALSE)) -> 270.31 | I88: 0 | M88: =IF(H88="","",D88*H88) -> 0
A89: =E89&F89 -> Filter StatusDigital Status | B89: =IF(E89="","",VLOOKUP(A89,'Parts List'!A:E,5,FALSE)) -> AFS-145 | D89: =$D$77*I89 -> 0 | E89: Filter Status | F89: Digital Status | H89: =IF(E89="","",VLOOKUP(A89,'Parts List'!A:F,6,FALSE)) -> 40.9 | I89: 0 | M89: =IF(H89="","",D89*H89) -> 0
A90: =E90&F90 -> Press TransmitterDuct Static Air | B90: =IF(E90="","",VLOOKUP(A90,'Parts List'!A:E,5,FALSE)) -> PX3DXX02 | D90: =$D$77*I90 -> 0 | E90: Press Transmitter | F90: Duct Static Air | H90: =IF(E90="","",VLOOKUP(A90,'Parts List'!A:F,6,FALSE)) -> 130.12 | I90: 0 | M90: =IF(H90="","",D90*H90) -> 0
A91: =E91&F91 -> Current SwDigital for VFD Status | B91: =IF(E91="","",VLOOKUP(A91,'Parts List'!A:E,5,FALSE)) -> H904 | D91: =$D$77*I91 -> 0 | E91: Current Sw | F91: Digital for VFD Status | H91: =IF(E91="","",VLOOKUP(A91,'Parts List'!A:F,6,FALSE)) -> 88.31 | I91: 0 | M91: =IF(H91="","",D91*H91) -> 0
A92: =E92&F92 -> Damper ActuatorLarge - Spring Return | B92: =IF(E92="","",VLOOKUP(A92,'Parts List'!A:E,5,FALSE)) -> MS7520A2007 | D92: =$D$77*I92 -> 0 | E92: Damper Actuator | F92: Large - Spring Return | H92: =IF(E92="","",VLOOKUP(A92,'Parts List'!A:F,6,FALSE)) -> 446.4658 | I92: 0 | M92: =IF(H92="","",D92*H92) -> 0
A93: =E93&F93 -> Temp SensorAveraging Sensor | B93: =IF(E93="","",VLOOKUP(A93,'Parts List'!A:E,5,FALSE)) -> C7041R2018 | D93: =$D$77*I93 -> 0 | E93: Temp Sensor | F93: Averaging Sensor | H93: =IF(E93="","",VLOOKUP(A93,'Parts List'!A:F,6,FALSE)) -> 166.9283 | I93: 0 | M93: =IF(H93="","",D93*H93) -> 0
A94: =E94&F94 -> Temp SensorDuct Temp/Humidity | B94: =IF(E94="","",VLOOKUP(A94,'Parts List'!A:E,5,FALSE)) -> H7735B2018 | D94: =$D$77*I94 -> 0 | E94: Temp Sensor | F94: Duct Temp/Humidity | H94: =IF(E94="","",VLOOKUP(A94,'Parts List'!A:F,6,FALSE)) -> 266.23465 | I94: 0 | M94: =IF(H94="","",D94*H94) -> 0
A95: =E95&F95 -> Humidity | B95: =IF(E95="","",VLOOKUP(A95,'Parts List'!A:E,5,FALSE)) -> Select Option | D95: =$D$77*I95 -> 0 | E95: Humidity | H95: =IF(E95="","",VLOOKUP(A95,'Parts List'!A:F,6,FALSE)) -> 0 | I95: 0 | M95: =IF(H95="","",D95*H95) -> 0
A96: =E96&F96 -> Humidity | B96: =IF(E96="","",VLOOKUP(A96,'Parts List'!A:E,5,FALSE)) -> Select Option | D96: =$D$77*I96 -> 0 | E96: Humidity | H96: =IF(E96="","",VLOOKUP(A96,'Parts List'!A:F,6,FALSE)) -> 0 | I96: 0 | M96: =IF(H96="","",D96*H96) -> 0
A97: =E97&F97 -> Carbon Dioxide SensorSpace CO2 wo LCD | B97: =IF(E97="","",VLOOKUP(A97,'Parts List'!A:E,5,FALSE)) -> C7263A1008 | D97: =$D$77*I97 -> 0 | E97: Carbon Dioxide Sensor | F97: Space CO2 wo LCD | H97: =IF(E97="","",VLOOKUP(A97,'Parts List'!A:F,6,FALSE)) -> 355.7389 | I97: 0 | M97: =IF(H97="","",D97*H97) -> 0
A98: =E98&F98 -> Carbon Dioxide SensorDuct CO2 wo LCD | B98: =IF(E98="","",VLOOKUP(A98,'Parts List'!A:E,5,FALSE)) -> C7632B1002 | D98: =$D$77*I98 -> 0 | E98: Carbon Dioxide Sensor | F98: Duct CO2 wo LCD | H98: =IF(E98="","",VLOOKUP(A98,'Parts List'!A:F,6,FALSE)) -> 331.2441 | I98: 0 | M98: =IF(H98="","",D98*H98) -> 0
A99: =E99&F99 -> Emergency Stop SwitchFlush Mtd | B99: =IF(E99="","",VLOOKUP(A99,'Parts List'!A:E,5,FALSE)) -> AOW401R + SSG1-67 | D99: =$D$77*I99 -> 0 | E99: Emergency Stop Switch | F99: Flush Mtd | H99: =IF(E99="","",VLOOKUP(A99,'Parts List'!A:F,6,FALSE)) -> 75.69 | I99: 0 | M99: =IF(H99="","",D99*H99) -> 0
A100: =E100&F100 -> Air Flow Monitor | B100: =IF(E100="","",VLOOKUP(A100,'Parts List'!A:E,5,FALSE)) -> Select Option | D100: =$D$77*I100 -> 0 | E100: Air Flow Monitor | H100: =IF(E100="","",VLOOKUP(A100,'Parts List'!A:F,6,FALSE)) -> 0 | I100: 0 | M100: =IF(H100="","",D100*H100) -> 0
A101: =E101&F101 -> See Valve Quote | B101: =IF(E101="","",VLOOKUP(A101,'Parts List'!A:E,5,FALSE)) -> N/A | D101: =$D$77*I101 -> 0 | E101: See Valve Quote | H101: =IF(E101="","",VLOOKUP(A101,'Parts List'!A:F,6,FALSE)) -> 0 | I101: 0 | M101: =IF(H101="","",D101*H101) -> 0
A102: =E102&F102 | B102: =IF(E102="","",VLOOKUP(A102,'Parts List'!A:E,5,FALSE)) | D102: =$D$77*I102 -> 0 | H102: =IF(E102="","",VLOOKUP(A102,'Parts List'!A:F,6,FALSE)) | I102: 1 | M102: =IF(H102="","",D102*H102) | N102: <- Duct Detector Interlock - Used for point count
A103: =E103&F103 | B103: =IF(E103="","",VLOOKUP(A103,'Parts List'!A:E,5,FALSE)) | D103: =$D$77*I103 -> 0 | H103: =IF(E103="","",VLOOKUP(A103,'Parts List'!A:F,6,FALSE)) | I103: 0 | M103: =IF(H103="","",D103*H103)
A104: =E104&F104 | B104: =IF(E104="","",VLOOKUP(A104,'Parts List'!A:E,5,FALSE)) | D104: =$D$77*I104 -> 0 | H104: =IF(E104="","",VLOOKUP(A104,'Parts List'!A:F,6,FALSE)) | I104: 0 | M104: =IF(H104="","",D104*H104)
A105: =E105&F105 | B105: =IF(E105="","",VLOOKUP(A105,'Parts List'!A:E,5,FALSE)) | H105: =IF(E105="","",VLOOKUP(A105,'Parts List'!A:F,6,FALSE)) | M105: =IF(H105="","",D105*H105)
A106: =E106&F106 -> Water Source Heat Pumps | D106: 0 | E106: Water Source Heat Pumps | I106: #/unit | N106: =SUM(I112:I120)+I108 -> 0 | O106: Pts/Unit | P106: =D106*N106 -> 0 | Q106: units | R106: =D106*S106 -> 0 | S106: 1500 | T106: per unit | V106: =D106*W106 -> 0 | W106: 3 | X106: per unit | Z106: =D106*AA106 -> 0 | AA106: 1 | AB106: per unit | AD106: =D106*AE106 -> 0 | AE106: 1 | AF106: per unit
A107: =E107&F107 -> Controller | B107: =IF(E107="","",VLOOKUP(A107,'Parts List'!A:E,5,FALSE)) -> Select Option | D107: =$D$106*I107 -> 0 | E107: Controller | H107: =IF(E107="","",VLOOKUP(A107,'Parts List'!A:F,6,FALSE)) -> 0 | I107: 0 | J107: =D107 -> 0 | K107: =D107*70 -> 0 | M107: =IF(H107="","",D107*H107) -> 0
A108: =E108&F108 -> Panel - Enclosure w Subpanel | B108: =IF(E108="","",VLOOKUP(A108,'Parts List'!A:E,5,FALSE)) -> Select Option | D108: =$D$106*I108 -> 0 | E108: Panel - Enclosure w Subpanel | H108: =IF(E108="","",VLOOKUP(A108,'Parts List'!A:F,6,FALSE)) -> 0 | I108: 0 | M108: =IF(H108="","",D108*H108) -> 0
A109: =E109&F109 -> Relay | B109: =IF(E109="","",VLOOKUP(A109,'Parts List'!A:E,5,FALSE)) -> Select Option | D109: =$D$106*I109 -> 0 | E109: Relay | H109: =IF(E109="","",VLOOKUP(A109,'Parts List'!A:F,6,FALSE)) -> 0 | I109: 0 | M109: =IF(H109="","",D109*H109) -> 0
A110: =E110&F110 -> Transformer | B110: =IF(E110="","",VLOOKUP(A110,'Parts List'!A:E,5,FALSE)) -> Select Option | D110: =$D$106*I110 -> 0 | E110: Transformer | H110: =IF(E110="","",VLOOKUP(A110,'Parts List'!A:F,6,FALSE)) -> 0 | I110: 0 | M110: =IF(H110="","",D110*H110) -> 0
A111: =E111&F111 -> Static Pressure Tips | B111: =IF(E111="","",VLOOKUP(A111,'Parts List'!A:E,5,FALSE)) -> N/A | D111: =$D$106*I111 -> 0 | E111: Static Pressure Tips | H111: =IF(E111="","",VLOOKUP(A111,'Parts List'!A:F,6,FALSE)) -> 0 | I111: 0 | M111: =IF(H111="","",D111*H111) -> 0
A112: =E112&F112 -> Current Sw | B112: =IF(E112="","",VLOOKUP(A112,'Parts List'!A:E,5,FALSE)) -> Select Option | D112: =$D$106*I112 -> 0 | E112: Current Sw | H112: =IF(E112="","",VLOOKUP(A112,'Parts List'!A:F,6,FALSE)) -> 0 | I112: 0 | M112: =IF(H112="","",D112*H112) -> 0
A113: =E113&F113 -> Filter Status | B113: =IF(E113="","",VLOOKUP(A113,'Parts List'!A:E,5,FALSE)) -> Select Option | D113: =$D$106*I113 -> 0 | E113: Filter Status | H113: =IF(E113="","",VLOOKUP(A113,'Parts List'!A:F,6,FALSE)) -> 0 | I113: 0 | M113: =IF(H113="","",D113*H113) -> 0
A114: =E114&F114 -> Communicating Room Thermostat | B114: =IF(E114="","",VLOOKUP(A114,'Parts List'!A:E,5,FALSE)) -> Select Option | D114: =$D$106*I114 -> 0 | E114: Communicating Room Thermostat | H114: =IF(E114="","",VLOOKUP(A114,'Parts List'!A:F,6,FALSE)) -> 0 | I114: 0 | J114: =D114 -> 0 | K114: =D114*50 -> 0 | M114: =IF(H114="","",D114*H114) -> 0
...

Sheet Estimate 6
B1: =Totals!B1 -> ESTIMATING SHEET VERSION 8.6 | G1: Salesman: | H1: =Totals!H1 -> 0 | L1: 1 | N1: <- 1=Page Used, 0=Page not used
B2: Job Name: | C2: =Totals!C2 -> 0 | G2: Estimator: | H2: =Totals!H2 -> 0 | L2: =Totals!L2 -> 0
B3: Part Number | D3: QTY. | E3: MATERIAL DESCRIPTON | H3: LIST $ | J3: # of Contrs | K3: # of Points | M3: TOTAL | R3: Electrical Price Check | V3: Tech | Z3: Graphics | AD3: Programming
D5: 0 | E5: VAV Boxes w Heat | F5: Option | I5: #/unit | N5: 1 | O5: Pts/VAV | P5: =D5*N5 -> 0 | Q5: points | R5: =P5*S5 -> 0 | S5: 550 | T5: per VAV | V5: =P5*W5 -> 0 | W5: 1 | X5: per VAV | Z5: =P5*AA5 -> 0 | AA5: 0.25 | AB5: per VAV | AD5: =P5*AE5 -> 0 | AE5: 0.25 | AF5: per VAV
A6: =E6&F6 -> ControllerOptimizer BACnet MSTP VAV Cntr w Act & VP, Bluetooth, 7 UIO, 5 SSR | B6: =IF(E6="","",VLOOKUP(A6,'Parts List'!A:E,5,FALSE)) -> VAA-VA75MB24NMC | D6: =$D$5*I6 -> 0 | E6: Controller | F6: Optimizer BACnet MSTP VAV Cntr w Act & VP, Bluetooth, 7 UIO, 5 SSR | H6: =IF(E6="","",VLOOKUP(A6,'Parts List'!A:F,6,FALSE)) -> 281.3558 | I6: 1 | J6: =D6 -> 0 | K6: =D6*70 -> 0 | M6: =IF(H6="","",D6*H6) -> 0
A7: =E7&F7 -> Temp SensorTR100 Space with LCD | B7: =IF(E7="","",VLOOKUP(A7,'Parts List'!A:E,5,FALSE)) -> TR100-T-G | D7: =$D$5*I7 -> 0 | E7: Temp Sensor | F7: TR100 Space with LCD | H7: =IF(E7="","",VLOOKUP(A7,'Parts List'!A:F,6,FALSE)) -> 128.71265 | I7: 1 | M7: =IF(H7="","",D7*H7) -> 0
A8: =E8&F8 -> Temp SensorDuct Insertion Sensor | B8: =IF(E8="","",VLOOKUP(A8,'Parts List'!A:E,5,FALSE)) -> C7041B2005 | D8: =$D$5*I8 -> 0 | E8: Temp Sensor | F8: Duct Insertion Sensor | H8: =IF(E8="","",VLOOKUP(A8,'Parts List'!A:F,6,FALSE)) -> 23.18855 | I8: 1 | M8: =IF(H8="","",D8*H8) -> 0
A9: =E9&F9 -> Current SwDigital Status Switch | B9: =IF(E9="","",VLOOKUP(A9,'Parts List'!A:E,5,FALSE)) -> H600 | D9: =$D$5*I9 -> 0 | E9: Current Sw | F9: Digital Status Switch | H9: =IF(E9="","",VLOOKUP(A9,'Parts List'!A:F,6,FALSE)) -> 31.43 | I9: 0 | M9: =IF(H9="","",D9*H9) -> 0
A10: =E10&F10 -> RelayRIB Pilot Relay | B10: =IF(E10="","",VLOOKUP(A10,'Parts List'!A:E,5,FALSE)) -> RIBU1C | D10: =$D$5*I10 -> 0 | E10: Relay | F10: RIB Pilot Relay | H10: =IF(E10="","",VLOOKUP(A10,'Parts List'!A:F,6,FALSE)) -> 14.36 | I10: 0 | M10: =IF(H10="","",D10*H10) -> 0
A11: =E11&F11 -> VAV HW Valve 2W & 3-way NSR | B11: =IF(E11="","",VLOOKUP(A11,'Parts List'!A:E,5,FALSE)) -> N/A | D11: =$D$5*I11 -> 0 | E11: VAV HW Valve 2W & 3-way NSR | H11: 150 | I11: 0 | M11: =IF(H11="","",D11*H11) -> 0
A12: =E12&F12 -> Air Flow MonitorRetrofit Flow Ring for VAV Boxes | B12: =IF(E12="","",VLOOKUP(A12,'Parts List'!A:E,5,FALSE)) -> 36FMI | D12: =$D$5*I12 -> 0 | E12: Air Flow Monitor | F12: Retrofit Flow Ring for VAV Boxes | H12: =IF(E12="","",VLOOKUP(A12,'Parts List'!A:F,6,FALSE)) -> 95 | I12: 0 | M12: =IF(H12="","",D12*H12) -> 0
B13: =IF(E13="","",VLOOKUP(A13,'Parts List'!A:E,5,FALSE)) | H13: =IF(E13="","",VLOOKUP(A13,'Parts List'!A:F,6,FALSE)) | M13: =IF(H13="","",D13*H13)
A15: =E15&F15 -> Cooling Only VAV Boxes | D15: 0 | E15: Cooling Only VAV Boxes | I15: #/unit | N15: 1 | O15: Pts/VAV | P15: =D15*N15 -> 0 | Q15: points | R15: =P15*S15 -> 0 | S15: 550 | T15: per VAV | V15: =P15*W15 -> 0 | W15: 1 | X15: per VAV | Z15: =P15*AA15 -> 0 | AA15: 0.25 | AB15: per VAV | AD15: =P15*AE15 -> 0 | AE15: 0.25 | AF15: per VAV
A16: =E16&F16 -> ControllerOptimizer BACnet MSTP VAV Cntr w Act & VP, Bluetooth, 7 UIO, 5 SSR | B16: =IF(E16="","",VLOOKUP(A16,'Parts List'!A:E,5,FALSE)) -> VAA-VA75MB24NMC | D16: =$D$15*I16 -> 0 | E16: Controller | F16: Optimizer BACnet MSTP VAV Cntr w Act & VP, Bluetooth, 7 UIO, 5 SSR | H16: =IF(E16="","",VLOOKUP(A16,'Parts List'!A:F,6,FALSE)) -> 281.3558 | I16: 1 | J16: =D16 -> 0 | K16: =D16*70 -> 0 | M16: =IF(H16="","",D16*H16) -> 0
A17: =E17&F17 -> Temp SensorTR100 Space with LCD | B17: =IF(E17="","",VLOOKUP(A17,'Parts List'!A:E,5,FALSE)) -> TR100-T-G | D17: =$D$15*I17 -> 0 | E17: Temp Sensor | F17: TR100 Space with LCD | H17: =IF(E17="","",VLOOKUP(A17,'Parts List'!A:F,6,FALSE)) -> 128.71265 | I17: 1 | M17: =IF(H17="","",D17*H17) -> 0
A18: =E18&F18 -> Transformer40 VA | B18: =IF(E18="","",VLOOKUP(A18,'Parts List'!A:E,5,FALSE)) -> TR40VA001 | D18: =$D$15*I18 -> 0 | E18: Transformer | F18: 40 VA | H18: =IF(E18="","",VLOOKUP(A18,'Parts List'!A:F,6,FALSE)) -> 17.76 | I18: 0 | M18: =IF(H18="","",D18*H18) -> 0
A19: =E19&F19 -> Air Flow MonitorRetrofit Flow Ring for VAV Boxes | B19: =IF(E19="","",VLOOKUP(A19,'Parts List'!A:E,5,FALSE)) -> 36FMI | D19: =$D$15*I19 -> 0 | E19: Air Flow Monitor | F19: Retrofit Flow Ring for VAV Boxes | H19: =IF(E19="","",VLOOKUP(A19,'Parts List'!A:F,6,FALSE)) -> 95 | I19: 0 | M19: =IF(H19="","",D19*H19) -> 0
B20: =IF(E20="","",VLOOKUP(A20,'Parts List'!A:E,5,FALSE)) | H20: =IF(E20="","",VLOOKUP(A20,'Parts List'!A:F,6,FALSE)) | M20: =IF(H20="","",D20*H20)
D23: 0 | E23: Supply Air Boxes - CRC/Phoenix LV Wiring and Integration | I23: #/unit | N23: 1 | O23: Pts/VAV | P23: =D23*N23 -> 0 | Q23: points | R23: =P23*S23 -> 0 | S23: 750 | T23: per VAV | V23: =P23*W23 -> 0 | W23: 1 | X23: per VAV | Z23: =P23*AA23 -> 0 | AA23: 0.25 | AB23: per VAV | AD23: =P23*AE23 -> 0 | AE23: 0.25 | AF23: per VAV
A24: =E24&F24 | B24: =IF(E24="","",VLOOKUP(A24,'[2]Parts List'!A:E,5,FALSE)) | D24: =$D$23*I24 -> 0 | H24: =IF(E24="","",VLOOKUP(A24,'[2]Parts List'!A:F,6,FALSE)) | I24: 1 | J24: =D24 -> 0 | K24: =D24*50 -> 0 | M24: =IF(H24="","",D24*H24)
D27: 0 | E27: Exhaust Air Boxes - CRC/Phoenix LV Wiring and Integration | I27: #/unit | N27: 1 | O27: Pts/VAV | P27: =D27*N27 -> 0 | Q27: points | R27: =P27*S27 -> 0 | S27: 750 | T27: per VAV | V27: =P27*W27 -> 0 | W27: 1 | X27: per VAV | Z27: =P27*AA27 -> 0 | AA27: 0.25 | AB27: per VAV | AD27: =P27*AE27 -> 0 | AE27: 0.25 | AF27: per VAV
A28: =E28&F28 | B28: =IF(E28="","",VLOOKUP(A28,'[2]Parts List'!A:E,5,FALSE)) | D28: =$D$27*I28 -> 0 | H28: =IF(E28="","",VLOOKUP(A28,'[2]Parts List'!A:F,6,FALSE)) | I28: 1 | M28: =IF(H28="","",D28*H28)
D31: 0 | E31: Return Air Boxes - CRC/Phoenix LV Wiring and Integration | I31: #/unit | N31: 1 | O31: Pts/VAV | P31: =D31*N31 -> 0 | Q31: points | R31: =P31*S31 -> 0 | S31: 750 | T31: per VAV | V31: =P31*W31 -> 0 | W31: 1 | X31: per VAV | Z31: =P31*AA31 -> 0 | AA31: 0.25 | AB31: per VAV | AD31: =P31*AE31 -> 0 | AE31: 0.25 | AF31: per VAV
A32: =E32&F32 | B32: =IF(E32="","",VLOOKUP(A32,'[2]Parts List'!A:E,5,FALSE)) | D32: =$D$31*I32 -> 0 | H32: =IF(E32="","",VLOOKUP(A32,'[2]Parts List'!A:F,6,FALSE)) | I32: 1 | M32: =IF(H32="","",D32*H32)
D35: 0 | E35: OR Room Pressure Monitors - CRC/Phoenix LV Wiring and Integration | I35: #/unit | N35: 1 | O35: Pts/VAV | P35: =D35*N35 -> 0 | Q35: points | R35: =P35*S35 -> 0 | S35: 750 | T35: per VAV | V35: =P35*W35 -> 0 | W35: 1 | X35: per VAV | Z35: =P35*AA35 -> 0 | AA35: 0.25 | AB35: per VAV | AD35: =P35*AE35 -> 0 | AE35: 0.25 | AF35: per VAV
A36: =E36&F36 | B36: =IF(E36="","",VLOOKUP(A36,'[2]Parts List'!A:E,5,FALSE)) | D36: =$D$35*I36 -> 0 | H36: =IF(E36="","",VLOOKUP(A36,'[2]Parts List'!A:F,6,FALSE)) | I36: 1 | M36: =IF(H36="","",D36*H36)
A40: =E40&F40 -> Cooling Only VAV Box Transformers | D40: 0 | E40: Cooling Only VAV Box Transformers | I40: #/unit | N40: =SUM(I41:I43) -> 0 | O40: Pts/Unit | P40: =D40*N40 -> 0 | Q40: points | R40: =P40*S40 -> 0 | S40: 550 | T40: per Unit | V40: =P40*W40 -> 0 | W40: 0 | X40: per unit | Z40: =D40*AA40 -> 0 | AA40: 0 | AB40: per unit | AD40: =D40*AE40 -> 0 | AE40: 0 | AF40: per unit
A41: =E41&F41 -> Transformer(3) - 100 VA w Enclosure | B41: =IF(E41="","",VLOOKUP(A41,'Parts List'!A:E,5,FALSE)) -> PSH300A | D41: =$D$40*I41 -> 0 | E41: Transformer | F41: (3) - 100 VA w Enclosure | H41: =IF(E41="","",VLOOKUP(A41,'Parts List'!A:F,6,FALSE)) -> 314.8 | I41: 0 | M41: =IF(H41="","",D41*H41) -> 0
A42: =E42&F42 -> Transformer(5) - 100 VA w Enclosure | B42: =IF(E42="","",VLOOKUP(A42,'Parts List'!A:E,5,FALSE)) -> PSH500A | D42: =$D$40*I42 -> 0 | E42: Transformer | F42: (5) - 100 VA w Enclosure | H42: =IF(E42="","",VLOOKUP(A42,'Parts List'!A:F,6,FALSE)) -> 430.65 | I42: 0 | M42: =IF(H42="","",D42*H42) -> 0
A43: =E43&F43 | B43: =IF(E43="","",VLOOKUP(A43,'Parts List'!A:E,5,FALSE)) | D43: =$D$40*I43 -> 0 | H43: =IF(E43="","",VLOOKUP(A43,'Parts List'!A:F,6,FALSE)) | I43: 0 | M43: =IF(H43="","",D43*H43)
B44: =IF(E44="","",VLOOKUP(A44,'Parts List'!A:E,5,FALSE)) | H44: =IF(E44="","",VLOOKUP(A44,'Parts List'!A:F,6,FALSE)) | M44: =IF(H44="","",D44*H44)
A46: =E46&F46 -> VAV Air Handling Unit | D46: 0 | E46: VAV Air Handling Unit | I46: #/unit | N46: =SUM(I57:I73)+I52 -> 1 | O46: Pts/Unit | P46: =D46*N46 -> 0 | Q46: points | R46: =P46*S46 -> 0 | S46: 350 | T46: per point | V46: =P46*W46 -> 0 | W46: 1 | X46: per point | Z46: =D46*AA46 -> 0 | AA46: 4 | AB46: per unit | AD46: =D46*AE46 -> 0 | AE46: 6 | AF46: per unit
A47: =E47&F47 -> ControllerOptimizer Plant Cntr, 1 IP, 3 Ethernet Switched+4 RS485 Ports | B47: =IF(E47="","",VLOOKUP(A47,'Parts List'!A:E,5,FALSE)) -> N-ADV-134-H-C | D47: =$D$46*I47 -> 0 | E47: Controller | F47: Optimizer Plant Cntr, 1 IP, 3 Ethernet Switched+4 RS485 Ports | H47: =IF(E47="","",VLOOKUP(A47,'Parts List'!A:F,6,FALSE)) -> 875.1457 | I47: 0 | J47: =D47 -> 0 | K47: =D47*70 -> 0 | M47: =IF(H47="","",D47*H47) -> 0
A48: =E48&F48 -> Optimizer License with 18 Month SMA | B48: =IF(E48="","",VLOOKUP(A48,'Parts List'!A:E,5,FALSE)) -> Select Option | D48: =$D$46*I48 -> 0 | E48: Optimizer License with 18 Month SMA | H48: =IF(E48="","",VLOOKUP(A48,'Parts List'!A:F,6,FALSE)) -> 0 | I48: 0 | J48: =D48 -> 0 | K48: =D48*70 -> 0 | M48: =IF(H48="","",D48*H48) -> 0
A49: =E49&F49 -> I/O ModuleOptimzer Unitary Cntr 5-UI, 5-DI, 4-AO, 4-DO I/O Module | B49: =IF(E49="","",VLOOKUP(A49,'Parts List'!A:E,5,FALSE)) -> ISMA-B-MIX18 | D49: =$D$46*I49 -> 0 | E49: I/O Module | F49: Optimzer Unitary Cntr 5-UI, 5-DI, 4-AO, 4-DO I/O Module | H49: =IF(E49="","",VLOOKUP(A49,'Parts List'!A:F,6,FALSE)) -> 338.81 | I49: 0 | M49: =IF(H49="","",D49*H49) -> 0
A50: =E50&F50 -> Phoenix Controller Core License | B50: =IF(E50="","",VLOOKUP(A50,'Parts List'!A:E,5,FALSE)) -> Select Option | D50: =$D$46*I50 -> 0 | E50: Phoenix Controller Core License | H50: =IF(E50="","",VLOOKUP(A50,'Parts List'!A:F,6,FALSE)) -> 0 | I50: 0 | M50: =IF(H50="","",D50*H50) -> 0
A51: =E51&F51 -> Phoenix ILC SMA | B51: =IF(E51="","",VLOOKUP(A51,'Parts List'!A:E,5,FALSE)) -> Select Option | D51: =$D$46*I51 -> 0 | E51: Phoenix ILC SMA | H51: =IF(E51="","",VLOOKUP(A51,'Parts List'!A:F,6,FALSE)) -> 0 | I51: 0 | M51: =IF(H51="","",D51*H51) -> 0
A52: =E52&F52 -> Panel - Enclosure w SubpanelNema-1 Medium | B52: =IF(E52="","",VLOOKUP(A52,'Parts List'!A:E,5,FALSE)) -> RET1-262007BT-P | D52: =$D$46*I52 -> 0 | E52: Panel - Enclosure w Subpanel | F52: Nema-1 Medium | H52: =IF(E52="","",VLOOKUP(A52,'Parts List'!A:F,6,FALSE)) -> 436.83 | I52: 0 | M52: =IF(H52="","",D52*H52) -> 0
A53: =E53&F53 -> Relay24VAC DPDT with Base | B53: =IF(E53="","",VLOOKUP(A53,'Parts List'!A:E,5,FALSE)) -> RH2B-UAC24 + SH2B-05 | D53: =$D$46*I53 -> 0 | E53: Relay | F53: 24VAC DPDT with Base | H53: =IF(E53="","",VLOOKUP(A53,'Parts List'!A:F,6,FALSE)) -> 8.12 | I53: 0 | M53: =IF(H53="","",D53*H53) -> 0
A54: =E54&F54 -> Transformer75 VA with circuit breaker | B54: =IF(E54="","",VLOOKUP(A54,'Parts List'!A:E,5,FALSE)) -> TR75VA004 | D54: =$D$46*I54 -> 0 | E54: Transformer | F54: 75 VA with circuit breaker | H54: =IF(E54="","",VLOOKUP(A54,'Parts List'!A:F,6,FALSE)) -> 42.14 | I54: 0 | M54: =IF(H54="","",D54*H54) -> 0
A55: =E55&F55 -> Power Supply24VDC Panel Mounted - 1.3 A | B55: =IF(E55="","",VLOOKUP(A55,'Parts List'!A:E,5,FALSE)) -> PS5R-VB24 | D55: =$D$46*I55 -> 0 | E55: Power Supply | F55: 24VDC Panel Mounted - 1.3 A | H55: =IF(E55="","",VLOOKUP(A55,'Parts List'!A:F,6,FALSE)) -> 50.96 | I55: 0 | M55: =IF(H55="","",D55*H55) -> 0
A56: =E56&F56 -> Static Pressure TipsDuct Kit | B56: =IF(E56="","",VLOOKUP(A56,'Parts List'!A:E,5,FALSE)) -> A-302K + A-345k | D56: =$D$46*I56 -> 0 | E56: Static Pressure Tips | F56: Duct Kit | H56: =IF(E56="","",VLOOKUP(A56,'Parts List'!A:F,6,FALSE)) -> 17.9 | I56: 0 | M56: =IF(H56="","",D56*H56) -> 0
A57: =E57&F57 -> ThermostatLow Limit | B57: =IF(E57="","",VLOOKUP(A57,'Parts List'!A:E,5,FALSE)) -> A11A-1C | D57: =$D$46*I57 -> 0 | E57: Thermostat | F57: Low Limit | H57: =IF(E57="","",VLOOKUP(A57,'Parts List'!A:F,6,FALSE)) -> 270.31 | I57: 0 | M57: =IF(H57="","",D57*H57) -> 0
A58: =E58&F58 -> Filter StatusDigital Status | B58: =IF(E58="","",VLOOKUP(A58,'Parts List'!A:E,5,FALSE)) -> AFS-145 | D58: =$D$46*I58 -> 0 | E58: Filter Status | F58: Digital Status | H58: =IF(E58="","",VLOOKUP(A58,'Parts List'!A:F,6,FALSE)) -> 40.9 | I58: 0 | M58: =IF(H58="","",D58*H58) -> 0
A59: =E59&F59 -> Press TransmitterDuct Static Air | B59: =IF(E59="","",VLOOKUP(A59,'Parts List'!A:E,5,FALSE)) -> PX3DXX02 | D59: =$D$46*I59 -> 0 | E59: Press Transmitter | F59: Duct Static Air | H59: =IF(E59="","",VLOOKUP(A59,'Parts List'!A:F,6,FALSE)) -> 130.12 | I59: 0 | M59: =IF(H59="","",D59*H59) -> 0
A60: =E60&F60 -> Press Transmitter | B60: =IF(E60="","",VLOOKUP(A60,'Parts List'!A:E,5,FALSE)) -> Select Option | D60: =$D$46*I60 -> 0 | E60: Press Transmitter | H60: =IF(E60="","",VLOOKUP(A60,'Parts List'!A:F,6,FALSE)) -> 0 | I60: 0 | M60: =IF(H60="","",D60*H60) -> 0
A61: =E61&F61 -> Press TransmitterHigh Static Limit Switch | B61: =IF(E61="","",VLOOKUP(A61,'Parts List'!A:E,5,FALSE)) -> 1900-5-MR | D61: =$D$46*I61 -> 0 | E61: Press Transmitter | F61: High Static Limit Switch | H61: =IF(E61="","",VLOOKUP(A61,'Parts List'!A:F,6,FALSE)) -> 111.93 | I61: 0 | M61: =IF(H61="","",D61*H61) -> 0
A62: =E62&F62 -> Current SwDigital for VFD Status | B62: =IF(E62="","",VLOOKUP(A62,'Parts List'!A:E,5,FALSE)) -> H904 | D62: =$D$46*I62 -> 0 | E62: Current Sw | F62: Digital for VFD Status | H62: =IF(E62="","",VLOOKUP(A62,'Parts List'!A:F,6,FALSE)) -> 88.31 | I62: 0 | M62: =IF(H62="","",D62*H62) -> 0
A63: =E63&F63 -> Damper ActuatorLarge - Spring Return | B63: =IF(E63="","",VLOOKUP(A63,'Parts List'!A:E,5,FALSE)) -> MS7520A2007 | D63: =$D$46*I63 -> 0 | E63: Damper Actuator | F63: Large - Spring Return | H63: =IF(E63="","",VLOOKUP(A63,'Parts List'!A:F,6,FALSE)) -> 446.4658 | I63: 0 | M63: =IF(H63="","",D63*H63) -> 0
A64: =E64&F64 -> Temp SensorAveraging Sensor | B64: =IF(E64="","",VLOOKUP(A64,'Parts List'!A:E,5,FALSE)) -> C7041R2018 | D64: =$D$46*I64 -> 0 | E64: Temp Sensor | F64: Averaging Sensor | H64: =IF(E64="","",VLOOKUP(A64,'Parts List'!A:F,6,FALSE)) -> 166.9283 | I64: 0 | M64: =IF(H64="","",D64*H64) -> 0
A65: =E65&F65 -> Temp SensorDuct Temp/Humidity | B65: =IF(E65="","",VLOOKUP(A65,'Parts List'!A:E,5,FALSE)) -> H7735B2018 | D65: =$D$46*I65 -> 0 | E65: Temp Sensor | F65: Duct Temp/Humidity | H65: =IF(E65="","",VLOOKUP(A65,'Parts List'!A:F,6,FALSE)) -> 266.23465 | I65: 0 | M65: =IF(H65="","",D65*H65) -> 0
A66: =E66&F66 -> Humidity | B66: =IF(E66="","",VLOOKUP(A66,'Parts List'!A:E,5,FALSE)) -> Select Option | D66: =$D$46*I66 -> 0 | E66: Humidity | H66: =IF(E66="","",VLOOKUP(A66,'Parts List'!A:F,6,FALSE)) -> 0 | I66: 0 | M66: =IF(H66="","",D66*H66) -> 0
A67: =E67&F67 -> Humidity | B67: =IF(E67="","",VLOOKUP(A67,'Parts List'!A:E,5,FALSE)) -> Select Option | D67: =$D$46*I67 -> 0 | E67: Humidity | H67: =IF(E67="","",VLOOKUP(A67,'Parts List'!A:F,6,FALSE)) -> 0 | I67: 0 | M67: =IF(H67="","",D67*H67) -> 0
A68: =E68&F68 -> Carbon Dioxide SensorSpace CO2 wo LCD | B68: =IF(E68="","",VLOOKUP(A68,'Parts List'!A:E,5,FALSE)) -> C7263A1008 | D68: =$D$46*I68 -> 0 | E68: Carbon Dioxide Sensor | F68: Space CO2 wo LCD | H68: =IF(E68="","",VLOOKUP(A68,'Parts List'!A:F,6,FALSE)) -> 355.7389 | I68: 0 | M68: =IF(H68="","",D68*H68) -> 0
A69: =E69&F69 -> Carbon Dioxide SensorDuct CO2 wo LCD | B69: =IF(E69="","",VLOOKUP(A69,'Parts List'!A:E,5,FALSE)) -> C7632B1002 | D69: =$D$46*I69 -> 0 | E69: Carbon Dioxide Sensor | F69: Duct CO2 wo LCD | H69: =IF(E69="","",VLOOKUP(A69,'Parts List'!A:F,6,FALSE)) -> 331.2441 | I69: 0 | M69: =IF(H69="","",D69*H69) -> 0
A70: =E70&F70 -> Emergency Stop SwitchFlush Mtd | B70: =IF(E70="","",VLOOKUP(A70,'Parts List'!A:E,5,FALSE)) -> AOW401R + SSG1-67 | D70: =$D$46*I70 -> 0 | E70: Emergency Stop Switch | F70: Flush Mtd | H70: =IF(E70="","",VLOOKUP(A70,'Parts List'!A:F,6,FALSE)) -> 75.69 | I70: 0 | M70: =IF(H70="","",D70*H70) -> 0
A71: =E71&F71 -> Air Flow Monitor | B71: =IF(E71="","",VLOOKUP(A71,'Parts List'!A:E,5,FALSE)) -> Select Option | D71: =$D$46*I71 -> 0 | E71: Air Flow Monitor | H71: =IF(E71="","",VLOOKUP(A71,'Parts List'!A:F,6,FALSE)) -> 0 | I71: 0 | M71: =IF(H71="","",D71*H71) -> 0
A72: =E72&F72 -> See Valve Quote | B72: =IF(E72="","",VLOOKUP(A72,'Parts List'!A:E,5,FALSE)) -> N/A | D72: =$D$46*I72 -> 0 | E72: See Valve Quote | H72: =IF(E72="","",VLOOKUP(A72,'Parts List'!A:F,6,FALSE)) -> 0 | I72: 0 | M72: =IF(H72="","",D72*H72) -> 0
A73: =E73&F73 | B73: =IF(E73="","",VLOOKUP(A73,'Parts List'!A:E,5,FALSE)) | D73: =$D$46*I73 -> 0 | H73: =IF(E73="","",VLOOKUP(A73,'Parts List'!A:F,6,FALSE)) | I73: 1 | M73: =IF(H73="","",D73*H73) | N73: <- Duct Detector Interlock - Used for point count
A74: =E74&F74 | B74: =IF(E74="","",VLOOKUP(A74,'Parts List'!A:E,5,FALSE)) | D74: =$D$46*I74 -> 0 | H74: =IF(E74="","",VLOOKUP(A74,'Parts List'!A:F,6,FALSE)) | I74: 0 | M74: =IF(H74="","",D74*H74)
A75: =E75&F75 | B75: =IF(E75="","",VLOOKUP(A75,'Parts List'!A:E,5,FALSE)) | D75: =$D$46*I75 -> 0 | H75: =IF(E75="","",VLOOKUP(A75,'Parts List'!A:F,6,FALSE)) | I75: 0 | M75: =IF(H75="","",D75*H75)
A76: =E76&F76 | B76: =IF(E76="","",VLOOKUP(A76,'Parts List'!A:E,5,FALSE)) | H76: =IF(E76="","",VLOOKUP(A76,'Parts List'!A:F,6,FALSE)) | M76: =IF(H76="","",D76*H76)
A77: =E77&F77 -> Constant Volume Air Handling Units | D77: 0 | E77: Constant Volume Air Handling Units | I77: #/unit | N77: =SUM(I88:I102)+I83 -> 1 | O77: Pts/Unit | P77: =D77*N77 -> 0 | Q77: units | R77: =P77*S77 -> 0 | S77: 350 | T77: per point | V77: =P77*W77 -> 0 | W77: 1 | X77: per point | Z77: =D77*AA77 -> 0 | AA77: 4 | AB77: per unit | AD77: =D77*AE77 -> 0 | AE77: 6 | AF77: per unit
A78: =E78&F78 -> ControllerOptimizer Plant Cntr, 1 IP, 3 Ethernet Switched+4 RS485 Ports | B78: =IF(E78="","",VLOOKUP(A78,'Parts List'!A:E,5,FALSE)) -> N-ADV-134-H-C | D78: =$D$77*I78 -> 0 | E78: Controller | F78: Optimizer Plant Cntr, 1 IP, 3 Ethernet Switched+4 RS485 Ports | H78: =IF(E78="","",VLOOKUP(A78,'Parts List'!A:F,6,FALSE)) -> 875.1457 | I78: 0 | J78: =D78 -> 0 | K78: =D78*70 -> 0 | M78: =IF(H78="","",D78*H78) -> 0
A79: =E79&F79 -> Optimizer License with 18 Month SMA | B79: =IF(E79="","",VLOOKUP(A79,'Parts List'!A:E,5,FALSE)) -> Select Option | D79: =$D$77*I79 -> 0 | E79: Optimizer License with 18 Month SMA | H79: =IF(E79="","",VLOOKUP(A79,'Parts List'!A:F,6,FALSE)) -> 0 | I79: 0 | J79: =D79 -> 0 | K79: =D79*70 -> 0 | M79: =IF(H79="","",D79*H79) -> 0
A80: =E80&F80 -> I/O ModuleOptimzer Unitary Cntr 5-UI, 5-DI, 4-AO, 4-DO I/O Module | B80: =IF(E80="","",VLOOKUP(A80,'Parts List'!A:E,5,FALSE)) -> ISMA-B-MIX18 | D80: =$D$77*I80 -> 0 | E80: I/O Module | F80: Optimzer Unitary Cntr 5-UI, 5-DI, 4-AO, 4-DO I/O Module | H80: =IF(E80="","",VLOOKUP(A80,'Parts List'!A:F,6,FALSE)) -> 338.81 | I80: 0 | M80: =IF(H80="","",D80*H80) -> 0
A81: =E81&F81 -> Phoenix Controller Core License | B81: =IF(E81="","",VLOOKUP(A81,'Parts List'!A:E,5,FALSE)) -> Select Option | D81: =$D$77*I81 -> 0 | E81: Phoenix Controller Core License | H81: =IF(E81="","",VLOOKUP(A81,'Parts List'!A:F,6,FALSE)) -> 0 | I81: 0 | M81: =IF(H81="","",D81*H81) -> 0
A82: =E82&F82 -> Phoenix ILC SMA | B82: =IF(E82="","",VLOOKUP(A82,'Parts List'!A:E,5,FALSE)) -> Select Option | D82: =$D$77*I82 -> 0 | E82: Phoenix ILC SMA | H82: =IF(E82="","",VLOOKUP(A82,'Parts List'!A:F,6,FALSE)) -> 0 | I82: 0 | M82: =IF(H82="","",D82*H82) -> 0
A83: =E83&F83 -> Panel - Enclosure w SubpanelNema-1 Medium | B83: =IF(E83="","",VLOOKUP(A83,'Parts List'!A:E,5,FALSE)) -> RET1-262007BT-P | D83: =$D$77*I83 -> 0 | E83: Panel - Enclosure w Subpanel | F83: Nema-1 Medium | H83: =IF(E83="","",VLOOKUP(A83,'Parts List'!A:F,6,FALSE)) -> 436.83 | I83: 0 | M83: =IF(H83="","",D83*H83) -> 0
A84: =E84&F84 -> Relay24VAC DPDT with Base | B84: =IF(E84="","",VLOOKUP(A84,'Parts List'!A:E,5,FALSE)) -> RH2B-UAC24 + SH2B-05 | D84: =$D$77*I84 -> 0 | E84: Relay | F84: 24VAC DPDT with Base | H84: =IF(E84="","",VLOOKUP(A84,'Parts List'!A:F,6,FALSE)) -> 8.12 | I84: 0 | M84: =IF(H84="","",D84*H84) -> 0
A85: =E85&F85 -> Transformer75 VA with circuit breaker | B85: =IF(E85="","",VLOOKUP(A85,'Parts List'!A:E,5,FALSE)) -> TR75VA004 | D85: =$D$77*I85 -> 0 | E85: Transformer | F85: 75 VA with circuit breaker | H85: =IF(E85="","",VLOOKUP(A85,'Parts List'!A:F,6,FALSE)) -> 42.14 | I85: 0 | M85: =IF(H85="","",D85*H85) -> 0
A86: =E86&F86 -> Power Supply24VDC Panel Mounted - 1.3 A | B86: =IF(E86="","",VLOOKUP(A86,'Parts List'!A:E,5,FALSE)) -> PS5R-VB24 | D86: =$D$77*I86 -> 0 | E86: Power Supply | F86: 24VDC Panel Mounted - 1.3 A | H86: =IF(E86="","",VLOOKUP(A86,'Parts List'!A:F,6,FALSE)) -> 50.96 | I86: 0 | M86: =IF(H86="","",D86*H86) -> 0
A87: =E87&F87 -> Static Pressure TipsDuct Kit | B87: =IF(E87="","",VLOOKUP(A87,'Parts List'!A:E,5,FALSE)) -> A-302K + A-345k | D87: =$D$77*I87 -> 0 | E87: Static Pressure Tips | F87: Duct Kit | H87: =IF(E87="","",VLOOKUP(A87,'Parts List'!A:F,6,FALSE)) -> 17.9 | I87: 0 | M87: =IF(H87="","",D87*H87) -> 0
A88: =E88&F88 -> ThermostatLow Limit | B88: =IF(E88="","",VLOOKUP(A88,'Parts List'!A:E,5,FALSE)) -> A11A-1C | D88: =$D$77*I88 -> 0 | E88: Thermostat | F88: Low Limit | H88: =IF(E88="","",VLOOKUP(A88,'Parts List'!A:F,6,FALSE)) -> 270.31 | I88: 0 | M88: =IF(H88="","",D88*H88) -> 0
A89: =E89&F89 -> Filter StatusDigital Status | B89: =IF(E89="","",VLOOKUP(A89,'Parts List'!A:E,5,FALSE)) -> AFS-145 | D89: =$D$77*I89 -> 0 | E89: Filter Status | F89: Digital Status | H89: =IF(E89="","",VLOOKUP(A89,'Parts List'!A:F,6,FALSE)) -> 40.9 | I89: 0 | M89: =IF(H89="","",D89*H89) -> 0
A90: =E90&F90 -> Press TransmitterDuct Static Air | B90: =IF(E90="","",VLOOKUP(A90,'Parts List'!A:E,5,FALSE)) -> PX3DXX02 | D90: =$D$77*I90 -> 0 | E90: Press Transmitter | F90: Duct Static Air | H90: =IF(E90="","",VLOOKUP(A90,'Parts List'!A:F,6,FALSE)) -> 130.12 | I90: 0 | M90: =IF(H90="","",D90*H90) -> 0
A91: =E91&F91 -> Current SwDigital for VFD Status | B91: =IF(E91="","",VLOOKUP(A91,'Parts List'!A:E,5,FALSE)) -> H904 | D91: =$D$77*I91 -> 0 | E91: Current Sw | F91: Digital for VFD Status | H91: =IF(E91="","",VLOOKUP(A91,'Parts List'!A:F,6,FALSE)) -> 88.31 | I91: 0 | M91: =IF(H91="","",D91*H91) -> 0
A92: =E92&F92 -> Damper ActuatorLarge - Spring Return | B92: =IF(E92="","",VLOOKUP(A92,'Parts List'!A:E,5,FALSE)) -> MS7520A2007 | D92: =$D$77*I92 -> 0 | E92: Damper Actuator | F92: Large - Spring Return | H92: =IF(E92="","",VLOOKUP(A92,'Parts List'!A:F,6,FALSE)) -> 446.4658 | I92: 0 | M92: =IF(H92="","",D92*H92) -> 0
A93: =E93&F93 -> Temp SensorAveraging Sensor | B93: =IF(E93="","",VLOOKUP(A93,'Parts List'!A:E,5,FALSE)) -> C7041R2018 | D93: =$D$77*I93 -> 0 | E93: Temp Sensor | F93: Averaging Sensor | H93: =IF(E93="","",VLOOKUP(A93,'Parts List'!A:F,6,FALSE)) -> 166.9283 | I93: 0 | M93: =IF(H93="","",D93*H93) -> 0
A94: =E94&F94 -> Temp SensorDuct Temp/Humidity | B94: =IF(E94="","",VLOOKUP(A94,'Parts List'!A:E,5,FALSE)) -> H7735B2018 | D94: =$D$77*I94 -> 0 | E94: Temp Sensor | F94: Duct Temp/Humidity | H94: =IF(E94="","",VLOOKUP(A94,'Parts List'!A:F,6,FALSE)) -> 266.23465 | I94: 0 | M94: =IF(H94="","",D94*H94) -> 0
A95: =E95&F95 -> Humidity | B95: =IF(E95="","",VLOOKUP(A95,'Parts List'!A:E,5,FALSE)) -> Select Option | D95: =$D$77*I95 -> 0 | E95: Humidity | H95: =IF(E95="","",VLOOKUP(A95,'Parts List'!A:F,6,FALSE)) -> 0 | I95: 0 | M95: =IF(H95="","",D95*H95) -> 0
A96: =E96&F96 -> Humidity | B96: =IF(E96="","",VLOOKUP(A96,'Parts List'!A:E,5,FALSE)) -> Select Option | D96: =$D$77*I96 -> 0 | E96: Humidity | H96: =IF(E96="","",VLOOKUP(A96,'Parts List'!A:F,6,FALSE)) -> 0 | I96: 0 | M96: =IF(H96="","",D96*H96) -> 0
A97: =E97&F97 -> Carbon Dioxide SensorSpace CO2 wo LCD | B97: =IF(E97="","",VLOOKUP(A97,'Parts List'!A:E,5,FALSE)) -> C7263A1008 | D97: =$D$77*I97 -> 0 | E97: Carbon Dioxide Sensor | F97: Space CO2 wo LCD | H97: =IF(E97="","",VLOOKUP(A97,'Parts List'!A:F,6,FALSE)) -> 355.7389 | I97: 0 | M97: =IF(H97="","",D97*H97) -> 0
A98: =E98&F98 -> Carbon Dioxide SensorDuct CO2 wo LCD | B98: =IF(E98="","",VLOOKUP(A98,'Parts List'!A:E,5,FALSE)) -> C7632B1002 | D98: =$D$77*I98 -> 0 | E98: Carbon Dioxide Sensor | F98: Duct CO2 wo LCD | H98: =IF(E98="","",VLOOKUP(A98,'Parts List'!A:F,6,FALSE)) -> 331.2441 | I98: 0 | M98: =IF(H98="","",D98*H98) -> 0
A99: =E99&F99 -> Emergency Stop SwitchFlush Mtd | B99: =IF(E99="","",VLOOKUP(A99,'Parts List'!A:E,5,FALSE)) -> AOW401R + SSG1-67 | D99: =$D$77*I99 -> 0 | E99: Emergency Stop Switch | F99: Flush Mtd | H99: =IF(E99="","",VLOOKUP(A99,'Parts List'!A:F,6,FALSE)) -> 75.69 | I99: 0 | M99: =IF(H99="","",D99*H99) -> 0
A100: =E100&F100 -> Air Flow Monitor | B100: =IF(E100="","",VLOOKUP(A100,'Parts List'!A:E,5,FALSE)) -> Select Option | D100: =$D$77*I100 -> 0 | E100: Air Flow Monitor | H100: =IF(E100="","",VLOOKUP(A100,'Parts List'!A:F,6,FALSE)) -> 0 | I100: 0 | M100: =IF(H100="","",D100*H100) -> 0
A101: =E101&F101 -> See Valve Quote | B101: =IF(E101="","",VLOOKUP(A101,'Parts List'!A:E,5,FALSE)) -> N/A | D101: =$D$77*I101 -> 0 | E101: See Valve Quote | H101: =IF(E101="","",VLOOKUP(A101,'Parts List'!A:F,6,FALSE)) -> 0 | I101: 0 | M101: =IF(H101="","",D101*H101) -> 0
A102: =E102&F102 | B102: =IF(E102="","",VLOOKUP(A102,'Parts List'!A:E,5,FALSE)) | D102: =$D$77*I102 -> 0 | H102: =IF(E102="","",VLOOKUP(A102,'Parts List'!A:F,6,FALSE)) | I102: 1 | M102: =IF(H102="","",D102*H102) | N102: <- Duct Detector Interlock - Used for point count
A103: =E103&F103 | B103: =IF(E103="","",VLOOKUP(A103,'Parts List'!A:E,5,FALSE)) | D103: =$D$77*I103 -> 0 | H103: =IF(E103="","",VLOOKUP(A103,'Parts List'!A:F,6,FALSE)) | I103: 0 | M103: =IF(H103="","",D103*H103)
A104: =E104&F104 | B104: =IF(E104="","",VLOOKUP(A104,'Parts List'!A:E,5,FALSE)) | D104: =$D$77*I104 -> 0 | H104: =IF(E104="","",VLOOKUP(A104,'Parts List'!A:F,6,FALSE)) | I104: 0 | M104: =IF(H104="","",D104*H104)
A105: =E105&F105 | B105: =IF(E105="","",VLOOKUP(A105,'Parts List'!A:E,5,FALSE)) | H105: =IF(E105="","",VLOOKUP(A105,'Parts List'!A:F,6,FALSE)) | M105: =IF(H105="","",D105*H105)
A106: =E106&F106 -> Water Source Heat Pumps | D106: 0 | E106: Water Source Heat Pumps | I106: #/unit | N106: =SUM(I112:I120)+I108 -> 0 | O106: Pts/Unit | P106: =D106*N106 -> 0 | Q106: units | R106: =D106*S106 -> 0 | S106: 1500 | T106: per unit | V106: =D106*W106 -> 0 | W106: 3 | X106: per unit | Z106: =D106*AA106 -> 0 | AA106: 1 | AB106: per unit | AD106: =D106*AE106 -> 0 | AE106: 1 | AF106: per unit
A107: =E107&F107 -> Controller | B107: =IF(E107="","",VLOOKUP(A107,'Parts List'!A:E,5,FALSE)) -> Select Option | D107: =$D$106*I107 -> 0 | E107: Controller | H107: =IF(E107="","",VLOOKUP(A107,'Parts List'!A:F,6,FALSE)) -> 0 | I107: 0 | J107: =D107 -> 0 | K107: =D107*70 -> 0 | M107: =IF(H107="","",D107*H107) -> 0
A108: =E108&F108 -> Panel - Enclosure w Subpanel | B108: =IF(E108="","",VLOOKUP(A108,'Parts List'!A:E,5,FALSE)) -> Select Option | D108: =$D$106*I108 -> 0 | E108: Panel - Enclosure w Subpanel | H108: =IF(E108="","",VLOOKUP(A108,'Parts List'!A:F,6,FALSE)) -> 0 | I108: 0 | M108: =IF(H108="","",D108*H108) -> 0
A109: =E109&F109 -> Relay | B109: =IF(E109="","",VLOOKUP(A109,'Parts List'!A:E,5,FALSE)) -> Select Option | D109: =$D$106*I109 -> 0 | E109: Relay | H109: =IF(E109="","",VLOOKUP(A109,'Parts List'!A:F,6,FALSE)) -> 0 | I109: 0 | M109: =IF(H109="","",D109*H109) -> 0
A110: =E110&F110 -> Transformer | B110: =IF(E110="","",VLOOKUP(A110,'Parts List'!A:E,5,FALSE)) -> Select Option | D110: =$D$106*I110 -> 0 | E110: Transformer | H110: =IF(E110="","",VLOOKUP(A110,'Parts List'!A:F,6,FALSE)) -> 0 | I110: 0 | M110: =IF(H110="","",D110*H110) -> 0
A111: =E111&F111 -> Static Pressure Tips | B111: =IF(E111="","",VLOOKUP(A111,'Parts List'!A:E,5,FALSE)) -> N/A | D111: =$D$106*I111 -> 0 | E111: Static Pressure Tips | H111: =IF(E111="","",VLOOKUP(A111,'Parts List'!A:F,6,FALSE)) -> 0 | I111: 0 | M111: =IF(H111="","",D111*H111) -> 0
A112: =E112&F112 -> Current Sw | B112: =IF(E112="","",VLOOKUP(A112,'Parts List'!A:E,5,FALSE)) -> Select Option | D112: =$D$106*I112 -> 0 | E112: Current Sw | H112: =IF(E112="","",VLOOKUP(A112,'Parts List'!A:F,6,FALSE)) -> 0 | I112: 0 | M112: =IF(H112="","",D112*H112) -> 0
A113: =E113&F113 -> Filter Status | B113: =IF(E113="","",VLOOKUP(A113,'Parts List'!A:E,5,FALSE)) -> Select Option | D113: =$D$106*I113 -> 0 | E113: Filter Status | H113: =IF(E113="","",VLOOKUP(A113,'Parts List'!A:F,6,FALSE)) -> 0 | I113: 0 | M113: =IF(H113="","",D113*H113) -> 0
A114: =E114&F114 -> Communicating Room Thermostat | B114: =IF(E114="","",VLOOKUP(A114,'Parts List'!A:E,5,FALSE)) -> Select Option | D114: =$D$106*I114 -> 0 | E114: Communicating Room Thermostat | H114: =IF(E114="","",VLOOKUP(A114,'Parts List'!A:F,6,FALSE)) -> 0 | I114: 0 | J114: =D114 -> 0 | K114: =D114*50 -> 0 | M114: =IF(H114="","",D114*H114) -> 0
...

Sheet Estimate 7
B1: =Totals!B1 -> ESTIMATING SHEET VERSION 8.6 | G1: Salesman: | H1: =Totals!H1 -> 0 | L1: 1 | N1: <- 1=Page Used, 0=Page not used
B2: Job Name: | C2: =Totals!C2 -> 0 | G2: Estimator: | H2: =Totals!H2 -> 0 | L2: =Totals!L2 -> 0
B3: Part Number | D3: QTY. | E3: MATERIAL DESCRIPTON | H3: LIST $ | J3: # of Contrs | K3: # of Points | M3: TOTAL | R3: Electrical Price Check | V3: Tech | Z3: Graphics | AD3: Programming
D5: 0 | E5: VAV Boxes w Heat | F5: Option | I5: #/unit | N5: 1 | O5: Pts/VAV | P5: =D5*N5 -> 0 | Q5: points | R5: =P5*S5 -> 0 | S5: 550 | T5: per VAV | V5: =P5*W5 -> 0 | W5: 1 | X5: per VAV | Z5: =P5*AA5 -> 0 | AA5: 0.25 | AB5: per VAV | AD5: =P5*AE5 -> 0 | AE5: 0.25 | AF5: per VAV
A6: =E6&F6 -> ControllerOptimizer BACnet MSTP VAV Cntr w Act & VP, Bluetooth, 7 UIO, 5 SSR | B6: =IF(E6="","",VLOOKUP(A6,'Parts List'!A:E,5,FALSE)) -> VAA-VA75MB24NMC | D6: =$D$5*I6 -> 0 | E6: Controller | F6: Optimizer BACnet MSTP VAV Cntr w Act & VP, Bluetooth, 7 UIO, 5 SSR | H6: =IF(E6="","",VLOOKUP(A6,'Parts List'!A:F,6,FALSE)) -> 281.3558 | I6: 1 | J6: =D6 -> 0 | K6: =D6*70 -> 0 | M6: =IF(H6="","",D6*H6) -> 0
A7: =E7&F7 -> Temp SensorTR100 Space with LCD | B7: =IF(E7="","",VLOOKUP(A7,'Parts List'!A:E,5,FALSE)) -> TR100-T-G | D7: =$D$5*I7 -> 0 | E7: Temp Sensor | F7: TR100 Space with LCD | H7: =IF(E7="","",VLOOKUP(A7,'Parts List'!A:F,6,FALSE)) -> 128.71265 | I7: 1 | M7: =IF(H7="","",D7*H7) -> 0
A8: =E8&F8 -> Temp SensorDuct Insertion Sensor | B8: =IF(E8="","",VLOOKUP(A8,'Parts List'!A:E,5,FALSE)) -> C7041B2005 | D8: =$D$5*I8 -> 0 | E8: Temp Sensor | F8: Duct Insertion Sensor | H8: =IF(E8="","",VLOOKUP(A8,'Parts List'!A:F,6,FALSE)) -> 23.18855 | I8: 1 | M8: =IF(H8="","",D8*H8) -> 0
A9: =E9&F9 -> Current SwDigital Status Switch | B9: =IF(E9="","",VLOOKUP(A9,'Parts List'!A:E,5,FALSE)) -> H600 | D9: =$D$5*I9 -> 0 | E9: Current Sw | F9: Digital Status Switch | H9: =IF(E9="","",VLOOKUP(A9,'Parts List'!A:F,6,FALSE)) -> 31.43 | I9: 0 | M9: =IF(H9="","",D9*H9) -> 0
A10: =E10&F10 -> RelayRIB Pilot Relay | B10: =IF(E10="","",VLOOKUP(A10,'Parts List'!A:E,5,FALSE)) -> RIBU1C | D10: =$D$5*I10 -> 0 | E10: Relay | F10: RIB Pilot Relay | H10: =IF(E10="","",VLOOKUP(A10,'Parts List'!A:F,6,FALSE)) -> 14.36 | I10: 0 | M10: =IF(H10="","",D10*H10) -> 0
A11: =E11&F11 -> VAV HW Valve 2W & 3-way NSR | B11: =IF(E11="","",VLOOKUP(A11,'Parts List'!A:E,5,FALSE)) -> N/A | D11: =$D$5*I11 -> 0 | E11: VAV HW Valve 2W & 3-way NSR | H11: 150 | I11: 0 | M11: =IF(H11="","",D11*H11) -> 0
A12: =E12&F12 -> Air Flow MonitorRetrofit Flow Ring for VAV Boxes | B12: =IF(E12="","",VLOOKUP(A12,'Parts List'!A:E,5,FALSE)) -> 36FMI | D12: =$D$5*I12 -> 0 | E12: Air Flow Monitor | F12: Retrofit Flow Ring for VAV Boxes | H12: =IF(E12="","",VLOOKUP(A12,'Parts List'!A:F,6,FALSE)) -> 95 | I12: 0 | M12: =IF(H12="","",D12*H12) -> 0
B13: =IF(E13="","",VLOOKUP(A13,'Parts List'!A:E,5,FALSE)) | H13: =IF(E13="","",VLOOKUP(A13,'Parts List'!A:F,6,FALSE)) | M13: =IF(H13="","",D13*H13)
A15: =E15&F15 -> Cooling Only VAV Boxes | D15: 0 | E15: Cooling Only VAV Boxes | I15: #/unit | N15: 1 | O15: Pts/VAV | P15: =D15*N15 -> 0 | Q15: points | R15: =P15*S15 -> 0 | S15: 550 | T15: per VAV | V15: =P15*W15 -> 0 | W15: 1 | X15: per VAV | Z15: =P15*AA15 -> 0 | AA15: 0.25 | AB15: per VAV | AD15: =P15*AE15 -> 0 | AE15: 0.25 | AF15: per VAV
A16: =E16&F16 -> ControllerOptimizer BACnet MSTP VAV Cntr w Act & VP, Bluetooth, 7 UIO, 5 SSR | B16: =IF(E16="","",VLOOKUP(A16,'Parts List'!A:E,5,FALSE)) -> VAA-VA75MB24NMC | D16: =$D$15*I16 -> 0 | E16: Controller | F16: Optimizer BACnet MSTP VAV Cntr w Act & VP, Bluetooth, 7 UIO, 5 SSR | H16: =IF(E16="","",VLOOKUP(A16,'Parts List'!A:F,6,FALSE)) -> 281.3558 | I16: 1 | J16: =D16 -> 0 | K16: =D16*70 -> 0 | M16: =IF(H16="","",D16*H16) -> 0
A17: =E17&F17 -> Temp SensorTR100 Space with LCD | B17: =IF(E17="","",VLOOKUP(A17,'Parts List'!A:E,5,FALSE)) -> TR100-T-G | D17: =$D$15*I17 -> 0 | E17: Temp Sensor | F17: TR100 Space with LCD | H17: =IF(E17="","",VLOOKUP(A17,'Parts List'!A:F,6,FALSE)) -> 128.71265 | I17: 1 | M17: =IF(H17="","",D17*H17) -> 0
A18: =E18&F18 -> Transformer40 VA | B18: =IF(E18="","",VLOOKUP(A18,'Parts List'!A:E,5,FALSE)) -> TR40VA001 | D18: =$D$15*I18 -> 0 | E18: Transformer | F18: 40 VA | H18: =IF(E18="","",VLOOKUP(A18,'Parts List'!A:F,6,FALSE)) -> 17.76 | I18: 0 | M18: =IF(H18="","",D18*H18) -> 0
A19: =E19&F19 -> Air Flow MonitorRetrofit Flow Ring for VAV Boxes | B19: =IF(E19="","",VLOOKUP(A19,'Parts List'!A:E,5,FALSE)) -> 36FMI | D19: =$D$15*I19 -> 0 | E19: Air Flow Monitor | F19: Retrofit Flow Ring for VAV Boxes | H19: =IF(E19="","",VLOOKUP(A19,'Parts List'!A:F,6,FALSE)) -> 95 | I19: 0 | M19: =IF(H19="","",D19*H19) -> 0
B20: =IF(E20="","",VLOOKUP(A20,'Parts List'!A:E,5,FALSE)) | H20: =IF(E20="","",VLOOKUP(A20,'Parts List'!A:F,6,FALSE)) | M20: =IF(H20="","",D20*H20)
D23: 0 | E23: Supply Air Boxes - CRC/Phoenix LV Wiring and Integration | I23: #/unit | N23: 1 | O23: Pts/VAV | P23: =D23*N23 -> 0 | Q23: points | R23: =P23*S23 -> 0 | S23: 750 | T23: per VAV | V23: =P23*W23 -> 0 | W23: 1 | X23: per VAV | Z23: =P23*AA23 -> 0 | AA23: 0.25 | AB23: per VAV | AD23: =P23*AE23 -> 0 | AE23: 0.25 | AF23: per VAV
A24: =E24&F24 | B24: =IF(E24="","",VLOOKUP(A24,'[2]Parts List'!A:E,5,FALSE)) | D24: =$D$23*I24 -> 0 | H24: =IF(E24="","",VLOOKUP(A24,'[2]Parts List'!A:F,6,FALSE)) | I24: 1 | J24: =D24 -> 0 | K24: =D24*50 -> 0 | M24: =IF(H24="","",D24*H24)
D27: 0 | E27: Exhaust Air Boxes - CRC/Phoenix LV Wiring and Integration | I27: #/unit | N27: 1 | O27: Pts/VAV | P27: =D27*N27 -> 0 | Q27: points | R27: =P27*S27 -> 0 | S27: 750 | T27: per VAV | V27: =P27*W27 -> 0 | W27: 1 | X27: per VAV | Z27: =P27*AA27 -> 0 | AA27: 0.25 | AB27: per VAV | AD27: =P27*AE27 -> 0 | AE27: 0.25 | AF27: per VAV
A28: =E28&F28 | B28: =IF(E28="","",VLOOKUP(A28,'[2]Parts List'!A:E,5,FALSE)) | D28: =$D$27*I28 -> 0 | H28: =IF(E28="","",VLOOKUP(A28,'[2]Parts List'!A:F,6,FALSE)) | I28: 1 | M28: =IF(H28="","",D28*H28)
D31: 0 | E31: Return Air Boxes - CRC/Phoenix LV Wiring and Integration | I31: #/unit | N31: 1 | O31: Pts/VAV | P31: =D31*N31 -> 0 | Q31: points | R31: =P31*S31 -> 0 | S31: 750 | T31: per VAV | V31: =P31*W31 -> 0 | W31: 1 | X31: per VAV | Z31: =P31*AA31 -> 0 | AA31: 0.25 | AB31: per VAV | AD31: =P31*AE31 -> 0 | AE31: 0.25 | AF31: per VAV
A32: =E32&F32 | B32: =IF(E32="","",VLOOKUP(A32,'[2]Parts List'!A:E,5,FALSE)) | D32: =$D$31*I32 -> 0 | H32: =IF(E32="","",VLOOKUP(A32,'[2]Parts List'!A:F,6,FALSE)) | I32: 1 | M32: =IF(H32="","",D32*H32)
D35: 0 | E35: OR Room Pressure Monitors - CRC/Phoenix LV Wiring and Integration | I35: #/unit | N35: 1 | O35: Pts/VAV | P35: =D35*N35 -> 0 | Q35: points | R35: =P35*S35 -> 0 | S35: 750 | T35: per VAV | V35: =P35*W35 -> 0 | W35: 1 | X35: per VAV | Z35: =P35*AA35 -> 0 | AA35: 0.25 | AB35: per VAV | AD35: =P35*AE35 -> 0 | AE35: 0.25 | AF35: per VAV
A36: =E36&F36 | B36: =IF(E36="","",VLOOKUP(A36,'[2]Parts List'!A:E,5,FALSE)) | D36: =$D$35*I36 -> 0 | H36: =IF(E36="","",VLOOKUP(A36,'[2]Parts List'!A:F,6,FALSE)) | I36: 1 | M36: =IF(H36="","",D36*H36)
